Workbook

Sheet Payroll Register
A2: PAYROLL REGISTER
A3: Payroll Period: | D3: ='Raw Sheet'!D2 -> 46023 | E3: ='Raw Sheet'!E2 -> 46037
A5: No. | C5: Name of Employees | D5: Monthly Basic Salary | E5: Semi-Monthly Basic Salary | F5: DE MINIMIS BENEFIT | L5: Other Non-Taxable Compensation | M5: Salary Adjustment | N5: Overtime | O5: NSD | P5: Absences / Tardiness | Q5: Holiday Pay | R5: Gross Compensation | S5: Gross Taxable Compensation | T5: Non-Taxable Compensation | U5: EMPLOYEE'S SHARE | Z5: Regular Net Taxable Compensation | AA5: Withholding Tax Computation | AF5: Withholding Tax Due | AG5: SSS Loan | AJ5: Advances to Employees | AK5: 2025 Tax Refund | AL5: Non-Taxable Compensation | AM5: NET PAY | AW5: Monthly Gross Compensation | AX5: SSS Contribution | AY5: PHIC Contribution | AZ5: HDMF Contribution
F6: YEAR END GIFTS | G6: Rice Subsidy | H6: Uniform/Clothing Allowance | I6: Laundry Allowance | J6: Meal Allowance | K6: Medical Allowance | AA6: Bracket | AB6: Basic | AC6: % | AD6: Basic | AE6: Excess | AG6: Salary | AH6: Calamity | AI6: HDMF Loan | AN6: EMPLOYER'S SHARE
U7: SSS - RSS | V7: SSS - WISP | W7: SSS - TOTAL | X7: PHIC | Y7: HDMF | AN7: SSS-RSS | AO7: SSS-EC | AP7: SSS-WISP | AQ7: SSS-TOTAL | AR7: PHIC | AS7: HDMF
A8: 1 | B8: 3 | C8: A | D8: =VLOOKUP(B8,'Raw Sheet'!$B$8:$G$28,6,FALSE) -> 37200 | E8: =D8/2 -> 18600 | F8: 0 | G8: =VLOOKUP(B8,'Raw Sheet'!$B$8:$L$28,11,FALSE)/2 -> 1000 | H8: =VLOOKUP(B8,'Raw Sheet'!$B$8:$M$28,12,FALSE)/2 -> 250 | I8: =VLOOKUP(B8,'Raw Sheet'!$B$8:$N$28,13,FALSE)/2 -> 150 | J8: 0 | K8: 0 | L8: 0 | M8: 0 | N8: ='Raw Sheet'!AH8+'Raw Sheet'!AL8 -> 0 | O8: =SUM('Raw Sheet'!AJ8,'Raw Sheet'!AP8,'Raw Sheet'!BB8,'Raw Sheet'!BH8) -> 256.55172 | P8: ='Raw Sheet'!BJ8 -> 0 | Q8: ='Raw Sheet'!BD8 -> 0 | R8: =E8+SUM(F8:Q8) -> 20256.552 | S8: =E8+SUM(M8:Q8) -> 18856.552 | T8: =SUM(F8:L8) -> 1400 | Z8: =S8-SUM(W8:Y8) -> 18856.552 | AA8: =IF(Z8>=333333,"333333",IF(Z8>=83333,"83333",IF(Z8>=33333,"33333",IF(Z8>=16667,"16667",IF(Z8>=10417,"10417",IF(Z8<10417,"0")))))) -> 16667 | AB8: =AA8+0 -> 16667 | AC8: =VLOOKUP(AB8,WTAX!E:F,2,0) -> 0.2 | AD8: =VLOOKUP(AB8,WTAX!E:G,3,0) -> 937.5 | AE8: =(Z8-AB8)*AC8 -> 437.91034 | AF8: =AD8+AE8 -> 1375.4103 | AG8: =VLOOKUP(B8,'Raw Sheet'!$B$8:$V$28,21,FALSE) -> 1845.8 | AH8: =VLOOKUP(B8,'Raw Sheet'!$B$8:$W$28,22,FALSE) -> 0 | AI8: =VLOOKUP(B8,'Raw Sheet'!$B$8:$X$28,23,FALSE) -> 0 | AJ8: =VLOOKUP(B8,'Raw Sheet'!$B$8:$Y$28,24,FALSE) -> 0 | AK8: =[1]Haguimit!$D$44 -> -0.00068965516 | AL8: =T8 -> 1400 | AM8: =Z8-SUM(AF8:AJ8)+SUM(AK8:AL8) -> 17035.341 | AN8: 0 | AO8: 0 | AP8: 0 | AQ8: 0 | AR8: 0 | AS8: 0 | AW8: =SUM(AU8:AV8) -> 0 | AX8: =AQ8+W8 -> 0 | AZ8: =SUM(Y8,AS8) -> 0
A9: 8 | B9: 17 | C9: B | D9: =VLOOKUP(B9,'Raw Sheet'!$B$8:$G$28,6,FALSE) -> 45000 | E9: =D9/2 -> 22500 | F9: 0 | G9: =VLOOKUP(B9,'Raw Sheet'!$B$8:$L$28,11,FALSE)/2 -> 0 | H9: =VLOOKUP(B9,'Raw Sheet'!$B$8:$M$28,12,FALSE)/2 -> 0 | I9: =VLOOKUP(B9,'Raw Sheet'!$B$8:$N$28,13,FALSE)/2 -> 0 | J9: 0 | K9: 0 | L9: 0 | M9: 0 | N9: ='Raw Sheet'!AH9+'Raw Sheet'!AL9 -> 2909.4828 | O9: =SUM('Raw Sheet'!AJ9,'Raw Sheet'!AP9,'Raw Sheet'!BB9,'Raw Sheet'!BH9) -> 879.31034 | P9: ='Raw Sheet'!BJ9 -> 0 | Q9: ='Raw Sheet'!BD9 -> 2068.9655 | R9: =E9+SUM(F9:Q9) -> 28357.759 | S9: =E9+SUM(M9:Q9) -> 28357.759 | T9: =SUM(F9:L9) -> 0 | Z9: =S9-SUM(W9:Y9) -> 28357.759 | AA9: =IF(Z9>=333333,"333333",IF(Z9>=83333,"83333",IF(Z9>=33333,"33333",IF(Z9>=16667,"16667",IF(Z9>=10417,"10417",IF(Z9<10417,"0")))))) -> 16667 | AB9: =AA9+0 -> 16667 | AC9: =VLOOKUP(AB9,WTAX!E:F,2,0) -> 0.2 | AD9: =VLOOKUP(AB9,WTAX!E:G,3,0) -> 937.5 | AE9: =(Z9-AB9)*AC9 -> 2338.1517 | AF9: =AD9+AE9 -> 3275.6517 | AG9: =VLOOKUP(B9,'Raw Sheet'!$B$8:$V$28,21,FALSE) -> 922.9 | AH9: =VLOOKUP(B9,'Raw Sheet'!$B$8:$W$28,22,FALSE) -> 0 | AI9: =VLOOKUP(B9,'Raw Sheet'!$B$8:$X$28,23,FALSE) -> 0 | AJ9: =VLOOKUP(B9,'Raw Sheet'!$B$8:$Y$28,24,FALSE) -> 0 | AK9: =[1]Viray!$D$44 -> -0.0037931035 | AL9: =T9 -> 0 | AM9: =Z9-SUM(AF9:AJ9)+SUM(AK9:AL9) -> 24159.203 | AN9: 0 | AO9: 0 | AP9: 0 | AQ9: 0 | AR9: 0 | AS9: 0 | AW9: =SUM(AU9:AV9) -> 0 | AX9: =AQ9+W9 -> 0 | AZ9: =SUM(Y9,AS9) -> 0
A10: 10 | B10: 21 | C10: C | D10: =VLOOKUP(B10,'Raw Sheet'!$B$8:$G$28,6,FALSE) -> 42000 | E10: =D10/2 -> 21000 | F10: 0 | G10: =VLOOKUP(B10,'Raw Sheet'!$B$8:$L$28,11,FALSE)/2 -> 1000 | H10: =VLOOKUP(B10,'Raw Sheet'!$B$8:$M$28,12,FALSE)/2 -> 50 | I10: =VLOOKUP(B10,'Raw Sheet'!$B$8:$N$28,13,FALSE)/2 -> 0 | J10: 0 | K10: 0 | L10: 0 | M10: 0 | N10: ='Raw Sheet'!AH10+'Raw Sheet'!AL10 -> 3620.6897 | O10: =SUM('Raw Sheet'!AJ10,'Raw Sheet'!AP10,'Raw Sheet'!BB10,'Raw Sheet'!BH10) -> 0 | P10: ='Raw Sheet'!BJ10 -> 0 | Q10: ='Raw Sheet'!BD10 -> 0 | R10: =E10+SUM(F10:Q10) -> 25670.69 | S10: =E10+SUM(M10:Q10) -> 24620.69 | T10: =SUM(F10:L10) -> 1050 | Z10: =S10-SUM(W10:Y10) -> 24620.69 | AA10: =IF(Z10>=333333,"333333",IF(Z10>=83333,"83333",IF(Z10>=33333,"33333",IF(Z10>=16667,"16667",IF(Z10>=10417,"10417",IF(Z10<10417,"0")))))) -> 16667 | AB10: =AA10+0 -> 16667 | AC10: =VLOOKUP(AB10,WTAX!E:F,2,0) -> 0.2 | AD10: =VLOOKUP(AB10,WTAX!E:G,3,0) -> 937.5 | AE10: =(Z10-AB10)*AC10 -> 1590.7379 | AF10: =AD10+AE10 -> 2528.2379 | AG10: =VLOOKUP(B10,'Raw Sheet'!$B$8:$V$28,21,FALSE) -> 922.9 | AH10: =VLOOKUP(B10,'Raw Sheet'!$B$8:$W$28,22,FALSE) -> 0 | AI10: =VLOOKUP(B10,'Raw Sheet'!$B$8:$X$28,23,FALSE) -> 0 | AJ10: =VLOOKUP(B10,'Raw Sheet'!$B$8:$Y$28,24,FALSE) -> 0 | AK10: =[1]Dy!$D$44 -> 0.0037931035 | AL10: =T10 -> 1050 | AM10: =Z10-SUM(AF10:AJ10)+SUM(AK10:AL10) -> 22219.556 | AN10: 0 | AO10: 0 | AP10: 0 | AQ10: 0 | AR10: 0 | AS10: 0 | AW10: =SUM(AU10:AV10) -> 0 | AX10: =AQ10+W10 -> 0 | AZ10: =SUM(Y10,AS10) -> 0
A11: 11 | B11: 23 | C11: D | D11: =VLOOKUP(B11,'Raw Sheet'!$B$8:$G$28,6,FALSE) -> 169600 | E11: =D11/2 -> 84800 | F11: 0 | G11: =VLOOKUP(B11,'Raw Sheet'!$B$8:$L$28,11,FALSE)/2 -> 1000 | H11: =VLOOKUP(B11,'Raw Sheet'!$B$8:$M$28,12,FALSE)/2 -> 250 | I11: =VLOOKUP(B11,'Raw Sheet'!$B$8:$N$28,13,FALSE)/2 -> 150 | J11: 0 | K11: 0 | L11: 0 | M11: 0 | N11: ='Raw Sheet'!AH11+'Raw Sheet'!AL11 -> 0 | O11: =SUM('Raw Sheet'!AJ11,'Raw Sheet'!AP11,'Raw Sheet'!BB11,'Raw Sheet'!BH11) -> 0 | P11: ='Raw Sheet'!BJ11 -> 0 | Q11: ='Raw Sheet'!BD11 -> 0 | R11: =E11+SUM(F11:Q11) -> 86200 | S11: =E11+SUM(M11:Q11) -> 84800 | T11: =SUM(F11:L11) -> 1400 | Z11: =S11-SUM(W11:Y11) -> 84800 | AA11: =IF(Z11>=333333,"333333",IF(Z11>=83333,"83333",IF(Z11>=33333,"33333",IF(Z11>=16667,"16667",IF(Z11>=10417,"10417",IF(Z11<10417,"0")))))) -> 83333 | AB11: =AA11+0 -> 83333 | AC11: =VLOOKUP(AB11,WTAX!E:F,2,0) -> 0.3 | AD11: =VLOOKUP(AB11,WTAX!E:G,3,0) -> 16770.7 | AE11: =(Z11-AB11)*AC11 -> 440.1 | AF11: =AD11+AE11 -> 17210.8 | AG11: =VLOOKUP(B11,'Raw Sheet'!$B$8:$V$28,21,FALSE) -> 0 | AH11: =VLOOKUP(B11,'Raw Sheet'!$B$8:$W$28,22,FALSE) -> 0 | AI11: =VLOOKUP(B11,'Raw Sheet'!$B$8:$X$28,23,FALSE) -> 0 | AJ11: =VLOOKUP(B11,'Raw Sheet'!$B$8:$Y$28,24,FALSE) -> 0 | AK11: =[1]Marquez!$D$44 -> 0 | AL11: =T11 -> 1400 | AM11: =Z11-SUM(AF11:AJ11)+SUM(AK11:AL11) -> 68989.2 | AN11: 0 | AO11: 0 | AP11: 0 | AQ11: 0 | AR11: 0 | AS11: 0 | AW11: =SUM(AU11:AV11) -> 0 | AX11: =AQ11+W11 -> 0 | AZ11: =SUM(Y11,AS11) -> 0
A12: 12 | B12: 25 | C12: E | D12: =VLOOKUP(B12,'Raw Sheet'!$B$8:$G$28,6,FALSE) -> 255600 | E12: =D12/2 -> 127800 | F12: 0 | G12: =VLOOKUP(B12,'Raw Sheet'!$B$8:$L$28,11,FALSE)/2 -> 1000 | H12: =VLOOKUP(B12,'Raw Sheet'!$B$8:$M$28,12,FALSE)/2 -> 250 | I12: =VLOOKUP(B12,'Raw Sheet'!$B$8:$N$28,13,FALSE)/2 -> 150 | J12: 0 | K12: 0 | L12: 0 | M12: 0 | N12: ='Raw Sheet'!AH12+'Raw Sheet'!AL12 -> 0 | O12: =SUM('Raw Sheet'!AJ12,'Raw Sheet'!AP12,'Raw Sheet'!BB12,'Raw Sheet'!BH12) -> 0 | P12: ='Raw Sheet'!BJ12 -> 0 | Q12: ='Raw Sheet'!BD12 -> 0 | R12: =E12+SUM(F12:Q12) -> 129200 | S12: =E12+SUM(M12:Q12) -> 127800 | T12: =SUM(F12:L12) -> 1400 | Z12: =S12-SUM(W12:Y12) -> 127800 | AA12: =IF(Z12>=333333,"333333",IF(Z12>=83333,"83333",IF(Z12>=33333,"33333",IF(Z12>=16667,"16667",IF(Z12>=10417,"10417",IF(Z12<10417,"0")))))) -> 83333 | AB12: =AA12+0 -> 83333 | AC12: =VLOOKUP(AB12,WTAX!E:F,2,0) -> 0.3 | AD12: =VLOOKUP(AB12,WTAX!E:G,3,0) -> 16770.7 | AE12: =(Z12-AB12)*AC12 -> 13340.1 | AF12: =AD12+AE12 -> 30110.8 | AG12: =VLOOKUP(B12,'Raw Sheet'!$B$8:$V$28,21,FALSE) -> 0 | AH12: =VLOOKUP(B12,'Raw Sheet'!$B$8:$W$28,22,FALSE) -> 0 | AI12: =VLOOKUP(B12,'Raw Sheet'!$B$8:$X$28,23,FALSE) -> 0 | AJ12: =VLOOKUP(B12,'Raw Sheet'!$B$8:$Y$28,24,FALSE) -> 41395.83 | AK12: =[1]Carreon!$D$44 -> 0 | AL12: =T12 -> 1400 | AM12: =Z12-SUM(AF12:AJ12)+SUM(AK12:AL12) -> 57693.37 | AN12: 0 | AO12: 0 | AP12: 0 | AQ12: 0 | AR12: 0 | AS12: 0 | AW12: =SUM(AU12:AV12) -> 0 | AX12: =AQ12+W12 -> 0 | AZ12: =SUM(Y12,AS12) -> 0
A13: 15 | B13: 31 | C13: F | D13: =VLOOKUP(B13,'Raw Sheet'!$B$8:$G$28,6,FALSE) -> 26000 | E13: =D13/2 -> 13000 | F13: 0 | G13: =VLOOKUP(B13,'Raw Sheet'!$B$8:$L$28,11,FALSE)/2 -> 780 | H13: =VLOOKUP(B13,'Raw Sheet'!$B$8:$M$28,12,FALSE)/2 -> 0 | I13: =VLOOKUP(B13,'Raw Sheet'!$B$8:$N$28,13,FALSE)/2 -> 0 | J13: 0 | K13: 0 | L13: 0 | M13: 0 | N13: ='Raw Sheet'!AH13+'Raw Sheet'!AL13 -> 0 | O13: =SUM('Raw Sheet'!AJ13,'Raw Sheet'!AP13,'Raw Sheet'!BB13,'Raw Sheet'!BH13) -> 0 | P13: ='Raw Sheet'!BJ13 -> 0 | Q13: ='Raw Sheet'!BD13 -> 1912.6437 | R13: =E13+SUM(F13:Q13) -> 15692.644 | S13: =E13+SUM(M13:Q13) -> 14912.644 | T13: =SUM(F13:L13) -> 780 | Z13: =S13-SUM(W13:Y13) -> 14912.644 | AA13: =IF(Z13>=333333,"333333",IF(Z13>=83333,"83333",IF(Z13>=33333,"33333",IF(Z13>=16667,"16667",IF(Z13>=10417,"10417",IF(Z13<10417,"0")))))) -> 10417 | AB13: =AA13+0 -> 10417 | AC13: =VLOOKUP(AB13,WTAX!E:F,2,0) -> 0.15 | AD13: =VLOOKUP(AB13,WTAX!E:G,3,0) -> 0 | AE13: =(Z13-AB13)*AC13 -> 674.34655 | AF13: =AD13+AE13 -> 674.34655 | AG13: =VLOOKUP(B13,'Raw Sheet'!$B$8:$V$28,21,FALSE) -> 0 | AH13: =VLOOKUP(B13,'Raw Sheet'!$B$8:$W$28,22,FALSE) -> 0 | AI13: =VLOOKUP(B13,'Raw Sheet'!$B$8:$X$28,23,FALSE) -> 0 | AJ13: =VLOOKUP(B13,'Raw Sheet'!$B$8:$Y$28,24,FALSE) -> 0 | AK13: =-[1]Colongan!$D$44 -> 4333.3366 | AL13: =T13 -> 780 | AM13: =Z13-SUM(AF13:AJ13)+SUM(AK13:AL13) -> 19351.634 | AN13: 0 | AO13: 0 | AP13: 0 | AQ13: 0 | AR13: 0 | AS13: 0 | AW13: =SUM(AU13:AV13) -> 0 | AX13: =AQ13+W13 -> 0 | AZ13: =SUM(Y13,AS13) -> 0
A14: 19 | B14: 39 | C14: G | D14: =VLOOKUP(B14,'Raw Sheet'!$B$8:$G$28,6,FALSE) -> 29680 | E14: =D14/2 -> 14840 | F14: 0 | G14: =VLOOKUP(B14,'Raw Sheet'!$B$8:$L$28,11,FALSE)/2 -> 1000 | H14: =VLOOKUP(B14,'Raw Sheet'!$B$8:$M$28,12,FALSE)/2 -> 250 | I14: =VLOOKUP(B14,'Raw Sheet'!$B$8:$N$28,13,FALSE)/2 -> 150 | J14: 0 | K14: 0 | L14: 0 | M14: 0 | N14: ='Raw Sheet'!AH14+'Raw Sheet'!AL14 -> 0 | O14: =SUM('Raw Sheet'!AJ14,'Raw Sheet'!AP14,'Raw Sheet'!BB14,'Raw Sheet'!BH14) -> 187.63218 | P14: ='Raw Sheet'!BJ14 -> 0 | Q14: ='Raw Sheet'!BD14 -> 2183.3563 | R14: =E14+SUM(F14:Q14) -> 18610.989 | S14: =E14+SUM(M14:Q14) -> 17210.989 | T14: =SUM(F14:L14) -> 1400 | Z14: =S14-SUM(W14:Y14) -> 17210.989 | AA14: =IF(Z14>=333333,"333333",IF(Z14>=83333,"83333",IF(Z14>=33333,"33333",IF(Z14>=16667,"16667",IF(Z14>=10417,"10417",IF(Z14<10417,"0")))))) -> 16667 | AB14: =AA14+0 -> 16667 | AC14: =VLOOKUP(AB14,WTAX!E:F,2,0) -> 0.2 | AD14: =VLOOKUP(AB14,WTAX!E:G,3,0) -> 937.5 | AE14: =(Z14-AB14)*AC14 -> 108.7977 | AF14: =AD14+AE14 -> 1046.2977 | AG14: =VLOOKUP(B14,'Raw Sheet'!$B$8:$V$28,21,FALSE) -> 0 | AH14: =VLOOKUP(B14,'Raw Sheet'!$B$8:$W$28,22,FALSE) -> 0 | AI14: =VLOOKUP(B14,'Raw Sheet'!$B$8:$X$28,23,FALSE) -> 0 | AJ14: =VLOOKUP(B14,'Raw Sheet'!$B$8:$Y$28,24,FALSE) -> 0 | AK14: =[1]Labradores!$D$44 -> 0.0049425287 | AL14: =T14 -> 1400 | AM14: =Z14-SUM(AF14:AJ14)+SUM(AK14:AL14) -> 17564.696 | AN14: 0 | AO14: 0 | AP14: 0 | AQ14: 0 | AR14: 0 | AS14: 0 | AW14: =SUM(AU14:AV14) -> 0 | AX14: =AQ14+W14 -> 0 | AZ14: =SUM(Y14,AS14) -> 0
A15: 36 | B15: 73 | C15: H | D15: =VLOOKUP(B15,'Raw Sheet'!$B$8:$G$28,6,FALSE) -> 90100 | E15: =D15/2 -> 45050 | F15: 0 | G15: =VLOOKUP(B15,'Raw Sheet'!$B$8:$L$28,11,FALSE)/2 -> 1000 | H15: =VLOOKUP(B15,'Raw Sheet'!$B$8:$M$28,12,FALSE)/2 -> 250 | I15: =VLOOKUP(B15,'Raw Sheet'!$B$8:$N$28,13,FALSE)/2 -> 150 | J15: 0 | K15: 0 | L15: 0 | M15: 0 | N15: ='Raw Sheet'!AH15+'Raw Sheet'!AL15 -> 0 | O15: =SUM('Raw Sheet'!AJ15,'Raw Sheet'!AP15,'Raw Sheet'!BB15,'Raw Sheet'!BH15) -> 0 | P15: ='Raw Sheet'!BJ15 -> 0 | Q15: ='Raw Sheet'!BD15 -> 0 | R15: =E15+SUM(F15:Q15) -> 46450 | S15: =E15+SUM(M15:Q15) -> 45050 | T15: =SUM(F15:L15) -> 1400 | Z15: =S15-SUM(W15:Y15) -> 45050 | AA15: =IF(Z15>=333333,"333333",IF(Z15>=83333,"83333",IF(Z15>=33333,"33333",IF(Z15>=16667,"16667",IF(Z15>=10417,"10417",IF(Z15<10417,"0")))))) -> 33333 | AB15: =AA15+0 -> 33333 | AC15: =VLOOKUP(AB15,WTAX!E:F,2,0) -> 0.25 | AD15: =VLOOKUP(AB15,WTAX!E:G,3,0) -> 4270.7 | AE15: =(Z15-AB15)*AC15 -> 2929.25 | AF15: =AD15+AE15 -> 7199.95 | AG15: =VLOOKUP(B15,'Raw Sheet'!$B$8:$V$28,21,FALSE) -> 0 | AH15: =VLOOKUP(B15,'Raw Sheet'!$B$8:$W$28,22,FALSE) -> 0 | AI15: =VLOOKUP(B15,'Raw Sheet'!$B$8:$X$28,23,FALSE) -> 0 | AJ15: =VLOOKUP(B15,'Raw Sheet'!$B$8:$Y$28,24,FALSE) -> 0 | AK15: =[1]Penaranda!$D$44 -> 0 | AL15: =T15 -> 1400 | AM15: =Z15-SUM(AF15:AJ15)+SUM(AK15:AL15) -> 39250.05 | AN15: 0 | AO15: 0 | AP15: 0 | AQ15: 0 | AR15: 0 | AS15: 0 | AW15: =SUM(AU15:AV15) -> 0 | AX15: =AQ15+W15 -> 0 | AZ15: =SUM(Y15,AS15) -> 0
A16: 37 | B16: 75 | C16: I | D16: =VLOOKUP(B16,'Raw Sheet'!$B$8:$G$28,6,FALSE) -> 133125 | E16: =D16/2 -> 66562.5 | F16: 0 | G16: =VLOOKUP(B16,'Raw Sheet'!$B$8:$L$28,11,FALSE)/2 -> 1000 | H16: =VLOOKUP(B16,'Raw Sheet'!$B$8:$M$28,12,FALSE)/2 -> 250 | I16: =VLOOKUP(B16,'Raw Sheet'!$B$8:$N$28,13,FALSE)/2 -> 150 | J16: 0 | K16: 0 | L16: 0 | M16: 0 | N16: ='Raw Sheet'!AH16+'Raw Sheet'!AL16 -> 0 | O16: =SUM('Raw Sheet'!AJ16,'Raw Sheet'!AP16,'Raw Sheet'!BB16,'Raw Sheet'!BH16) -> 3060.3448 | P16: ='Raw Sheet'!BJ16 -> 0 | Q16: ='Raw Sheet'!BD16 -> 0 | R16: =E16+SUM(F16:Q16) -> 71022.845 | S16: =E16+SUM(M16:Q16) -> 69622.845 | T16: =SUM(F16:L16) -> 1400 | Z16: =S16-SUM(W16:Y16) -> 69622.845 | AA16: =IF(Z16>=333333,"333333",IF(Z16>=83333,"83333",IF(Z16>=33333,"33333",IF(Z16>=16667,"16667",IF(Z16>=10417,"10417",IF(Z16<10417,"0")))))) -> 33333 | AB16: =AA16+0 -> 33333 | AC16: =VLOOKUP(AB16,WTAX!E:F,2,0) -> 0.25 | AD16: =VLOOKUP(AB16,WTAX!E:G,3,0) -> 4270.7 | AE16: =(Z16-AB16)*AC16 -> 9072.4612 | AF16: =AD16+AE16 -> 13343.161 | AG16: =VLOOKUP(B16,'Raw Sheet'!$B$8:$V$28,21,FALSE) -> 0 | AH16: =VLOOKUP(B16,'Raw Sheet'!$B$8:$W$28,22,FALSE) -> 0 | AI16: =VLOOKUP(B16,'Raw Sheet'!$B$8:$X$28,23,FALSE) -> 0 | AJ16: =VLOOKUP(B16,'Raw Sheet'!$B$8:$Y$28,24,FALSE) -> 0 | AK16: =[1]Cabante!$D$44 -> 0.0042816091 | AL16: =T16 -> 1400 | AM16: =Z16-SUM(AF16:AJ16)+SUM(AK16:AL16) -> 57679.688 | AN16: 0 | AO16: 0 | AP16: 0 | AQ16: 0 | AR16: 0 | AS16: 0 | AW16: =SUM(AU16:AV16) -> 0 | AX16: =AQ16+W16 -> 0 | AZ16: =SUM(Y16,AS16) -> 0
A17: 39 | B17: 79 | C17: J | D17: =VLOOKUP(B17,'Raw Sheet'!$B$8:$G$28,6,FALSE) -> 26250 | E17: =D17/2 -> 13125 | F17: 0 | G17: =VLOOKUP(B17,'Raw Sheet'!$B$8:$L$28,11,FALSE)/2 -> 1000 | H17: =VLOOKUP(B17,'Raw Sheet'!$B$8:$M$28,12,FALSE)/2 -> 250 | I17: =VLOOKUP(B17,'Raw Sheet'!$B$8:$N$28,13,FALSE)/2 -> 150 | J17: 0 | K17: 0 | L17: 0 | M17: 0 | N17: ='Raw Sheet'!AH17+'Raw Sheet'!AL17 -> 3439.6552 | O17: =SUM('Raw Sheet'!AJ17,'Raw Sheet'!AP17,'Raw Sheet'!BB17,'Raw Sheet'!BH17) -> 1297.4138 | P17: ='Raw Sheet'!BJ17 -> 0 | Q17: ='Raw Sheet'!BD17 -> 0 | R17: =E17+SUM(F17:Q17) -> 19262.069 | S17: =E17+SUM(M17:Q17) -> 17862.069 | T17: =SUM(F17:L17) -> 1400 | Z17: =S17-SUM(W17:Y17) -> 17862.069 | AA17: =IF(Z17>=333333,"333333",IF(Z17>=83333,"83333",IF(Z17>=33333,"33333",IF(Z17>=16667,"16667",IF(Z17>=10417,"10417",IF(Z17<10417,"0")))))) -> 16667 | AB17: =AA17+0 -> 16667 | AC17: =VLOOKUP(AB17,WTAX!E:F,2,0) -> 0.2 | AD17: =VLOOKUP(AB17,WTAX!E:G,3,0) -> 937.5 | AE17: =(Z17-AB17)*AC17 -> 239.01379 | AF17: =AD17+AE17 -> 1176.5138 | AG17: =VLOOKUP(B17,'Raw Sheet'!$B$8:$V$28,21,FALSE) -> 0 | AH17: =VLOOKUP(B17,'Raw Sheet'!$B$8:$W$28,22,FALSE) -> 0 | AI17: =VLOOKUP(B17,'Raw Sheet'!$B$8:$X$28,23,FALSE) -> 0 | AJ17: =VLOOKUP(B17,'Raw Sheet'!$B$8:$Y$28,24,FALSE) -> 0 | AK17: =[1]Zamora!$D$44 -> -0.0022413793 | AL17: =T17 -> 1400 | AM17: =Z17-SUM(AF17:AJ17)+SUM(AK17:AL17) -> 18085.553 | AN17: 0 | AO17: 0 | AP17: 0 | AQ17: 0 | AR17: 0 | AS17: 0 | AW17: =SUM(AU17:AV17) -> 0 | AX17: =AQ17+W17 -> 0 | AZ17: =SUM(Y17,AS17) -> 0
A18: 41 | B18: 83 | C18: K | D18: =VLOOKUP(B18,'Raw Sheet'!$B$8:$G$28,6,FALSE) -> 28646 | E18: =D18/2 -> 14323 | F18: 0 | G18: =VLOOKUP(B18,'Raw Sheet'!$B$8:$L$28,11,FALSE)/2 -> 1000 | H18: =VLOOKUP(B18,'Raw Sheet'!$B$8:$M$28,12,FALSE)/2 -> 250 | I18: =VLOOKUP(B18,'Raw Sheet'!$B$8:$N$28,13,FALSE)/2 -> 150 | J18: 0 | K18: 0 | L18: 0 | M18: 0 | N18: ='Raw Sheet'!AH18+'Raw Sheet'!AL18 -> 0 | O18: =SUM('Raw Sheet'!AJ18,'Raw Sheet'!AP18,'Raw Sheet'!BB18,'Raw Sheet'!BH18) -> 1317.0575 | P18: ='Raw Sheet'!BJ18 -> 0 | Q18: ='Raw Sheet'!BD18 -> 329.26437 | R18: =E18+SUM(F18:Q18) -> 17369.322 | S18: =E18+SUM(M18:Q18) -> 15969.322 | T18: =SUM(F18:L18) -> 1400 | Z18: =S18-SUM(W18:Y18) -> 15969.322 | AA18: =IF(Z18>=333333,"333333",IF(Z18>=83333,"83333",IF(Z18>=33333,"33333",IF(Z18>=16667,"16667",IF(Z18>=10417,"10417",IF(Z18<10417,"0")))))) -> 10417 | AB18: =AA18+0 -> 10417 | AC18: =VLOOKUP(AB18,WTAX!E:F,2,0) -> 0.15 | AD18: =VLOOKUP(AB18,WTAX!E:G,3,0) -> 0 | AE18: =(Z18-AB18)*AC18 -> 832.84828 | AF18: =AD18+AE18 -> 832.84828 | AG18: =VLOOKUP(B18,'Raw Sheet'!$B$8:$V$28,21,FALSE) -> 0 | AH18: =VLOOKUP(B18,'Raw Sheet'!$B$8:$W$28,22,FALSE) -> 0 | AI18: =VLOOKUP(B18,'Raw Sheet'!$B$8:$X$28,23,FALSE) -> 0 | AJ18: =VLOOKUP(B18,'Raw Sheet'!$B$8:$Y$28,24,FALSE) -> 0 | AK18: =[1]Belarma!$D$44 -> 0.0015517241 | AL18: =T18 -> 1400 | AM18: =Z18-SUM(AF18:AJ18)+SUM(AK18:AL18) -> 16536.475 | AN18: 0 | AO18: 0 | AP18: 0 | AQ18: 0 | AR18: 0 | AS18: 0 | AW18: =SUM(AU18:AV18) -> 0 | AX18: =AQ18+W18 -> 0 | AZ18: =SUM(Y18,AS18) -> 0
A19: 42 | B19: 85 | C19: L | D19: =VLOOKUP(B19,'Raw Sheet'!$B$8:$G$28,6,FALSE) -> 187500 | E19: =D19/2 -> 93750 | F19: 0 | G19: =VLOOKUP(B19,'Raw Sheet'!$B$8:$L$28,11,FALSE)/2 -> 1000 | H19: =VLOOKUP(B19,'Raw Sheet'!$B$8:$M$28,12,FALSE)/2 -> 250 | I19: =VLOOKUP(B19,'Raw Sheet'!$B$8:$N$28,13,FALSE)/2 -> 150 | J19: 0 | K19: 0 | L19: 0 | M19: 0 | N19: ='Raw Sheet'!AH19+'Raw Sheet'!AL19 -> 0 | O19: =SUM('Raw Sheet'!AJ19,'Raw Sheet'!AP19,'Raw Sheet'!BB19,'Raw Sheet'!BH19) -> 2155.1724 | P19: ='Raw Sheet'!BJ19 -> 0 | Q19: ='Raw Sheet'!BD19 -> 0 | R19: =E19+SUM(F19:Q19) -> 97305.172 | S19: =E19+SUM(M19:Q19) -> 95905.172 | T19: =SUM(F19:L19) -> 1400 | Z19: =S19-SUM(W19:Y19) -> 95905.172 | AA19: =IF(Z19>=333333,"333333",IF(Z19>=83333,"83333",IF(Z19>=33333,"33333",IF(Z19>=16667,"16667",IF(Z19>=10417,"10417",IF(Z19<10417,"0")))))) -> 83333 | AB19: =AA19+0 -> 83333 | AC19: =VLOOKUP(AB19,WTAX!E:F,2,0) -> 0.3 | AD19: =VLOOKUP(AB19,WTAX!E:G,3,0) -> 16770.7 | AE19: =(Z19-AB19)*AC19 -> 3771.6517 | AF19: =AD19+AE19 -> 20542.352 | AG19: =VLOOKUP(B19,'Raw Sheet'!$B$8:$V$28,21,FALSE) -> 0 | AH19: =VLOOKUP(B19,'Raw Sheet'!$B$8:$W$28,22,FALSE) -> 0 | AI19: =VLOOKUP(B19,'Raw Sheet'!$B$8:$X$28,23,FALSE) -> 0 | AJ19: =VLOOKUP(B19,'Raw Sheet'!$B$8:$Y$28,24,FALSE) -> 0 | AK19: =[1]Virtudes!$D$44 -> 0 | AL19: =T19 -> 1400 | AM19: =Z19-SUM(AF19:AJ19)+SUM(AK19:AL19) -> 76762.821 | AN19: 0 | AO19: 0 | AP19: 0 | AQ19: 0 | AR19: 0 | AS19: 0 | AW19: =SUM(AU19:AV19) -> 0 | AX19: =AQ19+W19 -> 0 | AZ19: =SUM(Y19,AS19) -> 0
A20: 43 | B20: 87 | C20: M | D20: =VLOOKUP(B20,'Raw Sheet'!$B$8:$G$28,6,FALSE) -> 102816 | E20: =D20/2 -> 51408 | F20: 0 | G20: =VLOOKUP(B20,'Raw Sheet'!$B$8:$L$28,11,FALSE)/2 -> 1000 | H20: =VLOOKUP(B20,'Raw Sheet'!$B$8:$M$28,12,FALSE)/2 -> 250 | I20: =VLOOKUP(B20,'Raw Sheet'!$B$8:$N$28,13,FALSE)/2 -> 150 | J20: 0 | K20: 0 | L20: 0 | M20: 0 | N20: ='Raw Sheet'!AH20+'Raw Sheet'!AL20 -> 0 | O20: =SUM('Raw Sheet'!AJ20,'Raw Sheet'!AP20,'Raw Sheet'!BB20,'Raw Sheet'!BH20) -> 0 | P20: ='Raw Sheet'!BJ20 -> -14181.517 | Q20: ='Raw Sheet'!BD20 -> 0 | R20: =E20+SUM(F20:Q20) -> 38626.483 | S20: =E20+SUM(M20:Q20) -> 37226.483 | T20: =SUM(F20:L20) -> 1400 | Z20: =S20-SUM(W20:Y20) -> 37226.483 | AA20: =IF(Z20>=333333,"333333",IF(Z20>=83333,"83333",IF(Z20>=33333,"33333",IF(Z20>=16667,"16667",IF(Z20>=10417,"10417",IF(Z20<10417,"0")))))) -> 33333 | AB20: =AA20+0 -> 33333 | AC20: =VLOOKUP(AB20,WTAX!E:F,2,0) -> 0.25 | AD20: =VLOOKUP(AB20,WTAX!E:G,3,0) -> 4270.7 | AE20: =(Z20-AB20)*AC20 -> 973.37069 | AF20: =AD20+AE20 -> 5244.0707 | AG20: =VLOOKUP(B20,'Raw Sheet'!$B$8:$V$28,21,FALSE) -> 0 | AH20: =VLOOKUP(B20,'Raw Sheet'!$B$8:$W$28,22,FALSE) -> 0 | AI20: =VLOOKUP(B20,'Raw Sheet'!$B$8:$X$28,23,FALSE) -> 0 | AJ20: =VLOOKUP(B20,'Raw Sheet'!$B$8:$Y$28,24,FALSE) -> 0 | AK20: =[1]Bautista!$D$44 -> -0.0022988507 | AL20: =T20 -> 1400 | AM20: =Z20-SUM(AF20:AJ20)+SUM(AK20:AL20) -> 33382.41 | AN20: 0 | AO20: 0 | AP20: 0 | AQ20: 0 | AR20: 0 | AS20: 0 | AW20: =SUM(AU20:AV20) -> 0 | AX20: =AQ20+W20 -> 0 | AZ20: =SUM(Y20,AS20) -> 0
A21: 44 | B21: 89 | C21: N | D21: =VLOOKUP(B21,'Raw Sheet'!$B$8:$G$28,6,FALSE) -> 24700 | E21: =D21/2 -> 12350 | F21: 0 | G21: =VLOOKUP(B21,'Raw Sheet'!$B$8:$L$28,11,FALSE)/2 -> 1000 | H21: =VLOOKUP(B21,'Raw Sheet'!$B$8:$M$28,12,FALSE)/2 -> 250 | I21: =VLOOKUP(B21,'Raw Sheet'!$B$8:$N$28,13,FALSE)/2 -> 150 | J21: 0 | K21: 0 | L21: 0 | M21: 0 | N21: ='Raw Sheet'!AH21+'Raw Sheet'!AL21 -> 0 | O21: =SUM('Raw Sheet'!AJ21,'Raw Sheet'!AP21,'Raw Sheet'!BB21,'Raw Sheet'!BH21) -> 908.50575 | P21: ='Raw Sheet'!BJ21 -> 0 | Q21: ='Raw Sheet'!BD21 -> 425.86207 | R21: =E21+SUM(F21:Q21) -> 15084.368 | S21: =E21+SUM(M21:Q21) -> 13684.368 | T21: =SUM(F21:L21) -> 1400 | Z21: =S21-SUM(W21:Y21) -> 13684.368 | AA21: =IF(Z21>=333333,"333333",IF(Z21>=83333,"83333",IF(Z21>=33333,"33333",IF(Z21>=16667,"16667",IF(Z21>=10417,"10417",IF(Z21<10417,"0")))))) -> 10417 | AB21: =AA21+0 -> 10417 | AC21: =VLOOKUP(AB21,WTAX!E:F,2,0) -> 0.15 | AD21: =VLOOKUP(AB21,WTAX!E:G,3,0) -> 0 | AE21: =(Z21-AB21)*AC21 -> 490.10517 | AF21: =AD21+AE21 -> 490.10517 | AG21: =VLOOKUP(B21,'Raw Sheet'!$B$8:$V$28,21,FALSE) -> 697.88 | AH21: =VLOOKUP(B21,'Raw Sheet'!$B$8:$W$28,22,FALSE) -> 0 | AI21: =VLOOKUP(B21,'Raw Sheet'!$B$8:$X$28,23,FALSE) -> 697.88 | AJ21: =VLOOKUP(B21,'Raw Sheet'!$B$8:$Y$28,24,FALSE) -> 0 | AK21: =[1]Angeles!$D$44 -> -0.00068965518 | AL21: =T21 -> 1400 | AM21: =Z21-SUM(AF21:AJ21)+SUM(AK21:AL21) -> 13198.502 | AN21: 0 | AO21: 0 | AP21: 0 | AQ21: 0 | AR21: 0 | AS21: 0 | AW21: =SUM(AU21:AV21) -> 0 | AX21: =AQ21+W21 -> 0 | AZ21: =SUM(Y21,AS21) -> 0
A22: 45 | B22: 91 | C22: O | D22: =VLOOKUP(B22,'Raw Sheet'!$B$8:$G$28,6,FALSE) -> 85000 | E22: =D22/2 -> 42500 | F22: 0 | G22: =VLOOKUP(B22,'Raw Sheet'!$B$8:$L$28,11,FALSE)/2 -> 1000 | H22: =VLOOKUP(B22,'Raw Sheet'!$B$8:$M$28,12,FALSE)/2 -> 250 | I22: =VLOOKUP(B22,'Raw Sheet'!$B$8:$N$28,13,FALSE)/2 -> 150 | J22: 0 | K22: 0 | L22: 0 | M22: 0 | N22: ='Raw Sheet'!AH22+'Raw Sheet'!AL22 -> 7474.1379 | O22: =SUM('Raw Sheet'!AJ22,'Raw Sheet'!AP22,'Raw Sheet'!BB22,'Raw Sheet'!BH22) -> 3517.2414 | P22: ='Raw Sheet'!BJ22 -> 0 | Q22: ='Raw Sheet'!BD22 -> 0 | R22: =E22+SUM(F22:Q22) -> 54891.379 | S22: =E22+SUM(M22:Q22) -> 53491.379 | T22: =SUM(F22:L22) -> 1400 | Z22: =S22-SUM(W22:Y22) -> 53491.379 | AA22: =IF(Z22>=333333,"333333",IF(Z22>=83333,"83333",IF(Z22>=33333,"33333",IF(Z22>=16667,"16667",IF(Z22>=10417,"10417",IF(Z22<10417,"0")))))) -> 33333 | AB22: =AA22+0 -> 33333 | AC22: =VLOOKUP(AB22,WTAX!E:F,2,0) -> 0.25 | AD22: =VLOOKUP(AB22,WTAX!E:G,3,0) -> 4270.7 | AE22: =(Z22-AB22)*AC22 -> 5039.5948 | AF22: =AD22+AE22 -> 9310.2948 | AG22: =VLOOKUP(B22,'Raw Sheet'!$B$8:$V$28,21,FALSE) -> 0 | AH22: =VLOOKUP(B22,'Raw Sheet'!$B$8:$W$28,22,FALSE) -> 0 | AI22: =VLOOKUP(B22,'Raw Sheet'!$B$8:$X$28,23,FALSE) -> 0 | AJ22: =VLOOKUP(B22,'Raw Sheet'!$B$8:$Y$28,24,FALSE) -> 0 | AK22: =[1]Morante!$D$44 -> 0.00022988504 | AL22: =T22 -> 1400 | AM22: =Z22-SUM(AF22:AJ22)+SUM(AK22:AL22) -> 45581.085 | AN22: 0 | AO22: 0 | AP22: 0 | AQ22: 0 | AR22: 0 | AS22: 0 | AW22: =SUM(AU22:AV22) -> 0 | AX22: =AQ22+W22 -> 0 | AZ22: =SUM(Y22,AS22) -> 0
A23: 46 | B23: 93 | C23: P | D23: =VLOOKUP(B23,'Raw Sheet'!$B$8:$G$28,6,FALSE) -> 130000 | E23: =D23/2 -> 65000 | F23: 0 | G23: =VLOOKUP(B23,'Raw Sheet'!$B$8:$L$28,11,FALSE)/2 -> 1000 | H23: =VLOOKUP(B23,'Raw Sheet'!$B$8:$M$28,12,FALSE)/2 -> 250 | I23: =VLOOKUP(B23,'Raw Sheet'!$B$8:$N$28,13,FALSE)/2 -> 150 | J23: 0 | K23: 0 | L23: 0 | M23: 0 | N23: ='Raw Sheet'!AH23+'Raw Sheet'!AL23 -> 5715.5172 | O23: =SUM('Raw Sheet'!AJ23,'Raw Sheet'!AP23,'Raw Sheet'!BB23,'Raw Sheet'!BH23) -> 3586.2069 | P23: ='Raw Sheet'!BJ23 -> 0 | Q23: ='Raw Sheet'!BD23 -> 0 | R23: =E23+SUM(F23:Q23) -> 75701.724 | S23: =E23+SUM(M23:Q23) -> 74301.724 | T23: =SUM(F23:L23) -> 1400 | Z23: =S23-SUM(W23:Y23) -> 74301.724 | AA23: =IF(Z23>=333333,"333333",IF(Z23>=83333,"83333",IF(Z23>=33333,"33333",IF(Z23>=16667,"16667",IF(Z23>=10417,"10417",IF(Z23<10417,"0")))))) -> 33333 | AB23: =AA23+0 -> 33333 | AC23: =VLOOKUP(AB23,WTAX!E:F,2,0) -> 0.25 | AD23: =VLOOKUP(AB23,WTAX!E:G,3,0) -> 4270.7 | AE23: =(Z23-AB23)*AC23 -> 10242.181 | AF23: =AD23+AE23 -> 14512.881 | AG23: =VLOOKUP(B23,'Raw Sheet'!$B$8:$V$28,21,FALSE) -> 1845.8 | AH23: =VLOOKUP(B23,'Raw Sheet'!$B$8:$W$28,22,FALSE) -> 0 | AI23: =VLOOKUP(B23,'Raw Sheet'!$B$8:$X$28,23,FALSE) -> 0 | AJ23: =VLOOKUP(B23,'Raw Sheet'!$B$8:$Y$28,24,FALSE) -> 0 | AK23: =-[1]Lindo!$D$44 -> -9750.9512 | AL23: =T23 -> 1400 | AM23: =Z23-SUM(AF23:AJ23)+SUM(AK23:AL23) -> 49592.092 | AN23: 0 | AO23: 0 | AP23: 0 | AQ23: 0 | AR23: 0 | AS23: 0 | AW23: =SUM(AU23:AV23) -> 0 | AX23: =AQ23+W23 -> 0 | AZ23: =SUM(Y23,AS23) -> 0
A24: 47 | B24: 95 | C24: Q | D24: =VLOOKUP(B24,'Raw Sheet'!$B$8:$G$28,6,FALSE) -> 30000 | E24: =D24/2 -> 15000 | F24: 0 | G24: =VLOOKUP(B24,'Raw Sheet'!$B$8:$L$28,11,FALSE)/2 -> 1000 | H24: =VLOOKUP(B24,'Raw Sheet'!$B$8:$M$28,12,FALSE)/2 -> 250 | I24: =VLOOKUP(B24,'Raw Sheet'!$B$8:$N$28,13,FALSE)/2 -> 150 | J24: 0 | K24: 0 | L24: 0 | M24: 0 | N24: ='Raw Sheet'!AH24+'Raw Sheet'!AL24 -> 0 | O24: =SUM('Raw Sheet'!AJ24,'Raw Sheet'!AP24,'Raw Sheet'!BB24,'Raw Sheet'!BH24) -> 275.86207 | P24: ='Raw Sheet'!BJ24 -> -1379.3103 | Q24: ='Raw Sheet'!BD24 -> 1379.3103 | R24: =E24+SUM(F24:Q24) -> 16675.862 | S24: =E24+SUM(M24:Q24) -> 15275.862 | T24: =SUM(F24:L24) -> 1400 | Z24: =S24-SUM(W24:Y24) -> 15275.862 | AA24: =IF(Z24>=333333,"333333",IF(Z24>=83333,"83333",IF(Z24>=33333,"33333",IF(Z24>=16667,"16667",IF(Z24>=10417,"10417",IF(Z24<10417,"0")))))) -> 10417 | AB24: =AA24+0 -> 10417 | AC24: =VLOOKUP(AB24,WTAX!E:F,2,0) -> 0.15 | AD24: =VLOOKUP(AB24,WTAX!E:G,3,0) -> 0 | AE24: =(Z24-AB24)*AC24 -> 728.82931 | AF24: =AD24+AE24 -> 728.82931 | AG24: =VLOOKUP(B24,'Raw Sheet'!$B$8:$V$28,21,FALSE) -> 0 | AH24: =VLOOKUP(B24,'Raw Sheet'!$B$8:$W$28,22,FALSE) -> 0 | AI24: =VLOOKUP(B24,'Raw Sheet'!$B$8:$X$28,23,FALSE) -> 0 | AJ24: =VLOOKUP(B24,'Raw Sheet'!$B$8:$Y$28,24,FALSE) -> 0 | AK24: =[1]Silva!$D$44 -> -0.0035862069 | AL24: =T24 -> 1400 | AM24: =Z24-SUM(AF24:AJ24)+SUM(AK24:AL24) -> 15947.029 | AN24: 0 | AO24: 0 | AP24: 0 | AQ24: 0 | AR24: 0 | AS24: 0 | AW24: =SUM(AU24:AV24) -> 0 | AX24: =AQ24+W24 -> 0 | AZ24: =SUM(Y24,AS24) -> 0
A25: 49 | B25: 99 | C25: R | D25: =VLOOKUP(B25,'Raw Sheet'!$B$8:$G$28,6,FALSE) -> 28000 | E25: =D25/2 -> 14000 | F25: 0 | G25: =VLOOKUP(B25,'Raw Sheet'!$B$8:$L$28,11,FALSE)/2 -> 1000 | H25: =VLOOKUP(B25,'Raw Sheet'!$B$8:$M$28,12,FALSE)/2 -> 250 | I25: =VLOOKUP(B25,'Raw Sheet'!$B$8:$N$28,13,FALSE)/2 -> 150 | J25: 0 | K25: 0 | L25: 0 | M25: 0 | N25: ='Raw Sheet'!AH25+'Raw Sheet'!AL25 -> 0 | O25: =SUM('Raw Sheet'!AJ25,'Raw Sheet'!AP25,'Raw Sheet'!BB25,'Raw Sheet'!BH25) -> 321.83908 | P25: ='Raw Sheet'!BJ25 -> 0 | Q25: ='Raw Sheet'!BD25 -> 0 | R25: =E25+SUM(F25:Q25) -> 15721.839 | S25: =E25+SUM(M25:Q25) -> 14321.839 | T25: =SUM(F25:L25) -> 1400 | Z25: =S25-SUM(W25:Y25) -> 14321.839 | AA25: =IF(Z25>=333333,"333333",IF(Z25>=83333,"83333",IF(Z25>=33333,"33333",IF(Z25>=16667,"16667",IF(Z25>=10417,"10417",IF(Z25<10417,"0")))))) -> 10417 | AB25: =AA25+0 -> 10417 | AC25: =VLOOKUP(AB25,WTAX!E:F,2,0) -> 0.15 | AD25: =VLOOKUP(AB25,WTAX!E:G,3,0) -> 0 | AE25: =(Z25-AB25)*AC25 -> 585.72586 | AF25: =AD25+AE25 -> 585.72586 | AG25: =VLOOKUP(B25,'Raw Sheet'!$B$8:$V$28,21,FALSE) -> 0 | AH25: =VLOOKUP(B25,'Raw Sheet'!$B$8:$W$28,22,FALSE) -> 0 | AI25: =VLOOKUP(B25,'Raw Sheet'!$B$8:$X$28,23,FALSE) -> 0 | AJ25: =VLOOKUP(B25,'Raw Sheet'!$B$8:$Y$28,24,FALSE) -> 0 | AK25: =[1]Espino!$D$44 -> -0.00022988506 | AL25: =T25 -> 1400 | AM25: =Z25-SUM(AF25:AJ25)+SUM(AK25:AL25) -> 15136.113 | AN25: 0 | AO25: 0 | AP25: 0 | AQ25: 0 | AR25: 0 | AS25: 0 | AW25: =SUM(AU25:AV25) -> 0 | AX25: =AQ25+W25 -> 0 | AZ25: =SUM(Y25,AS25) -> 0
A26: 50 | B26: 101 | C26: S | D26: =VLOOKUP(B26,'Raw Sheet'!$B$8:$G$28,6,FALSE) -> 85000 | E26: =D26/2 -> 42500 | F26: 0 | G26: =VLOOKUP(B26,'Raw Sheet'!$B$8:$L$28,11,FALSE)/2 -> 1000 | H26: =VLOOKUP(B26,'Raw Sheet'!$B$8:$M$28,12,FALSE)/2 -> 250 | I26: =VLOOKUP(B26,'Raw Sheet'!$B$8:$N$28,13,FALSE)/2 -> 150 | J26: 0 | K26: 0 | L26: 0 | M26: 0 | N26: ='Raw Sheet'!AH26+'Raw Sheet'!AL26 -> 3737.069 | O26: =SUM('Raw Sheet'!AJ26,'Raw Sheet'!AP26,'Raw Sheet'!BB26,'Raw Sheet'!BH26) -> 1563.2184 | P26: ='Raw Sheet'!BJ26 -> 0 | Q26: ='Raw Sheet'!BD26 -> 0 | R26: =E26+SUM(F26:Q26) -> 49200.287 | S26: =E26+SUM(M26:Q26) -> 47800.287 | T26: =SUM(F26:L26) -> 1400 | Z26: =S26-SUM(W26:Y26) -> 47800.287 | AA26: =IF(Z26>=333333,"333333",IF(Z26>=83333,"83333",IF(Z26>=33333,"33333",IF(Z26>=16667,"16667",IF(Z26>=10417,"10417",IF(Z26<10417,"0")))))) -> 33333 | AB26: =AA26+0 -> 33333 | AC26: =VLOOKUP(AB26,WTAX!E:F,2,0) -> 0.25 | AD26: =VLOOKUP(AB26,WTAX!E:G,3,0) -> 4270.7 | AE26: =(Z26-AB26)*AC26 -> 3616.8218 | AF26: =AD26+AE26 -> 7887.5218 | AG26: =VLOOKUP(B26,'Raw Sheet'!$B$8:$V$28,21,FALSE) -> 1809.09 | AH26: =VLOOKUP(B26,'Raw Sheet'!$B$8:$W$28,22,FALSE) -> 0 | AI26: =VLOOKUP(B26,'Raw Sheet'!$B$8:$X$28,23,FALSE) -> 0 | AJ26: =VLOOKUP(B26,'Raw Sheet'!$B$8:$Y$28,24,FALSE) -> 0 | AK26: =[1]Austria!$D$44 -> -0.0017471265 | AL26: =T26 -> 1400 | AM26: =Z26-SUM(AF26:AJ26)+SUM(AK26:AL26) -> 39503.674 | AN26: 0 | AO26: 0 | AP26: 0 | AQ26: 0 | AR26: 0 | AS26: 0 | AW26: =SUM(AU26:AV26) -> 0 | AX26: =AQ26+W26 -> 0 | AZ26: =SUM(Y26,AS26) -> 0
A27: 51 | B27: 103 | C27: T | D27: =VLOOKUP(B27,'Raw Sheet'!$B$8:$G$28,6,FALSE) -> 22000 | E27: =D27/2 -> 11000 | F27: 0 | G27: =VLOOKUP(B27,'Raw Sheet'!$B$8:$L$28,11,FALSE)/2 -> 1000 | H27: =VLOOKUP(B27,'Raw Sheet'!$B$8:$M$28,12,FALSE)/2 -> 250 | I27: =VLOOKUP(B27,'Raw Sheet'!$B$8:$N$28,13,FALSE)/2 -> 150 | J27: 0 | K27: 0 | L27: 0 | M27: 0 | N27: ='Raw Sheet'!AH27+'Raw Sheet'!AL27 -> 0 | O27: =SUM('Raw Sheet'!AJ27,'Raw Sheet'!AP27,'Raw Sheet'!BB27,'Raw Sheet'!BH27) -> 303.44828 | P27: ='Raw Sheet'!BJ27 -> -252.87356 | Q27: ='Raw Sheet'!BD27 -> 1011.4943 | R27: =E27+SUM(F27:Q27) -> 13462.069 | S27: =E27+SUM(M27:Q27) -> 12062.069 | T27: =SUM(F27:L27) -> 1400 | Z27: =S27-SUM(W27:Y27) -> 12062.069 | AA27: =IF(Z27>=333333,"333333",IF(Z27>=83333,"83333",IF(Z27>=33333,"33333",IF(Z27>=16667,"16667",IF(Z27>=10417,"10417",IF(Z27<10417,"0")))))) -> 10417 | AB27: =AA27+0 -> 10417 | AC27: =VLOOKUP(AB27,WTAX!E:F,2,0) -> 0.15 | AD27: =VLOOKUP(AB27,WTAX!E:G,3,0) -> 0 | AE27: =(Z27-AB27)*AC27 -> 246.76034 | AF27: =AD27+AE27 -> 246.76034 | AG27: =VLOOKUP(B27,'Raw Sheet'!$B$8:$V$28,21,FALSE) -> 0 | AH27: =VLOOKUP(B27,'Raw Sheet'!$B$8:$W$28,22,FALSE) -> 0 | AI27: =VLOOKUP(B27,'Raw Sheet'!$B$8:$X$28,23,FALSE) -> 0 | AJ27: =VLOOKUP(B27,'Raw Sheet'!$B$8:$Y$28,24,FALSE) -> 0 | AK27: =[1]Cruz!$D$44 -> 0.0028965517 | AL27: =T27 -> 1400 | AM27: =Z27-SUM(AF27:AJ27)+SUM(AK27:AL27) -> 13215.312 | AN27: 0 | AO27: 0 | AP27: 0 | AQ27: 0 | AR27: 0 | AS27: 0 | AW27: =SUM(AU27:AV27) -> 0 | AX27: =AQ27+W27 -> 0 | AZ27: =SUM(Y27,AS27) -> 0
A28: 52 | B28: 105 | C28: U | D28: =VLOOKUP(B28,'Raw Sheet'!$B$8:$G$28,6,FALSE) -> 18000 | E28: =D28/2 -> 9000 | F28: 0 | G28: =VLOOKUP(B28,'Raw Sheet'!$B$8:$L$28,11,FALSE)/2 -> 1000 | H28: =VLOOKUP(B28,'Raw Sheet'!$B$8:$M$28,12,FALSE)/2 -> 250 | I28: =VLOOKUP(B28,'Raw Sheet'!$B$8:$N$28,13,FALSE)/2 -> 150 | J28: 0 | K28: 0 | L28: 0 | M28: 0 | N28: ='Raw Sheet'!AH28+'Raw Sheet'!AL28 -> 0 | O28: =SUM('Raw Sheet'!AJ28,'Raw Sheet'!AP28,'Raw Sheet'!BB28,'Raw Sheet'!BH28) -> 227.58621 | P28: ='Raw Sheet'!BJ28 -> 0 | Q28: ='Raw Sheet'!BD28 -> 827.58621 | R28: =E28+SUM(F28:Q28) -> 11455.172 | S28: =E28+SUM(M28:Q28) -> 10055.172 | T28: =SUM(F28:L28) -> 1400 | Z28: =S28-SUM(W28:Y28) -> 10055.172 | AA28: =IF(Z28>=333333,"333333",IF(Z28>=83333,"83333",IF(Z28>=33333,"33333",IF(Z28>=16667,"16667",IF(Z28>=10417,"10417",IF(Z28<10417,"0")))))) -> 0 | AB28: =AA28+0 -> 0 | AC28: =VLOOKUP(AB28,WTAX!E:F,2,0) -> 0 | AD28: =VLOOKUP(AB28,WTAX!E:G,3,0) -> 0 | AE28: =(Z28-AB28)*AC28 -> 0 | AF28: =AD28+AE28 -> 0 | AG28: =VLOOKUP(B28,'Raw Sheet'!$B$8:$V$28,21,FALSE) -> 0 | AH28: =VLOOKUP(B28,'Raw Sheet'!$B$8:$W$28,22,FALSE) -> 0 | AI28: =VLOOKUP(B28,'Raw Sheet'!$B$8:$X$28,23,FALSE) -> 0 | AJ28: =VLOOKUP(B28,'Raw Sheet'!$B$8:$Y$28,24,FALSE) -> 0 | AK28: =[1]Magnaye!$D$44 -> 0 | AL28: =T28 -> 1400 | AM28: =Z28-SUM(AF28:AJ28)+SUM(AK28:AL28) -> 11455.172 | AN28: 0 | AO28: 0 | AP28: 0 | AQ28: 0 | AR28: 0 | AS28: 0 | AW28: =SUM(AU28:AV28) -> 0 | AX28: =AQ28+W28 -> 0 | AZ28: =SUM(Y28,AS28) -> 0
C29: TOTAL | D29: =SUM(D8:D28) -> 1596217 | E29: =SUM(E8:E28) -> 798108.5 | F29: =SUM(F8:F28) -> 0 | G29: =SUM(G8:G28) -> 19780 | H29: =SUM(H8:H28) -> 4550 | I29: =SUM(I8:I28) -> 2700 | J29: =SUM(J8:J28) -> 0 | K29: =SUM(K8:K28) -> 0 | ... AB29: =SUM(AB8:AB28) -> 595834 | AD29: =SUM(AD8:AD28) -> 80623.8 | AE29: =SUM(AE8:AE28) -> 57698.758 | AF29: =SUM(AF8:AF28) -> 138322.56 | AG29: =SUM(AG8:AG28) -> 8044.37 | AH29: =SUM(AH8:AH28) -> 0 | AI29: =SUM(AI8:AI28) -> 697.88 | AJ29: =SUM(AJ8:AJ28) -> 41395.83 | AK29: =SUM(AK8:AK28) -> -5417.6122 | ... AS29: =SUM(AS8:AS28) -> 0 | AW29: =SUM(AW8:AW28) -> 0 | AX29: =SUM(AX8:AX28) -> 0 | AY29: =SUM(AY8:AY28) -> 0 | AZ29: =SUM(AZ8:AZ28) -> 0
D31: =D29-'Raw Sheet'!G30 -> 0 | E31: =E29-'Raw Sheet'!H30 -> 0 | G31: =G29-('Raw Sheet'!L30/2) -> 0 | H31: =H29-('Raw Sheet'!M30/2) -> 0 | I31: =I29-('Raw Sheet'!N30/2) -> 0 | N31: =N29-SUM('Raw Sheet'!AH30,'Raw Sheet'!AL30,'Raw Sheet'!AN30) -> 0 | O31: =O29-SUM('Raw Sheet'!AJ30,'Raw Sheet'!AP30,'Raw Sheet'!BB30,'Raw Sheet'!BH30) -> 0 | P31: =P29+'Raw Sheet'!AB30+'Raw Sheet'!AD30 -> 0 | Q31: =Q29-SUM('Raw Sheet'!AX30,'Raw Sheet'!AZ30,'Raw Sheet'!BD30,'Raw Sheet'!BF30) -> 0 | R31: =R29-SUM(E29:Q29) -> 0 | S31: =S29-SUM(E29,M29:Q29) -> 0 | T31: =T29-(('Raw Sheet'!L30+'Raw Sheet'!M30+'Raw Sheet'!N30)/2) -> 0 | Z31: =Z29-SUM(S29,W29:Y29) -> 0 | AF31: =AF29-SUM(AD29:AE29) -> 0 | AG31: =AG29-'Raw Sheet'!V30 -> 0 | AH31: =AH29-'Raw Sheet'!W30 -> 0 | AI31: =AI29-'Raw Sheet'!X30 -> 0 | AJ31: =AJ29-'Raw Sheet'!Y30 -> 0 | AL31: =AL29-(SUM('Raw Sheet'!L30:N30)/2) -> 0 | AM31: =E29+G29+H29+I29+N29+O29+P29+Q29-AF29-AG29-AI29-AJ29+AK29-AM29 -> 0
R32: ='Raw Sheet'!H30+'Raw Sheet'!L30+'Raw Sheet'!M30+'Raw Sheet'!N30+'Raw Sheet'!BI30+'Raw Sheet'!BJ30-(SUM('Raw Sheet'!L30:N30)/2)-R29 -> 0
N34: Payroll Entry:
N35: Salaries Expense | R35: =E29+SUM(M29:Q29) -> 839187.22
N36: De Minimis Benefit | R36: =SUM(F29:K29) -> 27030
N37: Leave Conversion Pay | R37: =L29 -> 0
N38: SSS Contribution | R38: =AQ29 -> 0
N39: Philhealth Contribution | R39: =AR29 -> 0
N40: Pag-ibig Contribution - Direct | R40: =AS29 -> 0
N41: 13th Month Pay & Other Benefits | R41: 0
N42: Advances from Employees | R42: 0
P43: Compensation Withholding Tax | S43: =AF29 -> 138322.56
P44: Advances to Employees | S44: =AJ29 -> 41395.83
P45: SSS Contribution Payable | S45: =W29+AQ29 -> 0 | T45: =S45-AX29 -> 0
P46: Philhealth Contribution Payable | S46: =X29+AR29 -> 0 | T46: =S46-AY29 -> 0
P47: Pag-IBIG Contribution Payable | S47: =Y29+AS29 -> 0 | T47: =S47-AZ29 -> 0
P48: 2025 Tax refund | S48: =-AK29 -> 5417.6122
P49: Cash | S49: =AM29 -> 672338.97 | T49: =S49-AM29 -> 0
P50: SSS Loan Payable | S50: =AG29+AH29 -> 8044.37 | T50: =S50-SUM(AG29:AH29) -> 0
P51: HDMF Loan Payable | S51: =AI29 -> 697.88
R52: =SUM(R35:R50) -> 866217.22 | S52: =SUM(S35:S51) -> 866217.22
S53: =R52-S52 -> 0

Sheet PAYSLIP (1st)
A2: PAY SLIP | J2: PAY SLIP | S2: PAY SLIP | AB2: PAY SLIP | AK2: PAY SLIP | AT2: PAY SLIP | BC2: PAY SLIP | BL2: PAY SLIP | BU2: PAY SLIP | CD2: PAY SLIP | CM2: PAY SLIP | CV2: PAY SLIP | DE2: PAY SLIP | DN2: PAY SLIP | DW2: PAY SLIP | EF2: PAY SLIP | EO2: PAY SLIP | EX2: PAY SLIP | FG2: PAY SLIP | FP2: PAY SLIP | FY2: PAY SLIP | GH2: PAY SLIP | GQ2: PAY SLIP | GZ2: PAY SLIP | HI2: PAY SLIP | HR2: PAY SLIP | IA2: PAY SLIP | IJ2: PAY SLIP | IS2: PAY SLIP | JB2: PAY SLIP | JK2: PAY SLIP | JT2: PAY SLIP | KC2: PAY SLIP
A4: Employee: | B4: 28 | C4: Morales, Marco B. | F4: Payroll period: | G4: 45946 | H4: 45961 | J4: Employee: | K4: 29 | L4: Uy, John Michael B. | O4: Payroll period: | P4: 45946 | Q4: 45961 | S4: Employee: | T4: 30 | U4: Lagrisola, Ralph Rafael A. | X4: Payroll period: | Y4: 45946 | Z4: 45961 | AB4: Employee: | AC4: 31 | AD4: Lim, John Christopher Tan | AG4: Payroll period: | AH4: 45946 | AI4: 45961 | AK4: Employee: | AL4: 32 | AM4: Quilao, Najma M. | AP4: Payroll period: | AQ4: 45946 | AR4: 45961 | AT4: Employee: | AU4: 33 | AV4: Balingit, John Dave V. | AY4: Payroll period: | AZ4: 45946 | BA4: 45961 | BC4: Employee: | BD4: 34 | BE4: Tolentino, Julius Angelito R. | BH4: Payroll period: | BI4: 45946 | BJ4: 45961 | BL4: Employee: | BM4: 35 | BN4: Hilario, Gilbert C. | BQ4: Payroll period: | BR4: 45946 | BS4: 45961 | BU4: Employee: | BV4: 1 | BW4: =VLOOKUP(BV4,'Raw Sheet'!$A$8:$BK$59,'Raw Sheet'!$C$4,FALSE) -> A | BZ4: Payroll period: | CA4: ='Payroll Register'!D3 -> 46023 | CB4: ='Payroll Register'!E3 -> 46037 | CD4: Employee: | CE4: 5 | CF4: =VLOOKUP(CE4,'Raw Sheet'!$A$8:$BK$59,'Raw Sheet'!$C$4,FALSE) -> #N/A | CI4: Payroll period: | CJ4: 45946 | CK4: 45961 | CM4: Employee: | CN4: 38 | CO4: Antalan, Rogelio G. | CR4: Payroll period: | CS4: 45946 | CT4: 45961 | CV4: Employee: | CW4: 8 | CX4: =VLOOKUP(CW4,'Raw Sheet'!$A$8:$BK$59,'Raw Sheet'!$C$4,FALSE) -> B | DA4: Payroll period: | DB4: ='Raw Sheet'!D2 -> 46023 | DC4: ='Raw Sheet'!E2 -> 46037 | DE4: Employee: | DF4: 40 | DG4: Frias, Ulric Vhon Vargas | DJ4: Payroll period: | DK4: 45946 | DL4: 45961 | DN4: Employee: | DO4: 10 | DP4: =VLOOKUP(DO4,'Raw Sheet'!$A$8:$BK$59,'Raw Sheet'!$C$4,FALSE) -> C | DS4: Payroll period: | DT4: ='Raw Sheet'!D2 -> 46023 | DU4: ='Raw Sheet'!E2 -> 46037 | DW4: Employee: | DX4: 11 | DY4: =VLOOKUP(DX4,'Raw Sheet'!$A$8:$BK$59,'Raw Sheet'!$C$4,FALSE) -> D | EB4: Payroll period: | EC4: ='Raw Sheet'!D2 -> 46023 | ED4: ='Raw Sheet'!E2 -> 46037 | EF4: Employee: | EG4: 12 | EH4: =VLOOKUP(EG4,'Raw Sheet'!$A$8:$BK$59,'Raw Sheet'!$C$4,FALSE) -> E | EK4: Payroll period: | EL4: ='Raw Sheet'!D2 -> 46023 | EM4: ='Raw Sheet'!E2 -> 46037 | EO4: Employee: | EP4: 15 | EQ4: =VLOOKUP(EP4,'Raw Sheet'!$A$8:$BK$59,'Raw Sheet'!$C$4,FALSE) -> F | ET4: Payroll period: | EU4: ='Raw Sheet'!D2 -> 46023 | EV4: ='Raw Sheet'!E2 -> 46037 | EX4: Employee: | EY4: 19 | EZ4: =VLOOKUP(EY4,'Raw Sheet'!$A$8:$BK$59,'Raw Sheet'!$C$4,FALSE) -> G | FC4: Payroll period: | FD4: ='Raw Sheet'!D2 -> 46023 | FE4: ='Raw Sheet'!E2 -> 46037 | FG4: Employee: | FH4: 36 | FI4: =VLOOKUP(FH4,'Raw Sheet'!$A$8:$BK$59,'Raw Sheet'!$C$4,FALSE) -> H | FL4: Payroll period: | FM4: ='Raw Sheet'!D2 -> 46023 | FN4: ='Raw Sheet'!E2 -> 46037 | FP4: Employee: | FQ4: 37 | FR4: =VLOOKUP(FQ4,'Raw Sheet'!$A$8:$BK$59,'Raw Sheet'!$C$4,FALSE) -> I | FU4: Payroll period: | FV4: ='Raw Sheet'!D2 -> 46023 | FW4: ='Raw Sheet'!E2 -> 46037 | FY4: Employee: | FZ4: 48 | GA4: Arias, William Wallace Lao | GD4: Payroll period: | GE4: 45946 | GF4: 45961 | GH4: Employee: | GI4: 39 | GJ4: =VLOOKUP(GI4,'Raw Sheet'!$A$8:$BK$59,'Raw Sheet'!$C$4,FALSE) -> J | GM4: Payroll period: | GN4: ='Raw Sheet'!D2 -> 46023 | GO4: ='Raw Sheet'!E2 -> 46037 | GQ4: Employee: | GR4: 41 | GS4: =VLOOKUP(GR4,'Raw Sheet'!$A$8:$BK$59,'Raw Sheet'!$C$4,FALSE) -> K | GV4: Payroll period: | GW4: ='Raw Sheet'!D2 -> 46023 | GX4: ='Raw Sheet'!E2 -> 46037 | GZ4: Employee: | HA4: 42 | HB4: =VLOOKUP(HA4,'Raw Sheet'!$A$8:$BK$59,'Raw Sheet'!$C$4,FALSE) -> L | HE4: Payroll period: | HF4: ='Raw Sheet'!D2 -> 46023 | HG4: ='Raw Sheet'!E2 -> 46037 | HI4: Employee: | HJ4: 43 | HK4: =VLOOKUP(HJ4,'Raw Sheet'!$A$8:$BK$59,'Raw Sheet'!$C$4,FALSE) -> M | HN4: Payroll period: | HO4: ='Raw Sheet'!D2 -> 46023 | HP4: ='Raw Sheet'!E2 -> 46037 | HR4: Employee: | HS4: 44 | HT4: =VLOOKUP(HS4,'Raw Sheet'!$A$8:$BK$59,'Raw Sheet'!$C$4,FALSE) -> N | HW4: Payroll period: | HX4: ='Raw Sheet'!$D$2 -> 46023 | HY4: ='Raw Sheet'!$E$2 -> 46037 | IA4: Employee: | IB4: 45 | IC4: =VLOOKUP(IB4,'Raw Sheet'!$A$8:$BK$59,'Raw Sheet'!$C$4,FALSE) -> O | IF4: Payroll period: | IG4: ='Raw Sheet'!$D$2 -> 46023 | IH4: ='Raw Sheet'!$E$2 -> 46037 | IJ4: Employee: | IK4: 46 | IL4: =VLOOKUP(IK4,'Raw Sheet'!$A$8:$BK$59,'Raw Sheet'!$C$4,FALSE) -> P | IO4: Payroll period: | IP4: ='Raw Sheet'!$D$2 -> 46023 | IQ4: ='Raw Sheet'!$E$2 -> 46037 | IS4: Employee: | IT4: 47 | IU4: =VLOOKUP(IT4,'Raw Sheet'!$A$8:$BK$59,'Raw Sheet'!$C$4,FALSE) -> Q | IX4: Payroll period: | IY4: ='Raw Sheet'!$D$2 -> 46023 | IZ4: ='Raw Sheet'!$E$2 -> 46037 | JB4: Employee: | JC4: 49 | JD4: =VLOOKUP(JC4,'Raw Sheet'!$A$8:$BK$59,'Raw Sheet'!$C$4,FALSE) -> R | JG4: Payroll period: | JH4: ='Raw Sheet'!$D$2 -> 46023 | JI4: ='Raw Sheet'!$E$2 -> 46037 | JK4: Employee: | JL4: 50 | JM4: =VLOOKUP(JL4,'Raw Sheet'!$A$8:$BK$59,'Raw Sheet'!$C$4,FALSE) -> S | JP4: Payroll period: | JQ4: ='Raw Sheet'!$D$2 -> 46023 | JR4: ='Raw Sheet'!$E$2 -> 46037 | JT4: Employee: | JU4: 51 | JV4: =VLOOKUP(JU4,'Raw Sheet'!$A$8:$BK$59,'Raw Sheet'!$C$4,FALSE) -> T | JY4: Payroll period: | JZ4: ='Raw Sheet'!$D$2 -> 46023 | KA4: ='Raw Sheet'!$E$2 -> 46037 | KC4: Employee: | KD4: 52 | KE4: =VLOOKUP(KD4,'Raw Sheet'!$A$8:$BK$59,'Raw Sheet'!$C$4,FALSE) -> U | KH4: Payroll period: | KI4: ='Raw Sheet'!$D$2 -> 46023 | KJ4: ='Raw Sheet'!$E$2 -> 46037
A5: Position: | B5: Technical Support Engineer – L2 | J5: Position: | K5: Technical Support Engineer – L2 | S5: Position: | T5: Technical Support Engineer – L2 | AB5: Position: | AC5: Senior Service Lead - Technical Support | AK5: Position: | AL5: Service Desk Analyst L-1 | AT5: Position: | AU5: Technical Support Engineer – L2 | BC5: Position: | BD5: Technical Support Engineer – L2 | BL5: Position: | BM5: Technical Support Engineer – L2 | BU5: Position: | BV5: =VLOOKUP(BV4,'Raw Sheet'!$A$8:$BK$28,'Raw Sheet'!$F$4,FALSE) -> Service Desk Analyst-L1 | CD5: Position: | CE5: =VLOOKUP(CE4,'Raw Sheet'!$A$8:$BK$28,'Raw Sheet'!$F$4,FALSE) -> #N/A | CM5: Position: | CN5: Senior Security Analyst | CV5: Position: | CW5: =VLOOKUP(CW4,'Raw Sheet'!$A$8:$BK$28,'Raw Sheet'!$F$4,FALSE) -> Service Desk Analyst-L1 | DE5: Position: | DF5: Service Desk Analyst L-1 | DN5: Position: | DO5: =VLOOKUP(DO4,'Raw Sheet'!$A$8:$BK$28,'Raw Sheet'!$F$4,FALSE) -> Service Desk Analyst-L1 | DW5: Position: | DX5: =VLOOKUP(DX4,'Raw Sheet'!$A$8:$BK$28,'Raw Sheet'!$F$4,FALSE) -> Senior Operations Manager | EF5: Position: | EG5: =VLOOKUP(EG4,'Raw Sheet'!$A$8:$BK$28,'Raw Sheet'!$F$4,FALSE) -> Senior Project Manager | EO5: Position: | EP5: =VLOOKUP(EP4,'Raw Sheet'!$A$8:$BK$28,'Raw Sheet'!$F$4,FALSE) -> Service Desk Analyst-L1 | EX5: Position: | EY5: =VLOOKUP(EY4,'Raw Sheet'!$A$8:$BK$28,'Raw Sheet'!$F$4,FALSE) -> Service Desk Analyst-L1 | FG5: Position: | FH5: =VLOOKUP(FH4,'Raw Sheet'!$A$8:$BK$28,'Raw Sheet'!$F$4,FALSE) -> Senior Security Analyst | FP5: Position: | FQ5: =VLOOKUP(FQ4,'Raw Sheet'!$A$8:$BK$28,'Raw Sheet'!$F$4,FALSE) -> Lead Security Analyst | FY5: Position: | FZ5: Senior Security Analyst | GH5: Position: | GI5: =VLOOKUP(GI4,'Raw Sheet'!$A$8:$BK$28,'Raw Sheet'!$F$4,FALSE) -> Service Desk Analyst L-1 | GQ5: Position: | GR5: =VLOOKUP(GR4,'Raw Sheet'!$A$8:$BK$28,'Raw Sheet'!$F$4,FALSE) -> Service Desk Analyst L-1 | GZ5: Position: | HA5: =VLOOKUP(HA4,'Raw Sheet'!$A$8:$BK$28,'Raw Sheet'!$F$4,FALSE) -> Lead Security Analyst | HI5: Position: | HJ5: =VLOOKUP(HJ4,'Raw Sheet'!$A$8:$BK$28,'Raw Sheet'!$F$4,FALSE) -> Senior Security Analyst | HR5: Position: | HS5: =VLOOKUP(HS4,'Raw Sheet'!$A$8:$BK$28,'Raw Sheet'!$F$4,FALSE) -> Service Desk Analyst-L1 | IA5: Position: | IB5: =VLOOKUP(IB4,'Raw Sheet'!$A$8:$BK$28,'Raw Sheet'!$F$4,FALSE) -> Senior Security Analyst | IJ5: Position: | IK5: =VLOOKUP(IK4,'Raw Sheet'!$A$8:$BK$28,'Raw Sheet'!$F$4,FALSE) -> Senior Security Analyst | IS5: Position: | IT5: =VLOOKUP(IT4,'Raw Sheet'!$A$8:$BK$28,'Raw Sheet'!$F$4,FALSE) -> Service Desk Analyst L-1 | JB5: Position: | JC5: =VLOOKUP(JC4,'Raw Sheet'!$A$8:$BK$28,'Raw Sheet'!$F$4,FALSE) -> Service Desk Analyst L-1 | JK5: Position: | JL5: =VLOOKUP(JL4,'Raw Sheet'!$A$8:$BK$28,'Raw Sheet'!$F$4,FALSE) -> Senior Security Analyst | JT5: Position: | JU5: =VLOOKUP(JU4,'Raw Sheet'!$A$8:$BK$28,'Raw Sheet'!$F$4,FALSE) -> Service Desk Analyst L-1 | KC5: Position: | KD5: =VLOOKUP(KD4,'Raw Sheet'!$A$8:$BK$28,'Raw Sheet'!$F$4,FALSE) -> Service Desk Analyst L-1
A7: REGULAR EARNINGS | E7: TAXABLE OTHER EARNINGS | G7: NON-TAXABLE OTHER EARNINGS | J7: REGULAR EARNINGS | N7: TAXABLE OTHER EARNINGS | P7: NON-TAXABLE OTHER EARNINGS | S7: REGULAR EARNINGS | W7: TAXABLE OTHER EARNINGS | Y7: NON-TAXABLE OTHER EARNINGS | AB7: REGULAR EARNINGS | AF7: TAXABLE OTHER EARNINGS | AH7: NON-TAXABLE OTHER EARNINGS | AK7: REGULAR EARNINGS | AO7: TAXABLE OTHER EARNINGS | AQ7: NON-TAXABLE OTHER EARNINGS | AT7: REGULAR EARNINGS | AX7: TAXABLE OTHER EARNINGS | AZ7: NON-TAXABLE OTHER EARNINGS | BC7: REGULAR EARNINGS | BG7: TAXABLE OTHER EARNINGS | BI7: NON-TAXABLE OTHER EARNINGS | BL7: REGULAR EARNINGS | BP7: TAXABLE OTHER EARNINGS | BR7: NON-TAXABLE OTHER EARNINGS | BU7: REGULAR EARNINGS | BY7: TAXABLE OTHER EARNINGS | CA7: NON-TAXABLE OTHER EARNINGS | CD7: REGULAR EARNINGS | CH7: TAXABLE OTHER EARNINGS | CJ7: NON-TAXABLE OTHER EARNINGS | CM7: REGULAR EARNINGS | CQ7: TAXABLE OTHER EARNINGS | CS7: NON-TAXABLE OTHER EARNINGS | CV7: REGULAR EARNINGS | CZ7: TAXABLE OTHER EARNINGS | DB7: NON-TAXABLE OTHER EARNINGS | DE7: REGULAR EARNINGS | DI7: TAXABLE OTHER EARNINGS | DK7: NON-TAXABLE OTHER EARNINGS | DN7: REGULAR EARNINGS | DR7: TAXABLE OTHER EARNINGS | DT7: NON-TAXABLE OTHER EARNINGS | DW7: REGULAR EARNINGS | EA7: TAXABLE OTHER EARNINGS | EC7: NON-TAXABLE OTHER EARNINGS | EF7: REGULAR EARNINGS | EJ7: TAXABLE OTHER EARNINGS | EL7: NON-TAXABLE OTHER EARNINGS | EO7: REGULAR EARNINGS | ES7: TAXABLE OTHER EARNINGS | EU7: NON-TAXABLE OTHER EARNINGS | EX7: REGULAR EARNINGS | FB7: TAXABLE OTHER EARNINGS | FD7: NON-TAXABLE OTHER EARNINGS | FG7: REGULAR EARNINGS | FK7: TAXABLE OTHER EARNINGS | FM7: NON-TAXABLE OTHER EARNINGS | FP7: REGULAR EARNINGS | FT7: TAXABLE OTHER EARNINGS | FV7: NON-TAXABLE OTHER EARNINGS | FY7: REGULAR EARNINGS | GC7: TAXABLE OTHER EARNINGS | GE7: NON-TAXABLE OTHER EARNINGS | GH7: REGULAR EARNINGS | GL7: TAXABLE OTHER EARNINGS | GN7: NON-TAXABLE OTHER EARNINGS | GQ7: REGULAR EARNINGS | GU7: TAXABLE OTHER EARNINGS | GW7: NON-TAXABLE OTHER EARNINGS | GZ7: REGULAR EARNINGS | HD7: TAXABLE OTHER EARNINGS | HF7: NON-TAXABLE OTHER EARNINGS | HI7: REGULAR EARNINGS | HM7: TAXABLE OTHER EARNINGS | HO7: NON-TAXABLE OTHER EARNINGS | HR7: REGULAR EARNINGS | HV7: TAXABLE OTHER EARNINGS | HX7: NON-TAXABLE OTHER EARNINGS | IA7: REGULAR EARNINGS | IE7: TAXABLE OTHER EARNINGS | IG7: NON-TAXABLE OTHER EARNINGS | IJ7: REGULAR EARNINGS | IN7: TAXABLE OTHER EARNINGS | IP7: NON-TAXABLE OTHER EARNINGS | IS7: REGULAR EARNINGS | IW7: TAXABLE OTHER EARNINGS | IY7: NON-TAXABLE OTHER EARNINGS | JB7: REGULAR EARNINGS | JF7: TAXABLE OTHER EARNINGS | JH7: NON-TAXABLE OTHER EARNINGS | JK7: REGULAR EARNINGS | JO7: TAXABLE OTHER EARNINGS | JQ7: NON-TAXABLE OTHER EARNINGS | JT7: REGULAR EARNINGS | JX7: TAXABLE OTHER EARNINGS | JZ7: NON-TAXABLE OTHER EARNINGS | KC7: REGULAR EARNINGS | KG7: TAXABLE OTHER EARNINGS | KI7: NON-TAXABLE OTHER EARNINGS
C8: Days/Hours | D8: Amount | L8: Days/Hours | M8: Amount | U8: Days/Hours | V8: Amount | AD8: Days/Hours | AE8: Amount | AM8: Days/Hours | AN8: Amount | AV8: Days/Hours | AW8: Amount | BE8: Days/Hours | BF8: Amount | BN8: Days/Hours | BO8: Amount | BW8: Days/Hours | BX8: Amount | CF8: Days/Hours | CG8: Amount | CO8: Days/Hours | CP8: Amount | CX8: Days/Hours | CY8: Amount | DG8: Days/Hours | DH8: Amount | DP8: Days/Hours | DQ8: Amount | DY8: Days/Hours | DZ8: Amount | EH8: Days/Hours | EI8: Amount | EQ8: Days/Hours | ER8: Amount | EZ8: Days/Hours | FA8: Amount | FI8: Days/Hours | FJ8: Amount | FR8: Days/Hours | FS8: Amount | GA8: Days/Hours | GB8: Amount | GJ8: Days/Hours | GK8: Amount | GS8: Days/Hours | GT8: Amount | HB8: Days/Hours | HC8: Amount | HK8: Days/Hours | HL8: Amount | HT8: Days/Hours | HU8: Amount | IC8: Days/Hours | ID8: Amount | IL8: Days/Hours | IM8: Amount | IU8: Days/Hours | IV8: Amount | JD8: Days/Hours | JE8: Amount | JM8: Days/Hours | JN8: Amount | JV8: Days/Hours | JW8: Amount | KE8: Days/Hours | KF8: Amount
A9: Basic pay: | D9: 0 | J9: Basic pay: | M9: 0 | S9: Basic pay: | V9: 0 | AB9: Basic pay: | AE9: 0 | AK9: Basic pay: | AN9: 0 | AQ9: De Minimis Benefit | AR9: #REF! | AT9: Basic pay: | AW9: 0 | AZ9: De Minimis Benefit | BA9: 0 | BC9: Basic pay: | BF9: 0 | BI9: De Minimis Benefit | BJ9: #REF! | BL9: Basic pay: | BO9: 0 | BR9: De Minimis Benefit | BS9: #REF! | BU9: Basic pay: | BX9: =VLOOKUP(BV$4,'Raw Sheet'!$A$8:$BK$59,'Raw Sheet'!$H$4,FALSE) -> 18600 | CA9: De Minimis Benefit | CB9: ='Payroll Register'!T8 -> 1400 | CD9: Basic pay: | CG9: =VLOOKUP(CE$4,'Raw Sheet'!$A$8:$BK$59,'Raw Sheet'!$H$4,FALSE) -> #N/A | CM9: Basic pay: | CP9: 0 | CS9: De Minimis Benefit | CT9: #REF! | CV9: Basic pay: | CY9: =VLOOKUP(CW$4,'Raw Sheet'!$A$8:$BK$59,'Raw Sheet'!$H$4,FALSE) -> 22500 | DE9: Basic pay: | DH9: 0 | DK9: De Minimis Benefit | DL9: #REF! | DN9: Basic pay: | DQ9: =VLOOKUP(DO$4,'Raw Sheet'!$A$8:$BK$59,'Raw Sheet'!$H$4,FALSE) -> 21000 | DT9: De Minimis Benefit | DU9: ='Payroll Register'!T10 -> 1050 | DW9: Basic pay: | DZ9: =VLOOKUP(DX$4,'Raw Sheet'!$A$8:$BK$59,'Raw Sheet'!$H$4,FALSE) -> 84800 | EC9: De Minimis Benefit | ED9: 1400 | EF9: Basic pay: | EI9: =VLOOKUP(EG$4,'Raw Sheet'!$A$8:$BK$59,'Raw Sheet'!$H$4,FALSE) -> 127800 | EL9: De Minimis Benefit | EM9: 1400 | EO9: Basic pay: | ER9: =VLOOKUP(EP$4,'Raw Sheet'!$A$8:$BK$59,'Raw Sheet'!$H$4,FALSE) -> 13000 | EU9: De Minimis Benefit | EV9: ='Payroll Register'!T13 -> 780 | EX9: Basic pay: | FA9: =VLOOKUP(EY$4,'Raw Sheet'!$A$8:$BK$59,'Raw Sheet'!$H$4,FALSE) -> 14840 | FD9: De Minimis Benefit | FE9: 1400 | FG9: Basic pay: | FJ9: =VLOOKUP(FH$4,'Raw Sheet'!$A$8:$BK$59,'Raw Sheet'!$H$4,FALSE) -> 45050 | FM9: De Minimis Benefit | FN9: 1400 | FP9: Basic pay: | FS9: =VLOOKUP(FQ$4,'Raw Sheet'!$A$8:$BK$59,'Raw Sheet'!$H$4,FALSE) -> 66562.5 | FV9: De Minimis Benefit | FW9: 1400 | FY9: Basic pay: | GB9: 0 | GE9: De Minimis Benefit | GF9: #REF! | GH9: Basic pay: | GK9: =VLOOKUP(GI$4,'Raw Sheet'!$A$8:$BK$59,'Raw Sheet'!$H$4,FALSE) -> 13125 | GN9: De Minimis Benefit | GO9: 1400 | GQ9: Basic pay: | GT9: =VLOOKUP(GR$4,'Raw Sheet'!$A$8:$BK$59,'Raw Sheet'!$H$4,FALSE) -> 14323 | GW9: De Minimis Benefit | GX9: 1400 | GZ9: Basic pay: | HC9: =VLOOKUP(HA$4,'Raw Sheet'!$A$8:$BK$59,'Raw Sheet'!$H$4,FALSE) -> 93750 | HF9: De Minimis Benefit | HG9: 1400 | HI9: Basic pay: | HL9: =VLOOKUP(HJ$4,'Raw Sheet'!$A$8:$BK$59,'Raw Sheet'!$H$4,FALSE) -> 51408 | HO9: De Minimis Benefit | HP9: 1400 | HR9: Basic pay: | HU9: =VLOOKUP(HS$4,'Raw Sheet'!$A$8:$BK$59,'Raw Sheet'!$H$4,FALSE) -> 12350 | HX9: De Minimis Benefit | HY9: 1400 | IA9: Basic pay: | ID9: =VLOOKUP(IB$4,'Raw Sheet'!$A$8:$BK$59,'Raw Sheet'!$H$4,FALSE) -> 42500 | IG9: De Minimis Benefit | IH9: 1400 | IJ9: Basic pay: | IM9: =VLOOKUP(IK$4,'Raw Sheet'!$A$8:$BK$59,'Raw Sheet'!$H$4,FALSE) -> 65000 | IP9: De Minimis Benefit | IQ9: 1400 | IS9: Basic pay: | IV9: =VLOOKUP(IT$4,'Raw Sheet'!$A$8:$BK$59,'Raw Sheet'!$H$4,FALSE) -> 15000 | IY9: De Minimis Benefit | IZ9: 1400 | JB9: Basic pay: | JE9: =VLOOKUP(JC$4,'Raw Sheet'!$A$8:$BK$59,'Raw Sheet'!$H$4,FALSE) -> 14000 | JH9: De Minimis Benefit | JI9: 1400 | JK9: Basic pay: | JN9: =VLOOKUP(JL$4,'Raw Sheet'!$A$8:$BK$59,'Raw Sheet'!$H$4,FALSE) -> 42500 | JQ9: De Minimis Benefit | JR9: 1400 | JT9: Basic pay: | JW9: =VLOOKUP(JU$4,'Raw Sheet'!$A$8:$BK$59,'Raw Sheet'!$H$4,FALSE) -> 11000 | JZ9: De Minimis Benefit | KA9: 1400 | KC9: Basic pay: | KF9: =VLOOKUP(KD$4,'Raw Sheet'!$A$8:$BK$59,'Raw Sheet'!$H$4,FALSE) -> 9000 | KI9: De Minimis Benefit | KJ9: 1400
A10: Rate per hour | C10: 0 | J10: Rate per hour | L10: 0 | S10: Rate per hour | U10: 0 | AB10: Rate per hour | AD10: 0 | AK10: Rate per hour | AM10: 0 | AT10: Rate per hour | AV10: 0 | BC10: Rate per hour | BE10: 0 | BL10: Rate per hour | BN10: 0 | BU10: Rate per hour | BW10: =VLOOKUP(BV4,'Raw Sheet'!$A$8:$BK$59,'Raw Sheet'!$J$4,FALSE) -> 213.7931 | CD10: Rate per hour | CF10: =VLOOKUP(CE4,'Raw Sheet'!$A$8:$BK$59,'Raw Sheet'!$J$4,FALSE) -> #N/A | CM10: Rate per hour | CO10: 0 | CV10: Rate per hour | CX10: =VLOOKUP(CW4,'Raw Sheet'!$A$8:$BK$59,'Raw Sheet'!$J$4,FALSE) -> 258.62069 | DE10: Rate per hour | DG10: 0 | DN10: Rate per hour | DP10: =VLOOKUP(DO4,'Raw Sheet'!$A$8:$BK$59,'Raw Sheet'!$J$4,FALSE) -> 241.37931 | DW10: Rate per hour | DY10: =VLOOKUP(DX4,'Raw Sheet'!$A$8:$BK$59,'Raw Sheet'!$J$4,FALSE) -> 974.71264 | EF10: Rate per hour | EH10: =VLOOKUP(EG4,'Raw Sheet'!$A$8:$BK$59,'Raw Sheet'!$J$4,FALSE) -> 1468.9655 | EO10: Rate per hour | EQ10: =VLOOKUP(EP4,'Raw Sheet'!$A$8:$BK$59,'Raw Sheet'!$J$4,FALSE) -> 149.42529 | EU10: 2025 Tax Refund | EV10: ='Payroll Register'!AK13 -> 4333.3366 | EX10: Rate per hour | EZ10: =VLOOKUP(EY4,'Raw Sheet'!$A$8:$BK$59,'Raw Sheet'!$J$4,FALSE) -> 170.57471 | FG10: Rate per hour | FI10: =VLOOKUP(FH4,'Raw Sheet'!$A$8:$BK$59,'Raw Sheet'!$J$4,FALSE) -> 517.81609 | FP10: Rate per hour | FR10: =VLOOKUP(FQ4,'Raw Sheet'!$A$8:$BK$59,'Raw Sheet'!$J$4,FALSE) -> 765.08621 | FY10: Rate per hour | GA10: 0 | GH10: Rate per hour | GJ10: =VLOOKUP(GI4,'Raw Sheet'!$A$8:$BK$59,'Raw Sheet'!$J$4,FALSE) -> 150.86207 | GQ10: Rate per hour | GS10: =VLOOKUP(GR4,'Raw Sheet'!$A$8:$BK$59,'Raw Sheet'!$J$4,FALSE) -> 164.63218 | GZ10: Rate per hour | HB10: =VLOOKUP(HA4,'Raw Sheet'!$A$8:$BK$59,'Raw Sheet'!$J$4,FALSE) -> 1077.5862 | HI10: Rate per hour | HK10: =VLOOKUP(HJ4,'Raw Sheet'!$A$8:$BK$59,'Raw Sheet'!$J$4,FALSE) -> 590.89655 | HR10: Rate per hour | HT10: =VLOOKUP(HS4,'Raw Sheet'!$A$8:$BK$59,'Raw Sheet'!$J$4,FALSE) -> 141.95402 | IA10: Rate per hour | IC10: =VLOOKUP(IB4,'Raw Sheet'!$A$8:$BK$59,'Raw Sheet'!$J$4,FALSE) -> 488.50575 | IJ10: Rate per hour | IL10: =VLOOKUP(IK4,'Raw Sheet'!$A$8:$BK$59,'Raw Sheet'!$J$4,FALSE) -> 747.12644 | IS10: Rate per hour | IU10: =VLOOKUP(IT4,'Raw Sheet'!$A$8:$BK$59,'Raw Sheet'!$J$4,FALSE) -> 172.41379 | JB10: Rate per hour | JD10: =VLOOKUP(JC4,'Raw Sheet'!$A$8:$BK$59,'Raw Sheet'!$J$4,FALSE) -> 160.91954 | JK10: Rate per hour | JM10: =VLOOKUP(JL4,'Raw Sheet'!$A$8:$BK$59,'Raw Sheet'!$J$4,FALSE) -> 488.50575 | JT10: Rate per hour | JV10: =VLOOKUP(JU4,'Raw Sheet'!$A$8:$BK$59,'Raw Sheet'!$J$4,FALSE) -> 126.43678 | KC10: Rate per hour | KE10: =VLOOKUP(KD4,'Raw Sheet'!$A$8:$BK$59,'Raw Sheet'!$J$4,FALSE) -> 103.44828
A11: No. of hours Worked: | C11: 96 | J11: No. of hours Worked: | L11: 96 | S11: No. of hours Worked: | U11: 96 | AB11: No. of hours Worked: | AD11: 96 | AK11: No. of hours Worked: | AM11: 96 | AT11: No. of hours Worked: | AV11: 96 | BC11: No. of hours Worked: | BE11: 96 | BL11: No. of hours Worked: | BN11: 96 | BU11: No. of hours Worked: | BW11: =VLOOKUP(BV4,'Raw Sheet'!$A$8:$BK$28,63,FALSE) -> 72 | CD11: No. of hours Worked: | CF11: =VLOOKUP(CF4,'Raw Sheet'!L:BT,60,0) -> #N/A | CM11: No. of hours Worked: | CO11: 96 | CV11: No. of hours Worked: | CX11: =VLOOKUP(CW4,'Raw Sheet'!$A$8:$BK$28,63,0) -> 80 | DE11: No. of hours Worked: | DG11: 96 | DN11: No. of hours Worked: | DP11: =VLOOKUP(DO4,'Raw Sheet'!$A$8:$BK$28,63,0) -> 80 | DW11: No. of hours Worked: | DY11: =VLOOKUP(DX4,'Raw Sheet'!$A$8:$BK$28,63,0) -> 80 | EF11: No. of hours Worked: | EH11: =VLOOKUP(EG4,'Raw Sheet'!$A$8:$BK$28,63,0) -> 72 | EO11: No. of hours Worked: | EQ11: =VLOOKUP(EP4,'Raw Sheet'!$A$8:$BK$28,63,0) -> 80 | EX11: No. of hours Worked: | EZ11: =VLOOKUP(EY4,'Raw Sheet'!$A$8:$BK$28,63,0) -> 76 | FG11: No. of hours Worked: | FI11: =VLOOKUP(FH4,'Raw Sheet'!$A$8:$BK$28,63,0) -> 80 | FP11: No. of hours Worked: | FR11: =VLOOKUP(FR4,'Raw Sheet'!C:BK,60,0) -> 0 | FY11: No. of hours Worked: | GA11: 96 | GH11: No. of hours Worked: | GJ11: =VLOOKUP(GJ4,'Raw Sheet'!C:BK,60,0) -> 0 | GQ11: No. of hours Worked: | GS11: =VLOOKUP(GS4,'Raw Sheet'!C:BK,60,0) -> 0 | GZ11: No. of hours Worked: | HB11: =VLOOKUP(HB4,'Raw Sheet'!C:BK,60,0) -> 0 | HI11: No. of hours Worked: | HK11: ='Raw Sheet'!BK20 -> 0 | HR11: No. of hours Worked: | HT11: =VLOOKUP(HT4,'Raw Sheet'!C:BK,60,0) -> 0 | IA11: No. of hours Worked: | IC11: =VLOOKUP(IC4,'Raw Sheet'!C:BK,60,0) -> 0 | IJ11: No. of hours Worked: | IL11: =VLOOKUP(IL4,'Raw Sheet'!C:BK,60,0) -> 0 | IS11: No. of hours Worked: | IU11: =VLOOKUP(IU4,'Raw Sheet'!C:BK,60,0) -> -1379.3103 | JB11: No. of hours Worked: | JD11: =VLOOKUP(JD4,'Raw Sheet'!C:BK,60,0) -> 0 | JK11: No. of hours Worked: | JM11: =VLOOKUP(JM4,'Raw Sheet'!C:BK,60,0) -> 0 | JT11: No. of hours Worked: | JV11: ='Raw Sheet'!BK27 -> 68 | KC11: No. of hours Worked: | KE11: =VLOOKUP(KE4,'Raw Sheet'!C:BK,60,0) -> 0
A12: Night premium | C12: 0 | D12: =C10*10%*C12 -> 0 | J12: Night premium | L12: 0 | M12: =L10*10%*L12 -> 0 | S12: Night premium | U12: 0 | V12: =U10*10%*U12 -> 0 | AB12: Night premium | AD12: 0 | AE12: =AD10*10%*AD12 -> 0 | AK12: Night premium | AM12: 22 | AN12: =AM10*10%*AM12 -> 0 | AT12: Night premium | AV12: 22 | AW12: =AV10*10%*AV12 -> 0 | BC12: Night premium | BE12: 22 | BF12: =BE10*10%*BE12 -> 0 | BL12: Night premium | BN12: 22 | BO12: =BN10*10%*BN12 -> 0 | BU12: Night premium | BW12: =VLOOKUP(BV4,'Raw Sheet'!$A$8:$AI$28,35,0) -> 12 | BX12: =BW10*10%*BW12 -> 256.55172 | CD12: Night premium | CF12: 6 | CG12: =CF10*10%*CF12 -> #N/A | CM12: Night premium | CO12: 0 | CP12: =CO10*10%*CO12 -> 0 | CV12: Night premium | CX12: =VLOOKUP(CW4,'Raw Sheet'!$A$8:$AI$28,35,0) -> 30 | CY12: ='Payroll Register'!O9 -> 879.31034 | DE12: Night premium | DG12: 0 | DH12: =DG10*10%*DG12 -> 0 | DN12: Night premium | DP12: ='Raw Sheet'!AI10+'Raw Sheet'!AO10+'Raw Sheet'!BA10+'Raw Sheet'!BG10 -> 0 | DQ12: =DP10*10%*DP12 -> 0 | DW12: Night premium | DY12: ='Raw Sheet'!AI11+'Raw Sheet'!AO11+'Raw Sheet'!BA11+'Raw Sheet'!BG11 -> 0 | DZ12: =DY10*10%*DY12 -> 0 | EF12: Night premium | EH12: ='Raw Sheet'!AI12+'Raw Sheet'!AO12+'Raw Sheet'!BA12+'Raw Sheet'!BG12 -> 0 | EI12: =EH10*10%*EH12 -> 0 | EO12: Night premium | EQ12: ='Raw Sheet'!AI13+'Raw Sheet'!AO13+'Raw Sheet'!BA13+'Raw Sheet'!BG13 -> 0 | ER12: =EQ10*10%*EQ12 -> 0 | EX12: Night premium | EZ12: =VLOOKUP(EY4,'Raw Sheet'!A8:AI28,35,0) -> 9 | FA12: ='Payroll Register'!O14 -> 187.63218 | FG12: Night premium | FI12: ='Raw Sheet'!AI15+'Raw Sheet'!AO15+'Raw Sheet'!BA15+'Raw Sheet'!BG15 -> 0 | FJ12: =FI10*10%*FI12 -> 0 | FP12: Night premium | FR12: ='Raw Sheet'!AI16+'Raw Sheet'!AO16+'Raw Sheet'!BA16+'Raw Sheet'!BG16 -> 40 | FS12: =FR10*10%*FR12 -> 3060.3448 | FY12: Night premium | GA12: 32 | GB12: =GA10*10%*GA12 -> 0 | GH12: Night premium | GJ12: ='Raw Sheet'!AI17+'Raw Sheet'!AO17+'Raw Sheet'!BG17 -> 86 | GK12: =GJ10*10%*GJ12 -> 1297.4138 | GQ12: Night premium | GS12: ='Raw Sheet'!AI18+'Raw Sheet'!AO18+'Raw Sheet'!BG18 -> 80 | GT12: =GS10*10%*GS12 -> 1317.0575 | GZ12: Night premium | HB12: ='Raw Sheet'!AI19 -> 20 | HC12: ='Payroll Register'!O19 -> 2155.1724 | HI12: Night premium | HK12: ='Raw Sheet'!AI20+'Raw Sheet'!AO20+'Raw Sheet'!BG20 -> 0 | HL12: =HK10*10%*HK12 -> 0 | HR12: Night premium | HT12: ='Raw Sheet'!AI21+'Raw Sheet'!AO21+'Raw Sheet'!BG21 -> 64 | HU12: =HT10*10%*HT12 -> 908.50575 | IA12: Night premium | IC12: ='Raw Sheet'!AI22+'Raw Sheet'!AO22+'Raw Sheet'!BG22 -> 72 | ID12: =IC10*10%*IC12 -> 3517.2414 | IJ12: Night premium | IL12: ='Raw Sheet'!AI23+'Raw Sheet'!AO23+'Raw Sheet'!BG23 -> 48 | IM12: =IL10*10%*IL12 -> 3586.2069 | IS12: Night premium | IU12: ='Raw Sheet'!AI24+'Raw Sheet'!AO24+'Raw Sheet'!BG24 -> 16 | IV12: =IU10*10%*IU12 -> 275.86207 | JB12: Night premium | JD12: ='Raw Sheet'!AI25+'Raw Sheet'!AO25+'Raw Sheet'!BG25 -> 20 | JE12: =JD10*10%*JD12 -> 321.83908 | JK12: Night premium | JM12: ='Raw Sheet'!AI26+'Raw Sheet'!AO26+'Raw Sheet'!BG26 -> 32 | JN12: =JM10*10%*JM12 -> 1563.2184 | JT12: Night premium | JV12: ='Raw Sheet'!AI27+'Raw Sheet'!AO27+'Raw Sheet'!BG27 -> 24 | JW12: =JV10*10%*JV12 -> 303.44828 | KC12: Night premium | KE12: ='Raw Sheet'!AI28+'Raw Sheet'!AO28+'Raw Sheet'!BG28 -> 22 | KF12: =KE10*10%*KE12 -> 227.58621
A13: Less: Absences | C13: 0 | D13: 0 | J13: Less: Absences | L13: 0 | M13: 0 | S13: Less: Absences | U13: 0 | V13: 0 | AB13: Less: Absences | AD13: 0 | AE13: 0 | AK13: Less: Absences | AM13: 0 | AN13: 0 | AT13: Less: Absences | AV13: 0 | AW13: 0 | BC13: Less: Absences | BE13: 0 | BF13: 0 | BL13: Less: Absences | BN13: 0 | BO13: 0 | BU13: Less: Absences | BW13: 0 | BX13: 0 | CD13: Less: Absences | CF13: 72 | CG13: ='Payroll Register'!#REF! -> #REF! | CM13: Less: Absences | CO13: 0 | CP13: 0 | CV13: Less: Absences | CX13: 0 | CY13: 0 | DE13: Less: Absences | DG13: 0 | DH13: 0 | DN13: Less: Absences | DP13: 0 | DQ13: 0 | DW13: Less: Absences | DY13: 0 | DZ13: 0 | EF13: Less: Absences | EH13: 0 | EI13: 0 | EO13: Less: Absences | EQ13: 0 | ER13: 0 | EX13: Less: Absences | EZ13: 0 | FA13: 0 | FG13: Less: Absences | FI13: 0 | FJ13: 0 | FP13: Less: Absences | FR13: 0 | FS13: 0 | FY13: Less: Absences | GA13: 0 | GB13: 0 | GH13: Less: Absences | GJ13: 0 | GK13: 0 | GQ13: Less: Absences | GS13: 0 | GT13: 0 | GZ13: Less: Absences | HB13: 0 | HC13: 0 | HI13: Less: Absences | HK13: 3 | HL13: =-'Payroll Register'!P20 -> 14181.517 | HR13: Less: Absences | HT13: 0 | HU13: 0 | IA13: Less: Absences | IC13: 0 | ID13: 0 | IJ13: Less: Absences | IL13: 0 | IM13: 0 | IS13: Less: Absences | IU13: 0 | IV13: 0 | JB13: Less: Absences | JD13: 0 | JE13: 0 | JK13: Less: Absences | JM13: 0 | JN13: 0 | JT13: Less: Absences | JV13: 0 | KC13: Less: Absences | KE13: 0 | KF13: 0
A14: Late/Undertime | C14: 0 | D14: 0 | J14: Late/Undertime | L14: 0 | M14: 0 | S14: Late/Undertime | U14: 0 | V14: 0 | AB14: Late/Undertime | AD14: 0 | AE14: 0 | AK14: Late/Undertime | AM14: 0 | AN14: 0 | AT14: Late/Undertime | AV14: 0 | AW14: 0 | BC14: Late/Undertime | BE14: 0 | BF14: 0 | BL14: Late/Undertime | BN14: 0 | BO14: 0 | BU14: Late/Undertime | BW14: 0 | BX14: 0 | CD14: Late/Undertime | CF14: 0 | CG14: 0 | CM14: Late/Undertime | CO14: 0 | CP14: 0 | CV14: Late/Undertime | CX14: 0 | CY14: 0 | DE14: Late/Undertime | DG14: 0 | DH14: 0 | DN14: Late/Undertime | DP14: 0 | DQ14: 0 | DW14: Late/Undertime | DY14: 0 | DZ14: 0 | EF14: Late/Undertime | EH14: 0 | EI14: 0 | EO14: Late/Undertime | EQ14: 0 | ER14: 0 | EX14: Late/Undertime | EZ14: 0 | FA14: 0 | FG14: Late/Undertime | FI14: 0 | FJ14: 0 | FP14: Late/Undertime | FR14: 0 | FS14: 0 | FY14: Late/Undertime | GA14: 0 | GB14: 0 | GH14: Late/Undertime | GJ14: 0 | GK14: 0 | GQ14: Late/Undertime | GS14: 0 | GT14: 0 | GZ14: Late/Undertime | HB14: 0 | HC14: 0 | HI14: Late/Undertime | HK14: 0 | HL14: 0 | HR14: Late/Undertime | HT14: 0 | HU14: 0 | IA14: Late/Undertime | IC14: 0 | ID14: 0 | IJ14: Late/Undertime | IL14: 0 | IM14: 0 | IS14: Late/Undertime | IU14: 0 | IV14: 0 | JB14: Late/Undertime | JD14: 0 | JE14: ='Payroll Register'!P25 -> 0 | JK14: Late/Undertime | JM14: 0 | JN14: 0 | JT14: Late/Undertime | JV14: ='Raw Sheet'!AA27 -> 2 | JW14: =-'Payroll Register'!P27 -> 252.87356 | KC14: Late/Undertime | KE14: 0 | KF14: 0
A15: Net basic pay | D15: =SUM(D9:D12)-SUM(D13:D14) -> 0 | J15: Net basic pay | M15: =SUM(M9:M12)-SUM(M13:M14) -> 0 | S15: Net basic pay | V15: =SUM(V9:V12)-SUM(V13:V14) -> 0 | AB15: Net basic pay | AE15: =SUM(AE9:AE12)-SUM(AE13:AE14) -> 0 | AK15: Net basic pay | AN15: =SUM(AN9:AN12)-SUM(AN13:AN14) -> 0 | AT15: Net basic pay | AW15: =SUM(AW9:AW12)-SUM(AW13:AW14) -> 0 | BC15: Net basic pay | BF15: =SUM(BF9:BF12)-SUM(BF13:BF14) -> 0 | BL15: Net basic pay | BO15: =SUM(BO9:BO12)-SUM(BO13:BO14) -> 0 | BU15: Net basic pay | BX15: =SUM(BX9:BX12)-SUM(BX13:BX14) -> 18856.552 | CD15: Net basic pay | CG15: =SUM(CG9:CG12)+SUM(CG13:CG14) -> #N/A | CM15: Net basic pay | CP15: =SUM(CP9:CP12)-SUM(CP13:CP14) -> 0 | CV15: Net basic pay | CY15: =SUM(CY9:CY12)-SUM(CY13:CY14) -> 23379.31 | DE15: Net basic pay | DH15: =SUM(DH9:DH12)-SUM(DH13:DH14) -> 0 | DN15: Net basic pay | DQ15: =SUM(DQ9:DQ12)-SUM(DQ13:DQ14) -> 21000 | DW15: Net basic pay | DZ15: =SUM(DZ9:DZ12)-SUM(DZ13:DZ14) -> 84800 | EF15: Net basic pay | EI15: =SUM(EI9:EI12)-SUM(EI13:EI14) -> 127800 | EO15: Net basic pay | ER15: =SUM(ER9:ER12)-SUM(ER13:ER14) -> 13000 | EX15: Net basic pay | FA15: =SUM(FA9:FA12)-SUM(FA13:FA14) -> 15027.632 | FG15: Net basic pay | FJ15: =SUM(FJ9:FJ12)-SUM(FJ13:FJ14) -> 45050 | FP15: Net basic pay | FS15: =SUM(FS9:FS12)-SUM(FS13:FS14) -> 69622.845 | FY15: Net basic pay | GB15: =SUM(GB9:GB12)-SUM(GB13:GB14) -> 0 | GH15: Net basic pay | GK15: =SUM(GK9:GK12)-SUM(GK13:GK14) -> 14422.414 | GQ15: Net basic pay | GT15: =SUM(GT9:GT12)-SUM(GT13:GT14) -> 15640.057 | GZ15: Net basic pay | HC15: =SUM(HC9:HC12)-SUM(HC13:HC14) -> 95905.172 | HI15: Net basic pay | HL15: =SUM(HL9:HL12)-SUM(HL13:HL14) -> 37226.483 | HR15: Net basic pay | HU15: =SUM(HU9:HU12)-SUM(HU13:HU14) -> 13258.506 | IA15: Net basic pay | ID15: =SUM(ID9:ID12)-SUM(ID13:ID14) -> 46017.241 | IJ15: Net basic pay | IM15: =SUM(IM9:IM12)-SUM(IM13:IM14) -> 68586.207 | IS15: Net basic pay | IV15: =SUM(IV9:IV12)-SUM(IV13:IV14) -> 15275.862 | JB15: Net basic pay | JE15: =SUM(JE9:JE12)+SUM(JE13:JE14) -> 14321.839 | JK15: Net basic pay | JN15: =SUM(JN9:JN12)-SUM(JN13:JN14) -> 44063.218 | JT15: Net basic pay | JW15: =SUM(JW9:JW12)-SUM(JW14:JW14) -> 11050.575 | KC15: Net basic pay | KF15: =SUM(KF9:KF12)-SUM(KF13:KF14) -> 9227.5862
A17: Reg. OT<=10 hrs | C17: 0 | D17: 0 | J17: Reg. OT<=10 hrs | L17: 0 | M17: 0 | S17: Reg. OT<=10 hrs | U17: 0 | V17: 0 | AB17: Reg. OT<=10 hrs | AD17: 0 | AE17: 0 | AK17: Reg. OT<=10 hrs | AM17: 0 | AN17: 0 | AT17: Reg. OT<=10 hrs | AV17: 0 | AW17: 0 | BC17: Reg. OT<=10 hrs | BE17: 0 | BF17: 0 | BL17: Reg. OT<=10 hrs | BN17: 0 | BO17: 0 | BU17: Reg. OT<=10 hrs | BW17: 0 | BX17: 0 | CD17: Reg. OT<=10 hrs | CF17: 0 | CG17: 0 | CM17: Reg. OT<=10 hrs | CO17: 0 | CP17: 0 | CV17: Reg. OT<=10 hrs | CX17: =VLOOKUP(CW4,'Raw Sheet'!$A$8:$AG$29,33,0) -> 9 | CY17: =VLOOKUP(CW4,'Raw Sheet'!$A$8:$AH$28,34,0) -> 2909.4828 | DE17: Reg. OT<=10 hrs | DG17: 0 | DH17: 0 | DN17: Reg. OT<=10 hrs | DP17: =VLOOKUP(DO4,'Raw Sheet'!$A$8:$AG$29,33,0) -> 12 | DQ17: =VLOOKUP(DO4,'Raw Sheet'!$A$8:$AH$28,34,0) -> 3620.6897 | DW17: Reg. OT<=10 hrs | DY17: 0 | DZ17: 0 | EF17: Reg. OT<=10 hrs | EH17: 0 | EI17: 0 | EO17: Reg. OT<=10 hrs | EQ17: 0 | ER17: 0 | EX17: Reg. OT<=10 hrs | EZ17: =VLOOKUP(EY4,'Raw Sheet'!$A$8:$AG$28,33,0) -> 0 | FA17: =VLOOKUP(EY4,'Raw Sheet'!$A$8:$AH$28,34,0) -> 0 | FG17: Reg. OT<=10 hrs | FI17: 0 | FJ17: 0 | FP17: Reg. OT<=10 hrs | FR17: 0 | FS17: 0 | FY17: Reg. OT<=10 hrs | GA17: 0 | GB17: 0 | GH17: Reg. OT<=10 hrs | GJ17: 0 | GK17: 0 | GQ17: Reg. OT<=10 hrs | GS17: 0 | GT17: 0 | GZ17: Reg. OT<=10 hrs | HB17: 0 | HC17: 0 | HI17: Reg. OT<=10 hrs | HK17: 0 | HL17: 0 | HR17: Reg. OT<=10 hrs | HT17: 0 | HU17: 0 | IA17: Reg. OT<=10 hrs | IC17: 0 | ID17: 0 | IJ17: Reg. OT<=10 hrs | IL17: 0 | IM17: 0 | IS17: Reg. OT<=10 hrs | IU17: 0 | IV17: 0 | JB17: Reg. OT<=10 hrs | JD17: 0 | JE17: 0 | JK17: Reg. OT<=10 hrs | JM17: 0 | JN17: 0 | JT17: Reg. OT<=10 hrs | JV17: ='Raw Sheet'!BC27 -> 8 | JW17: ='Payroll Register'!Q27 -> 1011.4943 | KC17: Reg. OT<=10 hrs | KE17: 0 | KF17: 0
A18: Reg. OT>10 hrs | C18: =IF(C17>0,C19,0) -> 0 | D18: 0 | E18: GROSS PAY | H18: =D15+(SUM(D17:D29)+(F9+F10+F11)+SUM(H9:H17)) -> 0 | J18: Reg. OT>10 hrs | L18: =IF(L17>0,L19,0) -> 0 | M18: 0 | N18: GROSS PAY | Q18: =M15+(SUM(M17:M29)+(O9+O10+O11)+SUM(Q9:Q17)) -> 0 | S18: Reg. OT>10 hrs | U18: =IF(U17>0,U19,0) -> 0 | V18: 0 | W18: GROSS PAY | Z18: =V15+(SUM(V17:V29)+(X9+X10+X11)+SUM(Z9:Z17)) -> 0 | AB18: Reg. OT>10 hrs | AD18: =IF(AD17>0,AD19,0) -> 0 | AE18: 0 | AF18: GROSS PAY | AI18: =AE15+(SUM(AE17:AE29)+(AG9+AG10+AG11)+SUM(AI9:AI17)) -> 0 | AK18: Reg. OT>10 hrs | AM18: =IF(AM17>0,AM19,0) -> 0 | AN18: 0 | AO18: GROSS PAY | AR18: =AN15+(SUM(AN17:AN29)+(AP9+AP10+AP11)+SUM(AR9:AR17)) -> #REF! | AT18: Reg. OT>10 hrs | AV18: =IF(AV17>0,AV19,0) -> 0 | AW18: 0 | AX18: GROSS PAY | BA18: =AW15+(SUM(AW17:AW29)+(AY9+AY10+AY11)+SUM(BA9:BA17)) -> 0 | BC18: Reg. OT>10 hrs | BE18: =IF(BE17>0,BE19,0) -> 0 | BF18: 0 | BG18: GROSS PAY | BJ18: =BF15+(SUM(BF17:BF29)+(BH9+BH10+BH11)+SUM(BJ9:BJ17)) -> #REF! | BL18: Reg. OT>10 hrs | BN18: =IF(BN17>0,BN19,0) -> 0 | BO18: 0 | BP18: GROSS PAY | BS18: =BO15+(SUM(BO17:BO29)+(BQ9+BQ10+BQ11)+SUM(BS9:BS17)) -> #REF! | BU18: Reg. OT>10 hrs | BW18: =IF(BW17>0,BW19,0) -> 0 | BX18: 0 | BY18: GROSS PAY | CB18: =BX15+(SUM(BX17:BX29)+(BZ9+BZ10+BZ11)+SUM(CB9:CB17)) -> 20256.552 | CD18: Reg. OT>10 hrs | CF18: =IF(CF17>0,CF19,0) -> 0 | CG18: 0 | CH18: GROSS PAY | CK18: =CG15+(SUM(CG17:CG29)+(CI9+CI10+CI11)+SUM(CK9:CK17)) -> #N/A | CM18: Reg. OT>10 hrs | CO18: =IF(CO17>0,CO19,0) -> 0 | CP18: 0 | CQ18: GROSS PAY | CT18: =CP15+(SUM(CP17:CP29)+(CR9+CR10+CR11)+SUM(CT9:CT17)) -> #REF! | CV18: Reg. OT>10 hrs | CX18: =IF(CX17>0,CX19,0) -> 0 | CY18: 0 | CZ18: GROSS PAY | DC18: =CY15+(SUM(CY17:CY29)+(DA9+DA10+DA11)+SUM(DC9:DC17)) -> 28357.759 | DE18: Reg. OT>10 hrs | DG18: =IF(DG17>0,DG19,0) -> 0 | DH18: 0 | DI18: GROSS PAY | DL18: =DH15+(SUM(DH17:DH29)+(DJ9+DJ10+DJ11)+SUM(DL9:DL17)) -> #REF! | DN18: Reg. OT>10 hrs | DP18: 0 | DQ18: 0 | DR18: GROSS PAY | DU18: =DQ15+(SUM(DQ17:DQ29)+(DS9+DS10+DS11)+SUM(DU9:DU17)) -> 25670.69 | DW18: Reg. OT>10 hrs | DY18: =IF(DY17>0,DY19,0) -> 0 | DZ18: 0 | EA18: GROSS PAY | ED18: =DZ15+(SUM(DZ17:DZ29)+(EB9+EB10+EB11)+SUM(ED9:ED17)) -> 86200 | EF18: Reg. OT>10 hrs | EH18: =IF(EH17>0,EH19,0) -> 0 | EI18: 0 | EJ18: GROSS PAY | EM18: =EI15+(SUM(EI17:EI29)+(EK9+EK10+EK11)+SUM(EM9:EM17)) -> 129200 | EO18: Reg. OT>10 hrs | EQ18: =IF(EQ17>0,EQ19,0) -> 0 | ER18: 0 | ES18: GROSS PAY | EV18: =ER15+(SUM(ER17:ER29)+(ET9+ET10+ET11)+SUM(EV9:EV17)) -> 20025.98 | EX18: Reg. OT>10 hrs | EZ18: 0 | FA18: 0 | FB18: GROSS PAY | FE18: =FA15+(SUM(FA17:FA29)+(FC9+FC10+FC11)+SUM(FE9:FE17)) -> 18610.989 | FG18: Reg. OT>10 hrs | FI18: =IF(FI17>0,FI19,0) -> 0 | FJ18: 0 | FK18: GROSS PAY | FN18: =FJ15+(SUM(FJ17:FJ29)+(FL9+FL10+FL11)+SUM(FN9:FN17)) -> 46450 | FP18: Reg. OT>10 hrs | FR18: =IF(FR17>0,FR19,0) -> 0 | FS18: 0 | FT18: GROSS PAY | FW18: =FS15+(SUM(FS17:FS29)+(FU9+FU10+FU11)+SUM(FW9:FW17)) -> 71022.845 | FY18: Reg. OT>10 hrs | GA18: =IF(GA17>0,GA19,0) -> 0 | GB18: 0 | GC18: GROSS PAY | GF18: =GB15+(SUM(GB17:GB29)+(GD9+GD10+GD11)+SUM(GF9:GF17)) -> #REF! | GH18: Reg. OT>10 hrs | GJ18: 12 | GK18: ='Payroll Register'!N17 -> 3439.6552 | GL18: GROSS PAY | GO18: =GK15+(SUM(GK17:GK29)+(GM9+GM10+GM11)+SUM(GO9:GO17)) -> 19262.069 | GQ18: Reg. OT>10 hrs | GS18: =IF(GS17>0,GS19,0) -> 0 | GT18: 0 | GU18: GROSS PAY | GX18: =GT15+(SUM(GT17:GT29)+(GV9+GV10+GV11)+SUM(GX9:GX17)) -> 17369.322 | GZ18: Reg. OT>10 hrs | HB18: =IF(HB17>0,HB19,0) -> 0 | HC18: 0 | HD18: GROSS PAY | HG18: =HC15+(SUM(HC17:HC29)+(HE9+HE10+HE11)+SUM(HG9:HG17)) -> 97305.172 | HI18: Reg. OT>10 hrs | HK18: 0 | HL18: =VLOOKUP(HJ4,'Raw Sheet'!$A$8:$BL$29,33,FALSE) -> 0 | HM18: GROSS PAY | HP18: =HL15+(SUM(HL17:HL29)+(HN9+HN10+HN11)+SUM(HP9:HP17)) -> 38626.483 | HR18: Reg. OT>10 hrs | HT18: 0 | HU18: =VLOOKUP(HS4,'Raw Sheet'!$A$8:$BL$29,33,FALSE) -> 0 | HV18: GROSS PAY | HY18: =HU15+(SUM(HU17:HU29)+(HW9+HW10+HW11)+SUM(HY9:HY17)) -> 15084.368 | IA18: Reg. OT>10 hrs | IC18: 0 | ID18: ='Payroll Register'!N22 -> 7474.1379 | IE18: GROSS PAY | IH18: =ID15+(SUM(ID17:ID29)+(IF9+IF10+IF11)+SUM(IH9:IH17)) -> 54891.379 | IJ18: Reg. OT>10 hrs | IL18: ='Raw Sheet'!AG23 -> 6 | IM18: ='Payroll Register'!N23 -> 5715.5172 | IN18: GROSS PAY | IQ18: =IM15+(SUM(IM17:IM29)+(IO9+IO10+IO11)+SUM(IQ9:IQ17)) -> 75701.724 | IS18: Reg. OT>10 hrs | IU18: 0 | IV18: =VLOOKUP(IT4,'Raw Sheet'!$A$8:$BL$29,33,FALSE) -> 0 | IW18: GROSS PAY | IZ18: =IV15+(SUM(IV17:IV29)+(IX9+IX10+IX11)+SUM(IZ9:IZ17)) -> 16675.862 | JB18: Reg. OT>10 hrs | JD18: 0 | JE18: =VLOOKUP(JC4,'Raw Sheet'!$A$8:$BL$29,33,FALSE) -> 0 | JF18: GROSS PAY | JI18: =JE15+(SUM(JE17:JE29)+(JG9+JG10+JG11)+SUM(JI9:JI17)) -> 15721.839 | JK18: Reg. OT>10 hrs | JM18: ='Raw Sheet'!AG26 -> 6 | JN18: ='Payroll Register'!N26 -> 3737.069 | JO18: GROSS PAY | JR18: =JN15+(SUM(JN17:JN29)+(JP9+JP10+JP11)+SUM(JR9:JR17)) -> 49200.287 | JT18: Reg. OT>10 hrs | JV18: 0 | JW18: =VLOOKUP(JU4,'Raw Sheet'!$A$8:$BL$29,33,FALSE) -> 0 | JX18: GROSS PAY | KA18: =JW15+(SUM(JW17:JW29)+(JY9+JY10+JY11)+SUM(KA9:KA17)) -> 13462.069 | KC18: Reg. OT>10 hrs | KE18: 0 | KF18: =VLOOKUP(KD4,'Raw Sheet'!$A$8:$BL$29,33,FALSE) -> 0 | KG18: GROSS PAY | KJ18: =KF15+(SUM(KF17:KF29)+(KH9+KH10+KH11)+SUM(KJ9:KJ17)) -> 11455.172
A19: Night premium | C19: 0 | D19: 0 | J19: Night premium | L19: 0 | M19: 0 | S19: Night premium | U19: 0 | V19: 0 | AB19: Night premium | AD19: 0 | AE19: 0 | AK19: Night premium | AM19: -22 | AN19: 0 | AT19: Night premium | AV19: -22 | AW19: 0 | BC19: Night premium | BE19: -22 | BF19: 0 | BL19: Night premium | BN19: -22 | BO19: 0 | BU19: Night premium | BW19: 0 | BX19: 0 | CD19: Night premium | CF19: =IF(CF18>0,CF20,0) -> 0 | CG19: 0 | CM19: Night premium | CO19: 0 | CP19: 0 | CV19: Night premium | CX19: 0 | CY19: 0 | DE19: Night premium | DG19: 0 | DH19: 0 | DN19: Night premium | DP19: =IF(DP18>0,DP20,0) -> 0 | DQ19: 0 | DW19: Night premium | DY19: =IF(DY18>0,DY20,0) -> 0 | DZ19: 0 | EF19: Night premium | EH19: =IF(EH18>0,EH20,0) -> 0 | EI19: 0 | EO19: Night premium | EQ19: =IF(EQ18>0,EQ20,0) -> 0 | ER19: 0 | EX19: Night premium | EZ19: =IF(EZ18>0,EZ20,0) -> 0 | FA19: 0 | FG19: Night premium | FI19: =IF(FI18>0,FI20,0) -> 0 | FJ19: 0 | FP19: Night premium | FR19: =IF(FR18>0,FR20,0) -> 0 | FS19: 0 | FY19: Night premium | GA19: -32 | GB19: 0 | GH19: Night premium | GJ19: =IF(GJ18>0,GJ20,0) -> 0 | GK19: 0 | GQ19: Night premium | GS19: =IF(GS18>0,GS20,0) -> 0 | GT19: 0 | GZ19: Night premium | HB19: =IF(HB18>0,HB20,0) -> 0 | HC19: 0 | HI19: Night premium | HK19: =IF(HK18>0,HK20,0) -> 0 | HL19: 0 | HR19: Night premium | HT19: =IF(HT18>0,HT20,0) -> 0 | HU19: 0 | IA19: Night premium | IC19: =IF(IC18>0,IC20,0) -> 0 | ID19: 0 | IJ19: Night premium | IL19: =IF(IL18>0,IL20,0) -> 0 | IM19: 0 | IS19: Night premium | IU19: =IF(IU18>0,IU20,0) -> 0 | IV19: 0 | JB19: Night premium | JD19: =IF(JD18>0,JD20,0) -> 0 | JE19: 0 | JK19: Night premium | JM19: =IF(JM18>0,JM20,0) -> 0 | JN19: 0 | JT19: Night premium | JV19: =IF(JV18>0,JV20,0) -> 0 | JW19: 0 | KC19: Night premium | KE19: =IF(KE18>0,KE20,0) -> 0 | KF19: 0
A20: Sat OT<=10 hrs | C20: 0 | D20: 0 | E20: REGULAR DEDUCTIONS | G20: LOANS/ADVANCES | J20: Sat OT<=10 hrs | L20: 0 | M20: 0 | N20: REGULAR DEDUCTIONS | P20: LOANS/ADVANCES | S20: Sat OT<=10 hrs | U20: 0 | V20: 0 | W20: REGULAR DEDUCTIONS | Y20: LOANS/ADVANCES | AB20: Sat OT<=10 hrs | AD20: 0 | AE20: 0 | AF20: REGULAR DEDUCTIONS | AH20: LOANS/ADVANCES | AK20: Sat OT<=10 hrs | AM20: 0 | AN20: 0 | AO20: REGULAR DEDUCTIONS | AQ20: LOANS/ADVANCES | AT20: Sat OT<=10 hrs | AV20: 0 | AW20: 0 | AX20: REGULAR DEDUCTIONS | AZ20: LOANS/ADVANCES | BC20: Sat OT<=10 hrs | BE20: 0 | BF20: 0 | BG20: REGULAR DEDUCTIONS | BI20: LOANS/ADVANCES | BL20: Sat OT<=10 hrs | BN20: 0 | BO20: 0 | BP20: REGULAR DEDUCTIONS | BR20: LOANS/ADVANCES | BU20: Sat OT<=10 hrs | BW20: 0 | BX20: 0 | BY20: REGULAR DEDUCTIONS | CA20: LOANS/ADVANCES | CD20: Sat OT<=10 hrs | CF20: 0 | CG20: 0 | CH20: REGULAR DEDUCTIONS | CJ20: LOANS/ADVANCES | CM20: Sat OT<=10 hrs | CO20: 0 | CP20: 0 | CQ20: REGULAR DEDUCTIONS | CS20: LOANS/ADVANCES | CV20: Sat OT<=10 hrs | CX20: 0 | CY20: 0 | CZ20: REGULAR DEDUCTIONS | DB20: LOANS/ADVANCES | DE20: Sat OT<=10 hrs | DG20: 0 | DH20: 0 | DI20: REGULAR DEDUCTIONS | DK20: LOANS/ADVANCES | DN20: Sat OT<=10 hrs | DP20: 0 | DQ20: 0 | DR20: REGULAR DEDUCTIONS | DT20: LOANS/ADVANCES | DW20: Sat OT<=10 hrs | DY20: 0 | DZ20: 0 | EA20: REGULAR DEDUCTIONS | EC20: LOANS/ADVANCES | EF20: Sat OT<=10 hrs | EH20: 0 | EI20: 0 | EJ20: REGULAR DEDUCTIONS | EL20: LOANS/ADVANCES | EO20: Sat OT<=10 hrs | EQ20: 0 | ER20: 0 | ES20: REGULAR DEDUCTIONS | EU20: LOANS/ADVANCES | EX20: Sat OT<=10 hrs | EZ20: 0 | FA20: 0 | FB20: REGULAR DEDUCTIONS | FD20: LOANS/ADVANCES | FG20: Sat OT<=10 hrs | FI20: 0 | FJ20: 0 | FK20: REGULAR DEDUCTIONS | FM20: LOANS/ADVANCES | FP20: Sat OT<=10 hrs | FR20: 0 | FS20: 0 | FT20: REGULAR DEDUCTIONS | FV20: LOANS/ADVANCES | FY20: Sat OT<=10 hrs | GA20: 0 | GB20: 0 | GC20: REGULAR DEDUCTIONS | GE20: LOANS/ADVANCES | GH20: Sat OT<=10 hrs | GJ20: 0 | GK20: 0 | GL20: REGULAR DEDUCTIONS | GN20: LOANS/ADVANCES | GQ20: Sat OT<=10 hrs | GS20: 0 | GT20: 0 | GU20: REGULAR DEDUCTIONS | GW20: LOANS/ADVANCES | GZ20: Sat OT<=10 hrs | HB20: 0 | HC20: 0 | HD20: REGULAR DEDUCTIONS | HF20: LOANS/ADVANCES | HI20: Sat OT<=10 hrs | HK20: 0 | HL20: 0 | HM20: REGULAR DEDUCTIONS | HO20: LOANS/ADVANCES | HR20: Sat OT<=10 hrs | HT20: 0 | HU20: 0 | HV20: REGULAR DEDUCTIONS | HX20: LOANS/ADVANCES | IA20: Sat OT<=10 hrs | IC20: 0 | ID20: 0 | IE20: REGULAR DEDUCTIONS | IG20: LOANS/ADVANCES | IJ20: Sat OT<=10 hrs | IL20: 0 | IM20: 0 | IN20: REGULAR DEDUCTIONS | IP20: LOANS/ADVANCES | IS20: Sat OT<=10 hrs | IU20: 0 | IV20: 0 | IW20: REGULAR DEDUCTIONS | IY20: LOANS/ADVANCES | JB20: Sat OT<=10 hrs | JD20: 0 | JE20: 0 | JF20: REGULAR DEDUCTIONS | JH20: LOANS/ADVANCES | JK20: Sat OT<=10 hrs | JM20: 0 | JN20: 0 | JO20: REGULAR DEDUCTIONS | JQ20: LOANS/ADVANCES | JT20: Sat OT<=10 hrs | JV20: 0 | JW20: 0 | JX20: REGULAR DEDUCTIONS | JZ20: LOANS/ADVANCES | KC20: Sat OT<=10 hrs | KE20: 0 | KF20: 0 | KG20: REGULAR DEDUCTIONS | KI20: LOANS/ADVANCES
A21: Sat OT> 10 hrs | C21: =IF(C20>0,C22,0) -> 0 | D21: 0 | J21: Sat OT> 10 hrs | L21: =IF(L20>0,L22,0) -> 0 | M21: 0 | S21: Sat OT> 10 hrs | U21: =IF(U20>0,U22,0) -> 0 | V21: 0 | AB21: Sat OT> 10 hrs | AD21: =IF(AD20>0,AD22,0) -> 0 | AE21: 0 | AK21: Sat OT> 10 hrs | AM21: =IF(AM20>0,AM22,0) -> 0 | AN21: 0 | AT21: Sat OT> 10 hrs | AV21: =IF(AV20>0,AV22,0) -> 0 | AW21: 0 | BC21: Sat OT> 10 hrs | BE21: =IF(BE20>0,BE22,0) -> 0 | BF21: 0 | BL21: Sat OT> 10 hrs | BN21: =IF(BN20>0,BN22,0) -> 0 | BO21: 0 | BU21: Sat OT> 10 hrs | BW21: =IF(BW20>0,BW22,0) -> 0 | BX21: 0 | CD21: Sat OT> 10 hrs | CF21: =IF(CF20>0,CF22,0) -> 0 | CG21: 0 | CM21: Sat OT> 10 hrs | CO21: =IF(CO20>0,CO22,0) -> 0 | CP21: 0 | CV21: Sat OT> 10 hrs | CX21: =IF(CX20>0,CX22,0) -> 0 | CY21: 0 | DE21: Sat OT> 10 hrs | DG21: 0 | DH21: 0 | DN21: Sat OT> 10 hrs | DP21: =IF(DP20>0,DP22,0) -> 0 | DQ21: 0 | DW21: Sat OT> 10 hrs | DY21: =IF(DY20>0,DY22,0) -> 0 | DZ21: 0 | EF21: Sat OT> 10 hrs | EH21: =IF(EH20>0,EH22,0) -> 0 | EI21: 0 | EO21: Sat OT> 10 hrs | EQ21: =IF(EQ20>0,EQ22,0) -> 0 | ER21: 0 | EX21: Sat OT> 10 hrs | EZ21: =VLOOKUP(EY4,'Raw Sheet'!$A$8:$AK$28,37,0) -> 0 | FA21: =VLOOKUP(EY4,'Raw Sheet'!$A$8:$AL$28,38,0) -> 0 | FG21: Sat OT> 10 hrs | FI21: =IF(FI20>0,FI22,0) -> 0 | FJ21: 0 | FP21: Sat OT> 10 hrs | FR21: =IF(FR20>0,FR22,0) -> 0 | FS21: 0 | FY21: Sat OT> 10 hrs | GA21: =IF(GA20>0,GA22,0) -> 0 | GB21: 0 | GH21: Sat OT> 10 hrs | GJ21: =IF(GJ20>0,GJ22,0) -> 0 | GK21: 0 | GQ21: Sat OT> 10 hrs | GS21: =IF(GS20>0,GS22,0) -> 0 | GT21: 0 | GZ21: Sat OT> 10 hrs | HB21: =IF(HB20>0,HB22,0) -> 0 | HC21: 0 | HI21: Sat OT> 10 hrs | HK21: =IF(HK20>0,HK22,0) -> 0 | HL21: 0 | HR21: Sat OT> 10 hrs | HT21: =IF(HT20>0,HT22,0) -> 0 | HU21: 0 | IA21: Sat OT> 10 hrs | IC21: =IF(IC20>0,IC22,0) -> 0 | ID21: 0 | IJ21: Sat OT> 10 hrs | IL21: =IF(IL20>0,IL22,0) -> 0 | IM21: 0 | IS21: Sat OT> 10 hrs | IU21: =IF(IU20>0,IU22,0) -> 0 | IV21: 0 | JB21: Sat OT> 10 hrs | JD21: =IF(JD20>0,JD22,0) -> 0 | JE21: 0 | JK21: Sat OT> 10 hrs | JM21: =IF(JM20>0,JM22,0) -> 0 | JN21: 0 | JT21: Sat OT> 10 hrs | JV21: =IF(JV20>0,JV22,0) -> 0 | JW21: 0 | KC21: Sat OT> 10 hrs | KE21: =IF(KE20>0,KE22,0) -> 0 | KF21: 0
A22: Sat Night premium | C22: 0 | D22: 0 | E22: SSS | F22: #N/A | J22: Sat Night premium | L22: 0 | M22: 0 | N22: SSS | O22: #N/A | S22: Sat Night premium | U22: 0 | V22: 0 | W22: SSS | X22: #N/A | AB22: Sat Night premium | AD22: 0 | AE22: 0 | AF22: SSS | AG22: #N/A | AK22: Sat Night premium | AM22: 0 | AN22: 0 | AO22: SSS | AP22: #N/A | AT22: Sat Night premium | AV22: 0 | AW22: 0 | AX22: SSS | AY22: #N/A | BC22: Sat Night premium | BE22: 0 | BF22: 0 | BG22: SSS | BH22: #N/A | BL22: Sat Night premium | BN22: 0 | BO22: 0 | BP22: SSS | BQ22: #N/A | BU22: Sat Night premium | BW22: 0 | BX22: 0 | BY22: SSS | BZ22: =VLOOKUP(BV$4,'Payroll Register'!$A$5:$AS$29,23,FALSE) -> 0 | CA22: SSS Loan | CB22: ='Payroll Register'!AH8+'Payroll Register'!AG8 -> 1845.8 | CD22: Sat Night premium | CF22: 0 | CG22: 0 | CH22: SSS | CI22: =VLOOKUP(CE$4,'Payroll Register'!$A$5:$AS$29,23,FALSE) -> #N/A | CM22: Sat Night premium | CO22: 0 | CP22: 0 | CQ22: SSS | CR22: #N/A | CV22: Sat Night premium | CX22: 0 | CY22: 0 | CZ22: SSS | DA22: =VLOOKUP(CW$4,'Payroll Register'!$A$5:$AS$29,23,FALSE) -> 0 | DB22: SSS Loan | DC22: ='Payroll Register'!AH9+'Payroll Register'!AG9 -> 922.9 | DE22: Sat Night premium | DG22: 0 | DH22: 0 | DI22: SSS | DJ22: #N/A | DK22: Salary Advance | DL22: #REF! | DN22: Sat Night premium | DP22: 0 | DQ22: 0 | DR22: SSS | DS22: =VLOOKUP(DO$4,'Payroll Register'!$A$5:$AS$29,23,FALSE) -> 0 | DT22: SSS Loan | DU22: ='Payroll Register'!AG10+'Payroll Register'!AH10 -> 922.9 | DW22: Sat Night premium | DY22: 0 | DZ22: 0 | EA22: SSS | EB22: =VLOOKUP(DX$4,'Payroll Register'!$A$5:$AS$29,23,FALSE) -> 0 | EF22: Sat Night premium | EH22: 0 | EI22: 0 | EJ22: SSS | EK22: =VLOOKUP(EG$4,'Payroll Register'!$A$5:$AS$29,23,FALSE) -> 0 | EL22: Advances to Employees | EM22: ='Payroll Register'!AJ12 -> 41395.83 | EO22: Sat Night premium | EQ22: 0 | ER22: 0 | ES22: SSS | ET22: =VLOOKUP(EP$4,'Payroll Register'!$A$5:$AS$29,23,FALSE) -> 0 | EX22: Sat Night premium | EZ22: 0 | FA22: 0 | FB22: SSS | FC22: =VLOOKUP(EY$4,'Payroll Register'!$A$5:$AS$29,23,FALSE) -> 0 | FD22: SSS Loan | FE22: ='Payroll Register'!AG14 -> 0 | FG22: Sat Night premium | FI22: 0 | FJ22: 0 | FK22: SSS | FL22: =VLOOKUP(FH$4,'Payroll Register'!$A$5:$AS$29,23,FALSE) -> 0 | FP22: Sat Night premium | FR22: 0 | FS22: 0 | FT22: SSS | FU22: =VLOOKUP(FQ$4,'Payroll Register'!$A$5:$AS$29,23,FALSE) -> 0 | FY22: Sat Night premium | GA22: 0 | GB22: 0 | GC22: SSS | GD22: #N/A | GH22: Sat Night premium | GJ22: 0 | GK22: 0 | GL22: SSS | GM22: =VLOOKUP(GI$4,'Payroll Register'!$A$5:$AS$29,23,FALSE) -> 0 | GQ22: Sat Night premium | GS22: 0 | GT22: 0 | GU22: SSS | GV22: =VLOOKUP(GR$4,'Payroll Register'!$A$5:$AS$29,23,FALSE) -> 0 | GZ22: Sat Night premium | HB22: 0 | HC22: 0 | HD22: SSS | HE22: =VLOOKUP(HA$4,'Payroll Register'!$A$5:$AS$29,23,FALSE) -> 0 | HI22: Sat Night premium | HK22: 0 | HL22: 0 | HM22: SSS | HN22: =VLOOKUP(HJ$4,'Payroll Register'!$A$5:$AS$29,23,FALSE) -> 0 | HR22: Sat Night premium | HT22: 0 | HU22: 0 | HV22: SSS | HW22: =VLOOKUP(HS$4,'Payroll Register'!$A$5:$AS$29,23,FALSE) -> 0 | HX22: SSS Loan | HY22: ='Payroll Register'!AG21+'Payroll Register'!AH21 -> 697.88 | IA22: Sat Night premium | IC22: 0 | ID22: 0 | IE22: SSS | IF22: =VLOOKUP(IB$4,'Payroll Register'!$A$5:$AS$29,23,FALSE) -> 0 | IJ22: Sat Night premium | IL22: 0 | IM22: 0 | IN22: SSS | IO22: =VLOOKUP(IK$4,'Payroll Register'!$A$5:$AS$29,23,FALSE) -> 0 | IP22: SSS Loan | IQ22: ='Payroll Register'!AG23+'Payroll Register'!AH23 -> 1845.8 | IS22: Sat Night premium | IU22: 0 | IV22: 0 | IW22: SSS | IX22: =VLOOKUP(IT$4,'Payroll Register'!$A$5:$AS$29,23,FALSE) -> 0 | JB22: Sat Night premium | JD22: 0 | JE22: 0 | JF22: SSS | JG22: =VLOOKUP(JC$4,'Payroll Register'!$A$5:$AS$29,23,FALSE) -> 0 | JK22: Sat Night premium | JM22: 0 | JN22: 0 | JO22: SSS | JP22: =VLOOKUP(JL$4,'Payroll Register'!$A$5:$AS$29,23,FALSE) -> 0 | JQ22: SSS Loan | JR22: ='Payroll Register'!AG26+'Payroll Register'!AH26 -> 1809.09 | JT22: Sat Night premium | JV22: 0 | JW22: 0 | JX22: SSS | JY22: =VLOOKUP(JU$4,'Payroll Register'!$A$5:$AS$29,23,FALSE) -> 0 | KC22: Sat Night premium | KE22: 0 | KF22: 0 | KG22: SSS | KH22: =VLOOKUP(KD$4,'Payroll Register'!$A$5:$AS$29,23,FALSE) -> 0
A23: Sun OT<=10 hrs | C23: 0 | D23: 0 | E23: Philhealth | F23: #N/A | J23: Sun OT<=10 hrs | L23: 0 | M23: 0 | N23: Philhealth | O23: #N/A | S23: Sun OT<=10 hrs | U23: 0 | V23: 0 | W23: Philhealth | X23: #N/A | AB23: Sun OT<=10 hrs | AD23: 0 | AE23: 0 | AF23: Philhealth | AG23: #N/A | AK23: Sun OT<=10 hrs | AM23: 0 | AN23: 0 | AO23: Philhealth | AP23: #N/A | AT23: Sun OT<=10 hrs | AV23: 0 | AW23: 0 | AX23: Philhealth | AY23: #N/A | BC23: Sun OT<=10 hrs | BE23: 0 | BF23: 0 | BG23: Philhealth | BH23: #N/A | BL23: Sun OT<=10 hrs | BN23: 0 | BO23: 0 | BP23: Philhealth | BQ23: #N/A | BU23: Sun OT<=10 hrs | BW23: 0 | BX23: 0 | BY23: Philhealth | BZ23: =VLOOKUP(BV$4,'Payroll Register'!$A$5:$AS$29,24,FALSE) -> 0 | CD23: Sun OT<=10 hrs | CF23: 0 | CG23: 0 | CH23: Philhealth | CI23: =VLOOKUP(CE$4,'Payroll Register'!$A$5:$AS$29,24,FALSE) -> #N/A | CM23: Sun OT<=10 hrs | CO23: 0 | CP23: 0 | CQ23: Philhealth | CR23: #N/A | CV23: Sun OT<=10 hrs | CX23: 0 | CY23: 0 | CZ23: Philhealth | DA23: =VLOOKUP(CW$4,'Payroll Register'!$A$5:$AS$29,24,FALSE) -> 0 | DE23: Sun OT<=10 hrs | DG23: 0 | DH23: 0 | DI23: Philhealth | DJ23: #N/A | DN23: Sun OT<=10 hrs | DP23: 0 | DQ23: 0 | DR23: Philhealth | DS23: =VLOOKUP(DO$4,'Payroll Register'!$A$5:$AS$29,24,FALSE) -> 0 | DW23: Sun OT<=10 hrs | DY23: 0 | DZ23: 0 | EA23: Philhealth | EB23: =VLOOKUP(DX$4,'Payroll Register'!$A$5:$AS$29,24,FALSE) -> 0 | EF23: Sun OT<=10 hrs | EH23: 0 | EI23: 0 | EJ23: Philhealth | EK23: =VLOOKUP(EG$4,'Payroll Register'!$A$5:$AS$29,24,FALSE) -> 0 | EO23: Sun OT<=10 hrs | EQ23: 0 | ER23: 0 | ES23: Philhealth | ET23: =VLOOKUP(EP$4,'Payroll Register'!$A$5:$AS$29,24,FALSE) -> 0 | EX23: Sun OT<=10 hrs | EZ23: 0 | FA23: 0 | FB23: Philhealth | FC23: =VLOOKUP(EY$4,'Payroll Register'!$A$5:$AS$29,24,FALSE) -> 0 | FG23: Sun OT<=10 hrs | FI23: 0 | FJ23: 0 | FK23: Philhealth | FL23: =VLOOKUP(FH$4,'Payroll Register'!$A$5:$AS$29,24,FALSE) -> 0 | FP23: Sun OT<=10 hrs | FR23: 0 | FS23: 0 | FT23: Philhealth | FU23: =VLOOKUP(FQ$4,'Payroll Register'!$A$5:$AS$29,24,FALSE) -> 0 | FY23: Sun OT<=10 hrs | GA23: 0 | GB23: 0 | GC23: Philhealth | GD23: #N/A | GH23: Sun OT<=10 hrs | GJ23: 0 | GK23: 0 | GL23: Philhealth | GM23: =VLOOKUP(GI$4,'Payroll Register'!$A$5:$AS$29,24,FALSE) -> 0 | GQ23: Sun OT<=10 hrs | GS23: 0 | GT23: 0 | GU23: Philhealth | GV23: =VLOOKUP(GR$4,'Payroll Register'!$A$5:$AS$29,24,FALSE) -> 0 | GZ23: Sun OT<=10 hrs | HB23: 0 | HC23: 0 | HD23: Philhealth | HE23: =VLOOKUP(HA$4,'Payroll Register'!$A$5:$AS$29,24,FALSE) -> 0 | HI23: Sun OT<=10 hrs | HK23: 0 | HL23: 0 | HM23: Philhealth | HN23: =VLOOKUP(HJ$4,'Payroll Register'!$A$5:$AS$29,24,FALSE) -> 0 | HR23: Sun OT<=10 hrs | HT23: 0 | HU23: 0 | HV23: Philhealth | HW23: =VLOOKUP(HS$4,'Payroll Register'!$A$5:$AS$29,24,FALSE) -> 0 | IA23: Sun OT<=10 hrs | IC23: 0 | ID23: 0 | IE23: Philhealth | IF23: =VLOOKUP(IB$4,'Payroll Register'!$A$5:$AS$29,24,FALSE) -> 0 | IJ23: Sun OT<=10 hrs | IL23: 0 | IM23: 0 | IN23: Philhealth | IO23: =VLOOKUP(IK$4,'Payroll Register'!$A$5:$AS$29,24,FALSE) -> 0 | IP23: 2025 Tax Adjustment | IQ23: =-'Payroll Register'!AK23 -> 9750.9512 | IS23: Sun OT<=10 hrs | IU23: 0 | IV23: 0 | IW23: Philhealth | IX23: =VLOOKUP(IT$4,'Payroll Register'!$A$5:$AS$29,24,FALSE) -> 0 | JB23: Sun OT<=10 hrs | JD23: 0 | JE23: 0 | JF23: Philhealth | JG23: =VLOOKUP(JC$4,'Payroll Register'!$A$5:$AS$29,24,FALSE) -> 0 | JK23: Sun OT<=10 hrs | JM23: 0 | JN23: 0 | JO23: Philhealth | JP23: =VLOOKUP(JL$4,'Payroll Register'!$A$5:$AS$29,24,FALSE) -> 0 | JT23: Sun OT<=10 hrs | JV23: 0 | JW23: 0 | JX23: Philhealth | JY23: =VLOOKUP(JU$4,'Payroll Register'!$A$5:$AS$29,24,FALSE) -> 0 | KC23: Sun OT<=10 hrs | KE23: 0 | KF23: 0 | KG23: Philhealth | KH23: =VLOOKUP(KD$4,'Payroll Register'!$A$5:$AS$29,24,FALSE) -> 0
A24: Sun OT> 10 hrs | C24: =IF(C23>0,C25,0) -> 0 | D24: 0 | E24: HDMF | F24: #N/A | J24: Sun OT> 10 hrs | L24: =IF(L23>0,L25,0) -> 0 | M24: 0 | N24: HDMF | O24: #N/A | S24: Sun OT> 10 hrs | U24: =IF(U23>0,U25,0) -> 0 | V24: 0 | W24: HDMF | X24: #N/A | AB24: Sun OT> 10 hrs | AD24: =IF(AD23>0,AD25,0) -> 0 | AE24: 0 | AF24: HDMF | AG24: #N/A | AK24: Sun OT> 10 hrs | AM24: =IF(AM23>0,AM25,0) -> 0 | AN24: 0 | AO24: HDMF | AP24: #N/A | AT24: Sun OT> 10 hrs | AV24: =IF(AV23>0,AV25,0) -> 0 | AW24: 0 | AX24: HDMF | AY24: #N/A | BC24: Sun OT> 10 hrs | BE24: =IF(BE23>0,BE25,0) -> 0 | BF24: 0 | BG24: HDMF | BH24: #N/A | BL24: Sun OT> 10 hrs | BN24: =IF(BN23>0,BN25,0) -> 0 | BO24: 0 | BP24: HDMF | BQ24: #N/A | BU24: Sun OT> 10 hrs | BW24: =IF(BW23>0,BW25,0) -> 0 | BX24: 0 | BY24: HDMF | BZ24: =VLOOKUP(BV$4,'Payroll Register'!$A$5:$AS$29,25,FALSE) -> 0 | CD24: Sun OT> 10 hrs | CF24: =IF(CF23>0,CF25,0) -> 0 | CG24: 0 | CH24: HDMF | CI24: =VLOOKUP(CE$4,'Payroll Register'!$A$5:$AS$29,25,FALSE) -> #N/A | CM24: Sun OT> 10 hrs | CO24: =IF(CO23>0,CO25,0) -> 0 | CP24: 0 | CQ24: HDMF | CR24: #N/A | CV24: Sun OT> 10 hrs | CX24: =IF(CX23>0,CX25,0) -> 0 | CY24: 0 | CZ24: HDMF | DA24: =VLOOKUP(CW$4,'Payroll Register'!$A$5:$AS$29,25,FALSE) -> 0 | DE24: Sun OT> 10 hrs | DG24: 0 | DH24: 0 | DI24: HDMF | DJ24: #N/A | DN24: Sun OT> 10 hrs | DP24: =IF(DP23>0,DP25,0) -> 0 | DQ24: 0 | DR24: HDMF | DS24: =VLOOKUP(DO$4,'Payroll Register'!$A$5:$AS$29,25,FALSE) -> 0 | DW24: Sun OT> 10 hrs | DY24: =IF(DY23>0,DY25,0) -> 0 | DZ24: 0 | EA24: HDMF | EB24: =VLOOKUP(DX$4,'Payroll Register'!$A$5:$AS$29,25,FALSE) -> 0 | EF24: Sun OT> 10 hrs | EH24: =IF(EH23>0,EH25,0) -> 0 | EI24: 0 | EJ24: HDMF | EK24: =VLOOKUP(EG$4,'Payroll Register'!$A$5:$AS$29,25,FALSE) -> 0 | EO24: Sun OT> 10 hrs | EQ24: =IF(EQ23>0,EQ25,0) -> 0 | ER24: 0 | ES24: HDMF | ET24: =VLOOKUP(EP$4,'Payroll Register'!$A$5:$AS$29,25,FALSE) -> 0 | EX24: Sun OT> 10 hrs | EZ24: =IF(EZ23>0,EZ25,0) -> 0 | FA24: 0 | FB24: HDMF | FC24: =VLOOKUP(EY$4,'Payroll Register'!$A$5:$AS$29,25,FALSE) -> 0 | FG24: Sun OT> 10 hrs | FI24: =IF(FI23>0,FI25,0) -> 0 | FJ24: 0 | FK24: HDMF | FL24: =VLOOKUP(FH$4,'Payroll Register'!$A$5:$AS$29,25,FALSE) -> 0 | FP24: Sun OT> 10 hrs | FR24: =IF(FR23>0,FR25,0) -> 0 | FS24: 0 | FT24: HDMF | FU24: =VLOOKUP(FQ$4,'Payroll Register'!$A$5:$AS$29,25,FALSE) -> 0 | FY24: Sun OT> 10 hrs | GA24: =IF(GA23>0,GA25,0) -> 0 | GB24: 0 | GC24: HDMF | GD24: #N/A | GH24: Sun OT> 10 hrs | GJ24: =IF(GJ23>0,GJ25,0) -> 0 | GK24: 0 | GL24: HDMF | GM24: =VLOOKUP(GI$4,'Payroll Register'!$A$5:$AS$29,25,FALSE) -> 0 | GQ24: Sun OT> 10 hrs | GS24: =IF(GS23>0,GS25,0) -> 0 | GT24: 0 | GU24: HDMF | GV24: =VLOOKUP(GR$4,'Payroll Register'!$A$5:$AS$29,25,FALSE) -> 0 | GZ24: Sun OT> 10 hrs | HB24: =IF(HB23>0,HB25,0) -> 0 | HC24: 0 | HD24: HDMF | HE24: =VLOOKUP(HA$4,'Payroll Register'!$A$5:$AS$29,25,FALSE) -> 0 | HI24: Sun OT> 10 hrs | HK24: =IF(HK23>0,HK25,0) -> 0 | HL24: 0 | HM24: HDMF | HN24: =VLOOKUP(HJ$4,'Payroll Register'!$A$5:$AS$29,25,FALSE) -> 0 | HR24: Sun OT> 10 hrs | HT24: =IF(HT23>0,HT25,0) -> 0 | HU24: 0 | HV24: HDMF | HW24: =VLOOKUP(HS$4,'Payroll Register'!$A$5:$AS$29,25,FALSE) -> 0 | HX24: HMDF Loan | HY24: ='Payroll Register'!AI21 -> 697.88 | IA24: Sun OT> 10 hrs | IC24: =IF(IC23>0,IC25,0) -> 0 | ID24: 0 | IE24: HDMF | IF24: =VLOOKUP(IB$4,'Payroll Register'!$A$5:$AS$29,25,FALSE) -> 0 | IJ24: Sun OT> 10 hrs | IL24: =IF(IL23>0,IL25,0) -> 0 | IM24: 0 | IN24: HDMF | IO24: =VLOOKUP(IK$4,'Payroll Register'!$A$5:$AS$29,25,FALSE) -> 0 | IS24: Sun OT> 10 hrs | IU24: =IF(IU23>0,IU25,0) -> 0 | IV24: 0 | IW24: HDMF | IX24: =VLOOKUP(IT$4,'Payroll Register'!$A$5:$AS$29,25,FALSE) -> 0 | JB24: Sun OT> 10 hrs | JD24: =IF(JD23>0,JD25,0) -> 0 | JE24: 0 | JF24: HDMF | JG24: =VLOOKUP(JC$4,'Payroll Register'!$A$5:$AS$29,25,FALSE) -> 0 | JK24: Sun OT> 10 hrs | JM24: =IF(JM23>0,JM25,0) -> 0 | JN24: 0 | JO24: HDMF | JP24: =VLOOKUP(JL$4,'Payroll Register'!$A$5:$AS$29,25,FALSE) -> 0 | JT24: Sun OT> 10 hrs | JV24: =IF(JV23>0,JV25,0) -> 0 | JW24: 0 | JX24: HDMF | JY24: =VLOOKUP(JU$4,'Payroll Register'!$A$5:$AS$29,25,FALSE) -> 0 | KC24: Sun OT> 10 hrs | KE24: =IF(KE23>0,KE25,0) -> 0 | KF24: 0 | KG24: HDMF | KH24: =VLOOKUP(KD$4,'Payroll Register'!$A$5:$AS$29,25,FALSE) -> 0
A25: Sun Night premium | C25: 0 | D25: 0 | E25: Withholding tax | F25: #N/A | J25: Sun Night premium | L25: 0 | M25: 0 | N25: Withholding tax | O25: #N/A | S25: Sun Night premium | U25: 0 | V25: 0 | W25: Withholding tax | X25: #N/A | AB25: Sun Night premium | AD25: 0 | AE25: 0 | AF25: Withholding tax | AG25: #N/A | AK25: Sun Night premium | AM25: 0 | AN25: 0 | AO25: Withholding tax | AP25: #N/A | AT25: Sun Night premium | AV25: 0 | AW25: 0 | AX25: Withholding tax | AY25: #N/A | BC25: Sun Night premium | BE25: 0 | BF25: 0 | BG25: Withholding tax | BH25: #N/A | BL25: Sun Night premium | BN25: 0 | BO25: 0 | BP25: Withholding tax | BQ25: #N/A | BU25: Sun Night premium | BW25: 0 | BX25: 0 | BY25: Withholding tax | BZ25: ='Payroll Register'!AF8 -> 1375.4103 | CD25: Sun Night premium | CF25: 0 | CG25: 0 | CH25: Withholding tax | CI25: =VLOOKUP(CE$4,'Payroll Register'!$A$5:$AS$29,32,FALSE) -> #N/A | CM25: Sun Night premium | CO25: 0 | CP25: 0 | CQ25: Withholding tax | CR25: #N/A | CV25: Sun Night premium | CX25: 0 | CY25: 0 | CZ25: Withholding tax | DA25: ='Payroll Register'!AF9 -> 3275.6517 | DE25: Sun Night premium | DG25: 0 | DH25: 0 | DI25: Withholding tax | DJ25: #N/A | DN25: Sun Night premium | DP25: 0 | DQ25: 0 | DR25: Withholding tax | DS25: ='Payroll Register'!AF10 -> 2528.2379 | DW25: Sun Night premium | DY25: 0 | DZ25: 0 | EA25: Withholding tax | EB25: ='Payroll Register'!AF11 -> 17210.8 | EF25: Sun Night premium | EH25: 0 | EI25: 0 | EJ25: Withholding tax | EK25: ='Payroll Register'!AF12 -> 30110.8 | EO25: Sun Night premium | EQ25: 0 | ER25: 0 | ES25: Withholding tax | ET25: ='Payroll Register'!AF13 -> 674.34655 | EX25: Sun Night premium | EZ25: 0 | FA25: 0 | FB25: Withholding tax | FC25: ='Payroll Register'!AF14 -> 1046.2977 | FG25: Sun Night premium | FI25: 0 | FJ25: 0 | FK25: Withholding tax | FL25: ='Payroll Register'!AF15 -> 7199.95 | FP25: Sun Night premium | FR25: 0 | FS25: 0 | FT25: Withholding tax | FU25: =VLOOKUP(FQ$4,'Payroll Register'!$A$5:$AS$29,32,FALSE) -> 13343.161 | FY25: Sun Night premium | GA25: 0 | GB25: 0 | GC25: Withholding tax | GD25: #N/A | GH25: Sun Night premium | GJ25: 0 | GK25: 0 | GL25: Withholding tax | GM25: ='Payroll Register'!AF17 -> 1176.5138 | GQ25: Sun Night premium | GS25: 0 | GT25: 0 | GU25: Withholding tax | GV25: =VLOOKUP(GR$4,'Payroll Register'!$A$5:$AS$29,32,FALSE) -> 832.84828 | GZ25: Sun Night premium | HB25: 0 | HC25: 0 | HD25: Withholding tax | HE25: =VLOOKUP(HA$4,'Payroll Register'!$A$5:$AS$29,32,FALSE) -> 20542.352 | HI25: Sun Night premium | HK25: 0 | HL25: 0 | HM25: Withholding tax | HN25: =VLOOKUP(HJ$4,'Payroll Register'!$A$5:$AS$29,32,FALSE) -> 5244.0707 | HR25: Sun Night premium | HT25: 0 | HU25: 0 | HV25: Withholding tax | HW25: =VLOOKUP(HS$4,'Payroll Register'!$A$5:$AS$29,32,FALSE) -> 490.10517 | IA25: Sun Night premium | IC25: 0 | ID25: 0 | IE25: Withholding tax | IF25: =VLOOKUP(IB$4,'Payroll Register'!$A$5:$AS$29,32,FALSE) -> 9310.2948 | IJ25: Sun Night premium | IL25: 0 | IM25: 0 | IN25: Withholding tax | IO25: =VLOOKUP(IK$4,'Payroll Register'!$A$5:$AS$29,32,FALSE) -> 14512.881 | IS25: Sun Night premium | IU25: 0 | IV25: 0 | IW25: Withholding tax | IX25: =VLOOKUP(IT$4,'Payroll Register'!$A$5:$AS$29,32,FALSE) -> 728.82931 | JB25: Sun Night premium | JD25: 0 | JE25: 0 | JF25: Withholding tax | JG25: =VLOOKUP(JC$4,'Payroll Register'!$A$5:$AS$29,32,FALSE) -> 585.72586 | JK25: Sun Night premium | JM25: 0 | JN25: 0 | JO25: Withholding tax | JP25: =VLOOKUP(JL$4,'Payroll Register'!$A$5:$AS$29,32,FALSE) -> 7887.5218 | JT25: Sun Night premium | JV25: 0 | JW25: 0 | JX25: Withholding tax | JY25: =VLOOKUP(JU$4,'Payroll Register'!$A$5:$AS$29,32,FALSE) -> 246.76034 | KC25: Sun Night premium | KE25: 0 | KF25: 0 | KG25: Withholding tax | KH25: =VLOOKUP(KD$4,'Payroll Register'!$A$5:$AS$29,32,FALSE) -> 0
A26: Hol OT<=10 hrs | C26: 0 | D26: 0 | E26: OTHER DEDUCTIONS | J26: Hol OT<=10 hrs | L26: 0 | M26: 0 | N26: OTHER DEDUCTIONS | S26: Hol OT<=10 hrs | U26: 0 | V26: 0 | W26: OTHER DEDUCTIONS | AB26: Hol OT<=10 hrs | AD26: 0 | AE26: 0 | AF26: OTHER DEDUCTIONS | AK26: Hol OT<=10 hrs | AM26: 0 | AN26: 0 | AO26: OTHER DEDUCTIONS | AT26: Hol OT<=10 hrs | AV26: 0 | AW26: 0 | AX26: OTHER DEDUCTIONS | BC26: Hol OT<=10 hrs | BE26: 0 | BF26: 0 | BG26: OTHER DEDUCTIONS | BL26: Hol OT<=10 hrs | BN26: 0 | BO26: 0 | BP26: OTHER DEDUCTIONS | BU26: Hol OT<=10 hrs | BW26: =VLOOKUP(BV4,'Raw Sheet'!$A$8:$AX$28,49,0) -> 0 | BX26: =VLOOKUP(BV4,'Raw Sheet'!$A$8:$AX$28,50,0) -> 0 | BY26: OTHER DEDUCTIONS | CD26: Hol OT<=10 hrs | CF26: 0 | CG26: 0 | CH26: OTHER DEDUCTIONS | CM26: Hol OT<=10 hrs | CO26: 0 | CP26: 0 | CQ26: OTHER DEDUCTIONS | CV26: Hol OT<=10 hrs | CX26: ='Raw Sheet'!BC9 -> 8 | CY26: ='Payroll Register'!Q9 -> 2068.9655 | CZ26: OTHER DEDUCTIONS | DE26: Hol OT<=10 hrs | DG26: 0 | DH26: 0 | DI26: OTHER DEDUCTIONS | DN26: Hol OT<=10 hrs | DP26: =VLOOKUP(DO4,'Raw Sheet'!$A$8:$AX$28,49,0) -> 0 | DQ26: =VLOOKUP(DO4,'Raw Sheet'!$A$8:$AX$28,50,0) -> 0 | DR26: OTHER DEDUCTIONS | DW26: Hol OT<=10 hrs | DY26: 0 | DZ26: 0 | EA26: OTHER DEDUCTIONS | EF26: Hol OT<=10 hrs | EH26: 0 | EI26: 0 | EJ26: OTHER DEDUCTIONS | EO26: Hol OT<=10 hrs | EQ26: ='Raw Sheet'!BC13 -> 8 | ER26: ='Payroll Register'!Q13 -> 1912.6437 | ES26: OTHER DEDUCTIONS | EX26: Hol OT<=10 hrs | EZ26: ='Raw Sheet'!BC14 -> 8 | FA26: ='Payroll Register'!Q14 -> 2183.3563 | FB26: OTHER DEDUCTIONS | FG26: Hol OT<=10 hrs | FI26: 0 | FJ26: 0 | FK26: OTHER DEDUCTIONS | FP26: Hol OT<=10 hrs | FR26: 0 | FS26: =VLOOKUP(FQ4,'Raw Sheet'!$A$8:$BL$37,53,FALSE) -> 0 | FT26: OTHER DEDUCTIONS | FY26: Hol OT<=10 hrs | GA26: 0 | GB26: 0 | GC26: OTHER DEDUCTIONS | GH26: Hol OT<=10 hrs | GJ26: ='Raw Sheet'!AW17 -> 0 | GK26: ='Raw Sheet'!AX17 -> 0 | GL26: OTHER DEDUCTIONS | GQ26: Hol OT<=10 hrs | GS26: ='Raw Sheet'!BC18 -> 2 | GT26: ='Payroll Register'!Q18 -> 329.26437 | GU26: OTHER DEDUCTIONS | GZ26: Hol OT<=10 hrs | HB26: 0 | HC26: 0 | HD26: OTHER DEDUCTIONS | HI26: Hol OT<=10 hrs | HK26: 0 | HL26: 0 | HM26: OTHER DEDUCTIONS | HR26: Hol OT<=10 hrs | HT26: ='Raw Sheet'!BC21 -> 3 | HU26: ='Payroll Register'!Q21 -> 425.86207 | HV26: OTHER DEDUCTIONS | IA26: Hol OT<=10 hrs | IC26: 0 | ID26: =VLOOKUP(IB4,'Raw Sheet'!$A$8:$BL$29,53,FALSE) -> 0 | IE26: OTHER DEDUCTIONS | IJ26: Hol OT<=10 hrs | IL26: 0 | IM26: 0 | IN26: OTHER DEDUCTIONS | IS26: Hol OT<=10 hrs | IU26: 0 | IV26: 0 | IW26: OTHER DEDUCTIONS | JB26: Hol OT<=10 hrs | JD26: 0 | JE26: 0 | JF26: OTHER DEDUCTIONS | JK26: Hol OT<=10 hrs | JM26: 6 | JN26: =VLOOKUP(JL4,'Raw Sheet'!$A$8:$BL$29,53,FALSE) -> 0 | JO26: OTHER DEDUCTIONS | JT26: Hol OT<=10 hrs | JV26: 0 | JW26: =VLOOKUP(JU4,'Raw Sheet'!$A$8:$BL$29,53,FALSE) -> 0 | JX26: OTHER DEDUCTIONS | KC26: Hol OT<=10 hrs | KE26: ='Raw Sheet'!BC28 -> 8 | KF26: ='Payroll Register'!Q28 -> 827.58621 | KG26: OTHER DEDUCTIONS
A27: Hol OT>10 hrs | C27: 0 | D27: 0 | J27: Hol OT>10 hrs | L27: 0 | M27: 0 | S27: Hol OT>10 hrs | U27: 0 | V27: 0 | AB27: Hol OT>10 hrs | AD27: 0 | AE27: 0 | AK27: Hol OT>10 hrs | AM27: 0 | AN27: 0 | AT27: Hol OT>10 hrs | AV27: 0 | AW27: 0 | BC27: Hol OT>10 hrs | BE27: 0 | BF27: 0 | BL27: Hol OT>10 hrs | BN27: 0 | BO27: 0 | BU27: Hol OT>10 hrs | BW27: 0 | BX27: 0 | CD27: Hol OT>10 hrs | CF27: 0 | CG27: 0 | CM27: Hol OT>10 hrs | CO27: 0 | CP27: 0 | CV27: Hol OT>10 hrs | CX27: 0 | CY27: 0 | DE27: Hol OT>10 hrs | DG27: 0 | DH27: 0 | DN27: Hol OT>10 hrs | DP27: 0 | DQ27: 0 | DW27: Hol OT>10 hrs | DY27: 0 | DZ27: 0 | EF27: Hol OT>10 hrs | EH27: 0 | EI27: 0 | EO27: Hol OT>10 hrs | EQ27: 0 | ER27: 0 | EX27: Hol OT>10 hrs | EZ27: 0 | FA27: 0 | FG27: Hol OT>10 hrs | FI27: 0 | FJ27: 0 | FP27: Hol OT>10 hrs | FR27: 0 | FS27: 0 | FY27: Hol OT>10 hrs | GA27: 0 | GB27: 0 | GH27: Hol OT>10 hrs | GJ27: 0 | GK27: 0 | GQ27: Hol OT>10 hrs | GS27: 0 | GT27: =VLOOKUP(GR4,'Raw Sheet'!$A$8:$BL$29,53,FALSE) -> 0 | GZ27: Hol OT>10 hrs | HB27: 0 | HC27: 0 | HI27: Hol OT>10 hrs | HK27: 0 | HL27: 0 | HR27: Hol OT>10 hrs | HT27: 0 | HU27: =VLOOKUP(HS4,'Raw Sheet'!$A$8:$BL$29,53,FALSE) -> 0 | IA27: Hol OT>10 hrs | IC27: 0 | ID27: 0 | IJ27: Hol OT>10 hrs | IL27: 0 | IM27: =VLOOKUP(IK4,'Raw Sheet'!$A$8:$BL$29,53,FALSE) -> 0 | IS27: Hol OT>10 hrs | IU27: 0 | IV27: =VLOOKUP(IT4,'Raw Sheet'!$A$8:$BL$29,53,FALSE) -> 0 | JB27: Hol OT>10 hrs | JD27: 0 | JE27: =VLOOKUP(JC4,'Raw Sheet'!$A$8:$BL$29,53,FALSE) -> 0 | JK27: Hol OT>10 hrs | JM27: 0 | JN27: 0 | JT27: Hol OT>10 hrs | JV27: 0 | JW27: 0 | KC27: Hol OT>10 hrs | KE27: 0 | KF27: 0
A28: Hol Night premium | C28: 0 | D28: 0 | J28: Hol Night premium | L28: 0 | M28: 0 | S28: Hol Night premium | U28: 0 | V28: 0 | AB28: Hol Night premium | AD28: 0 | AE28: 0 | AK28: Hol Night premium | AM28: 0 | AN28: 0 | AT28: Hol Night premium | AV28: 0 | AW28: 0 | BC28: Hol Night premium | BE28: 0 | BF28: 0 | BL28: Hol Night premium | BN28: 0 | BO28: 0 | BU28: Hol Night premium | BW28: =VLOOKUP(BV4,'Raw Sheet'!$A$8:$BA$28,53,0) -> 0 | BX28: =VLOOKUP(BV4,'Raw Sheet'!$A$8:$BB$28,54,0) -> 0 | CD28: Hol Night premium | CF28: 0 | CG28: 0 | CM28: Hol Night premium | CO28: 0 | CP28: 0 | CV28: Hol Night premium | CX28: =VLOOKUP(CW4,'Raw Sheet'!$A$8:$BA$28,53,0) -> 0 | CY28: =VLOOKUP(CW4,'Raw Sheet'!$A$8:$BB$28,54,0) -> 0 | DE28: Hol Night premium | DG28: 0 | DH28: 0 | DN28: Hol Night premium | DP28: 0 | DQ28: 0 | DW28: Hol Night premium | DY28: 0 | DZ28: 0 | EF28: Hol Night premium | EH28: 0 | EI28: 0 | EO28: Hol Night premium | EQ28: 0 | ER28: 0 | EX28: Hol Night premium | EZ28: =VLOOKUP(EY4,'Raw Sheet'!$A$8:$BA$28,53,0) -> 0 | FA28: =VLOOKUP(EY4,'Raw Sheet'!$A$8:$BB$28,54,0) -> 0 | FG28: Hol Night premium | FI28: 0 | FJ28: 0 | FP28: Hol Night premium | FR28: 0 | FS28: 0 | FY28: Hol Night premium | GA28: 0 | GB28: 0 | GH28: Hol Night premium | GJ28: ='Raw Sheet'!BA17 -> 0 | GK28: =VLOOKUP(GI4,'Raw Sheet'!$A$8:$BL$37,53,FALSE) -> 0 | GQ28: Hol Night premium | GS28: 0 | GT28: 0 | GZ28: Hol Night premium | HB28: 0 | HC28: 0 | HI28: Hol Night premium | HK28: 0 | HL28: 0 | HR28: Hol Night premium | HT28: 0 | HU28: 0 | IA28: Hol Night premium | IC28: 0 | ID28: 0 | IJ28: Hol Night premium | IL28: 0 | IM28: 0 | IS28: Hol Night premium | IU28: 0 | IV28: 0 | JB28: Hol Night premium | JD28: 0 | JE28: 0 | JK28: Hol Night premium | JM28: 0 | JN28: 0 | JT28: Hol Night premium | JV28: 0 | JW28: 0 | KC28: Hol Night premium | KE28: 0 | KF28: 0
G29: TOTAL DEDUCTIONS | H29: =SUM(F22:F25)+SUM(F27:F28)+SUM(H22:H25) -> #N/A | P29: TOTAL DEDUCTIONS | Q29: =SUM(O22:O25)+SUM(O27:O28)+SUM(Q22:Q25) -> #N/A | Y29: TOTAL DEDUCTIONS | Z29: =SUM(X22:X25)+SUM(X27:X28)+SUM(Z22:Z25) -> #N/A | AH29: TOTAL DEDUCTIONS | AI29: =SUM(AG22:AG25)+SUM(AG27:AG28)+SUM(AI22:AI25) -> #N/A | AQ29: TOTAL DEDUCTIONS | AR29: =SUM(AP22:AP25)+SUM(AP27:AP28)+SUM(AR22:AR25) -> #N/A | AZ29: TOTAL DEDUCTIONS | BA29: =SUM(AY22:AY25)+SUM(AY27:AY28)+SUM(BA22:BA25) -> #N/A | BI29: TOTAL DEDUCTIONS | BJ29: =SUM(BH22:BH25)+SUM(BH27:BH28)+SUM(BJ22:BJ25) -> #N/A | BR29: TOTAL DEDUCTIONS | BS29: =SUM(BQ22:BQ25)+SUM(BQ27:BQ28)+SUM(BS22:BS25) -> #N/A | CA29: TOTAL DEDUCTIONS | CB29: =CB22+BZ25 -> 3221.2103 | CJ29: TOTAL DEDUCTIONS | CK29: =SUM(CI22:CI25)+SUM(CI27:CI28)+SUM(CK22:CK25) -> #N/A | CS29: TOTAL DEDUCTIONS | CT29: =SUM(CR22:CR25)+SUM(CR27:CR28)+SUM(CT22:CT25) -> #N/A | DB29: TOTAL DEDUCTIONS | DC29: =SUM(DA22:DA25)+SUM(DA27:DA28)+SUM(DC22:DC25) -> 4198.5517 | DK29: TOTAL DEDUCTIONS | DL29: =SUM(DJ22:DJ25)+SUM(DJ27:DJ28)+SUM(DL22:DL25) -> #N/A | DT29: TOTAL DEDUCTIONS | DU29: =SUM(DS22:DS25)+SUM(DS27:DS28)+SUM(DU22:DU25) -> 3451.1379 | EC29: TOTAL DEDUCTIONS | ED29: =SUM(EB22:EB25)+SUM(EB27:EB28)+SUM(ED22:ED25) -> 17210.8 | EL29: TOTAL DEDUCTIONS | EM29: =SUM(EK22:EK25)+SUM(EK27:EK28)+SUM(EM22:EM25) -> 71506.63 | EU29: TOTAL DEDUCTIONS | EV29: =SUM(ET22:ET25)+SUM(ET27:ET28)+SUM(EV22:EV25) -> 674.34655 | FD29: TOTAL DEDUCTIONS | FE29: =SUM(FC22:FC25)+SUM(FC27:FC28)+SUM(FE22:FE25) -> 1046.2977 | FM29: TOTAL DEDUCTIONS | FN29: =SUM(FL22:FL25)+SUM(FL27:FL28)+SUM(FN22:FN25) -> 7199.95 | FV29: TOTAL DEDUCTIONS | FW29: =SUM(FU22:FU25)+SUM(FU27:FU28)+SUM(FW22:FW25) -> 13343.161 | GE29: TOTAL DEDUCTIONS | GF29: =SUM(GD22:GD25)+SUM(GD27:GD28)+SUM(GF22:GF25) -> #N/A | GN29: TOTAL DEDUCTIONS | GO29: =SUM(GM22:GM25)+SUM(GM27:GM28)+SUM(GO22:GO25) -> 1176.5138 | GW29: TOTAL DEDUCTIONS | GX29: =SUM(GV22:GV25)+SUM(GV27:GV28)+SUM(GX22:GX25) -> 832.84828 | HF29: TOTAL DEDUCTIONS | HG29: =SUM(HE22:HE25)+SUM(HE27:HE28)+SUM(HG22:HG25) -> 20542.352 | HO29: TOTAL DEDUCTIONS | HP29: =SUM(HN22:HN25)+SUM(HN27:HN28)+SUM(HP22:HP25) -> 5244.0707 | HX29: TOTAL DEDUCTIONS | HY29: =SUM(HW22:HW25)+SUM(HW27:HW28)+SUM(HY22:HY25) -> 1885.8652 | IG29: TOTAL DEDUCTIONS | IH29: =SUM(IF22:IF25)+SUM(IF27:IF28)+SUM(IH22:IH25) -> 9310.2948 | IP29: TOTAL DEDUCTIONS | IQ29: =SUM(IO22:IO25)+SUM(IO27:IO28)+SUM(IQ22:IQ25) -> 26109.632 | IY29: TOTAL DEDUCTIONS | IZ29: =SUM(IX22:IX25)+SUM(IX27:IX28)+SUM(IZ22:IZ25) -> 728.82931 | JH29: TOTAL DEDUCTIONS | JI29: =SUM(JG22:JG25)+SUM(JG27:JG28)+SUM(JI22:JI25) -> 585.72586 | JQ29: TOTAL DEDUCTIONS | JR29: =SUM(JP22:JP25)+SUM(JP27:JP28)+SUM(JR22:JR25) -> 9696.6118 | JZ29: TOTAL DEDUCTIONS | KA29: =SUM(JY22:JY25)+SUM(JY27:JY28)+SUM(KA22:KA25) -> 246.76034 | KI29: TOTAL DEDUCTIONS | KJ29: =SUM(KH22:KH25)+SUM(KH27:KH28)+SUM(KJ22:KJ25) -> 0
A32: Employee signature: | G32: NET PAY: | H32: =H18-H29 -> #N/A | J32: Employee signature: | P32: NET PAY: | Q32: =Q18-Q29 -> #N/A | S32: Employee signature: | Y32: NET PAY: | Z32: =Z18-Z29 -> #N/A | AB32: Employee signature: | AH32: NET PAY: | AI32: =AI18-AI29 -> #N/A | AK32: Employee signature: | AQ32: NET PAY: | AR32: =AR18-AR29 -> #REF! | AT32: Employee signature: | AZ32: NET PAY: | BA32: =BA18-BA29 -> #N/A | BC32: Employee signature: | BI32: NET PAY: | BJ32: =BJ18-BJ29 -> #REF! | BL32: Employee signature: | BR32: NET PAY: | BS32: =BS18-BS29 -> #REF! | BU32: Employee signature: | CA32: NET PAY: | CB32: =CB18-CB29 -> 17035.341 | CD32: Employee signature: | CJ32: NET PAY: | CK32: =CK18-CK29 -> #N/A | CM32: Employee signature: | CS32: NET PAY: | CT32: =CT18-CT29 -> #REF! | CV32: Employee signature: | DB32: NET PAY: | DC32: =DC18-DC29 -> 24159.207 | DE32: Employee signature: | DK32: NET PAY: | DL32: =DL18-DL29 -> #REF! | DN32: Employee signature: | DT32: NET PAY: | DU32: =DU18-DU29 -> 22219.552 | DW32: Employee signature: | EC32: NET PAY: | ED32: =ED18-ED29 -> 68989.2 | EF32: Employee signature: | EL32: NET PAY: | EM32: =EM18-EM29 -> 57693.37 | EO32: Employee signature: | EU32: NET PAY: | EV32: =EV18-EV29 -> 19351.634 | EX32: Employee signature: | FD32: NET PAY: | FE32: =FE18-FE29 -> 17564.691 | FG32: Employee signature: | FM32: NET PAY: | FN32: =FN18-FN29 -> 39250.05 | FP32: Employee signature: | FV32: NET PAY: | FW32: =FW18-FW29 -> 57679.684 | FY32: Employee signature: | GE32: NET PAY: | GF32: =GF18-GF29 -> #REF! | GH32: Employee signature: | GN32: NET PAY: | GO32: =GO18-GO29 -> 18085.555 | GQ32: Employee signature: | GW32: NET PAY: | GX32: =GX18-GX29 -> 16536.474 | GZ32: Employee signature: | HF32: NET PAY: | HG32: =HG18-HG29 -> 76762.821 | HI32: Employee signature: | HO32: NET PAY: | HP32: =HP18-HP29 -> 33382.412 | HR32: Employee signature: | HX32: NET PAY: | HY32: =HY18-HY29 -> 13198.503 | IA32: Employee signature: | IG32: NET PAY: | IH32: =IH18-IH29 -> 45581.084 | IJ32: Employee signature: | IP32: NET PAY: | IQ32: =IQ18-IQ29 -> 49592.092 | IS32: Employee signature: | IY32: NET PAY: | IZ32: =IZ18-IZ29 -> 15947.033 | JB32: Employee signature: | JH32: NET PAY: | JI32: =JI18-JI29 -> 15136.113 | JK32: Employee signature: | JQ32: NET PAY: | JR32: =JR18-JR29 -> 39503.676 | JT32: Employee signature: | JZ32: NET PAY: | KA32: =KA18-KA29 -> 13215.309 | KC32: Employee signature: | KI32: NET PAY: | KJ32: =KJ18-KJ29 -> 11455.172
CB35: =CB32-'Payroll Register'!AM8 -> 0.00068965516 | CK35: =CK32-'Payroll Register'!#REF! -> #N/A | DC35: =DC32-'Payroll Register'!AM9 -> 0.0037931035 | DU35: =DU32-'Payroll Register'!AM10 -> -0.0037931035 | ED35: =ED32-'Payroll Register'!AM11 -> 0 | EM35: =EM32-'Payroll Register'!AM12 -> 0 | EV35: =EV32-'Payroll Register'!AM13 -> 0 | FE35: =FE32-'Payroll Register'!AM14 -> -0.0049425287 | FN35: =FN32-'Payroll Register'!AM15 -> 0 | FW35: =FW32-'Payroll Register'!AM16 -> -0.0042816091 | GO35: =GO32-'Payroll Register'!AM17 -> 0.0022413793 | GX35: =GX32-'Payroll Register'!AM18 -> -0.0015517241 | HG35: =HG32-'Payroll Register'!AM19 -> 0 | HP35: =HP32-'Payroll Register'!AM20 -> 0.0022988507 | HY35: =HY32-'Payroll Register'!AM21 -> 0.00068965518 | IH35: =IH32-'Payroll Register'!AM22 -> -0.00022988504 | IQ35: =IQ32-'Payroll Register'!AM23 -> 0 | IZ35: =IZ32-'Payroll Register'!AM24 -> 0.0035862069 | JI35: =JI32-'Payroll Register'!AM25 -> 0.00022988506 | JR35: =JR32-'Payroll Register'!AM26 -> 0.0017471265 | KA35: =KA32-'Payroll Register'!AM27 -> -0.0028965517 | KJ35: =KJ32-'Payroll Register'!AM28 -> 0

Sheet Timesheet
A1: ECN | B1: Program | C1: Group | D1: Name | E1: 46023 | M1: 46024 | T1: 46025 | Z1: 46026 | AF1: 46027 | AL1: 46028 | AR1: 46029 | AX1: 46030 | BD1: 46031 | BJ1: 46032 | BP1: 46033 | BV1: 46034 | CB1: 46035 | CH1: 46036 | CN1: 46037 | CT1: SUMMARY
E2: IN | F2: OUT | G2: TOTAL REGULAR HOURS | H2: TOTAL REGULAR HOLIDAY HOURS | I2: TOTAL O.T. HOURS | J2: TOTAL TARDY MINUTES | K2: TOTAL NIGHT DIFFERENTIAL | L2: TOTAL REGULAR HOLIDAY NIGHT DIFFERENTIAL | M2: IN | N2: OUT | O2: TOTAL REGULAR HOURS | P2: TOTAL O.T. HOURS | Q2: TOTAL RDOT HOURS | R2: TOTAL TARDY MINUTES | S2: TOTAL NIGHT DIFFERENTIAL | T2: IN | U2: OUT | V2: TOTAL REGULAR HOURS | W2: TOTAL O.T. HOURS | X2: TOTAL TARDY MINUTES | Y2: TOTAL NIGHT DIFFERENTIAL | Z2: IN | AA2: OUT | AB2: TOTAL REGULAR HOURS | AC2: TOTAL O.T. HOURS | AD2: TOTAL TARDY MINUTES | AE2: TOTAL NIGHT DIFFERENTIAL | AF2: IN | AG2: OUT | AH2: TOTAL REGULAR HOURS | AI2: TOTAL O.T. HOURS | AJ2: TOTAL TARDY MINUTES | AK2: TOTAL NIGHT DIFFERENTIAL | AL2: IN | AM2: OUT | AN2: TOTAL REGULAR HOURS | AO2: TOTAL O.T. HOURS | AP2: TOTAL TARDY MINUTES | AQ2: TOTAL NIGHT DIFFERENTIAL | AR2: IN | AS2: OUT | AT2: TOTAL REGULAR HOURS | AU2: TOTAL O.T. HOURS | AV2: TOTAL TARDY MINUTES | AW2: TOTAL NIGHT DIFFERENTIAL | AX2: IN | AY2: OUT | AZ2: TOTAL REGULAR HOURS | BA2: TOTAL O.T. HOURS | BB2: TOTAL TARDY MINUTES | BC2: TOTAL NIGHT DIFFERENTIAL | BD2: IN | BE2: OUT | BF2: TOTAL REGULAR HOURS | BG2: TOTAL O.T. HOURS | BH2: TOTAL TARDY MINUTES | BI2: TOTAL NIGHT DIFFERENTIAL | BJ2: IN | BK2: OUT | BL2: TOTAL REGULAR HOURS | BM2: TOTAL O.T. HOURS | BN2: TOTAL TARDY MINUTES | BO2: TOTAL NIGHT DIFFERENTIAL | BP2: IN | BQ2: OUT | BR2: TOTAL REGULAR HOURS | BS2: TOTAL O.T. HOURS | BT2: TOTAL TARDY MINUTES | BU2: TOTAL NIGHT DIFFERENTIAL | BV2: IN | BW2: OUT | BX2: TOTAL REGULAR HOURS | BY2: TOTAL O.T. HOURS | BZ2: TOTAL TARDY MINUTES | CA2: TOTAL NIGHT DIFFERENTIAL | CB2: IN | CC2: OUT | CD2: TOTAL REGULAR HOURS | CE2: TOTAL O.T. HOURS | CF2: TOTAL TARDY MINUTES | CG2: TOTAL NIGHT DIFFERENTIAL | CH2: IN | CI2: OUT | CJ2: TOTAL REGULAR HOURS | CK2: TOTAL O.T. HOURS | CL2: TOTAL TARDY MINUTES | CM2: TOTAL NIGHT DIFFERENTIAL | CN2: IN | CO2: OUT | CP2: TOTAL REGULAR HOURS | CQ2: TOTAL O.T. HOURS | CR2: TOTAL TARDY MINUTES | CS2: TOTAL NIGHT DIFFERENTIAL | CT2: TOTAL REGULAR HOURS | CU2: TOTAL REGULAR HOLIDAY HOURS | CV2: TOTAL O.T. HOURS | CW2: TOTAL RDOT HOURS | CX2: TOTAL TARDY MINUTES | CY2: TOTAL NIGHT DIFFERENTIAL | CZ2: TOTAL REGULAR HOLIDAY NIGHT DIFFERENTIAL | DA2: HOLIDAY OFF | DB2: TOTAL PAID LEAVES | DC2: TOTAL LWOP | DD2: REMARKS
A3: 8001 | B3: Unipart Logistics | C3: L1 | D3: A | E3: Holiday Off | F3: Holiday Off | G3: Holiday Off | H3: Holiday Off | I3: Holiday Off | J3: Holiday Off | K3: Holiday Off | L3: Holiday Off | M3: Vacation Leave | N3: Vacation Leave | O3: Vacation Leave | P3: Vacation Leave | Q3: Vacation Leave | R3: Vacation Leave | S3: Vacation Leave | T3: OFF | U3: OFF | V3: OFF | W3: OFF | X3: OFF | Y3: OFF | Z3: OFF | AA3: OFF | AB3: OFF | AC3: OFF | AD3: OFF | AE3: OFF | AF3: 0.625 | AG3: 0 | AH3: 8 | AI3: 0 | AJ3: 0 | AK3: 2 | AL3: 0.625 | AM3: 0 | AN3: 8 | AO3: 0 | AP3: 0 | AQ3: 2 | AR3: 0.625 | AS3: 0 | AT3: 8 | AU3: 0 | AV3: 0 | AW3: 2 | AX3: 0.41666667 | AY3: 0.79166667 | AZ3: 8 | BA3: 0 | BB3: 0 | BC3: 0 | BD3: 0.41666667 | BE3: 0.79166667 | BF3: 8 | BG3: 0 | BH3: 0 | BI3: 0 | BJ3: OFF | BK3: OFF | BL3: OFF | BM3: OFF | BN3: OFF | BO3: OFF | BP3: OFF | BQ3: OFF | BR3: OFF | BS3: OFF | BT3: OFF | BU3: OFF | BV3: 0.625 | BW3: 0 | BX3: 8 | BY3: 0 | BZ3: 0 | CA3: 2 | CB3: 0.625 | CC3: 0 | CD3: 8 | CE3: 0 | CF3: 0 | CG3: 2 | CH3: 0.625 | CI3: 0 | CJ3: 8 | CK3: 0 | CL3: 0 | CM3: 2 | CN3: 0.41666667 | CO3: 0.79166667 | CP3: 8 | CQ3: 0 | CR3: 0 | CS3: 0 | CT3: =SUM(G3,O3,V3,AB3,AH3,AN3,AT3,AZ3,BF3,BL3,BR3,BX3,CD3,CJ3,CP3) -> 72 | CU3: =SUM(H3) -> 0 | CV3: =SUM(I3,P3,W3,AC3,AI3,AO3,AU3,BA3,BG3,BM3,BS3,BY3,CE3,CK3,CQ3) -> 0 | CW3: =SUM(Q3) -> 0 | CX3: =SUM(J3,R3,X3,AD3,AJ3,AP3,AV3,BB3,BH3,BN3,BT3,BZ3,CF3,CL3,CR3) -> 0 | CY3: =SUM(K3,S3,Y3,AE3,AK3,AQ3,AW3,BC3,BI3,BO3,BU3,CA3,CG3,CM3,CS3) -> 12 | CZ3: =SUM(L3) -> 0 | DA3: 1 | DB3: 1 | DC3: 0
A4: 8008 | B4: Unipart Logistics | C4: L1 | D4: B | E4: 0.625 | F4: 0 | G4: 0 | H4: 8 | I4: 0 | J4: 0 | K4: 0 | L4: 2 | M4: 0.625 | N4: 0.041666667 | O4: 8 | P4: 1 | Q4: 0 | R4: 0 | S4: 3 | T4: OFF | U4: OFF | V4: OFF | W4: OFF | X4: OFF | Y4: OFF | Z4: OFF | AA4: OFF | AB4: OFF | AC4: OFF | AD4: OFF | AE4: OFF | AF4: 0.625 | AG4: 0.041666667 | AH4: 8 | AI4: 0 | AJ4: 0 | AK4: 3 | AL4: 0.625 | AM4: 0.041666667 | AN4: 8 | AO4: 1 | AP4: 0 | AQ4: 3 | AR4: 0.625 | AS4: 0.041666667 | AT4: 8 | AU4: 1 | AV4: 0 | AW4: 3 | AX4: 0.625 | AY4: 0.041666667 | AZ4: 8 | BA4: 1 | BB4: 0 | BC4: 3 | BD4: 0.625 | BE4: 0.041666667 | BF4: 8 | BG4: 1 | BH4: 0 | BI4: 3 | BJ4: OFF | BK4: OFF | BL4: OFF | BM4: OFF | BN4: OFF | BO4: OFF | BP4: OFF | BQ4: OFF | BR4: OFF | BS4: OFF | BT4: OFF | BU4: OFF | BV4: 0.625 | BW4: 0.041666667 | BX4: 8 | BY4: 1 | BZ4: 0 | CA4: 3 | CB4: 0.625 | CC4: 0.041666667 | CD4: 8 | CE4: 1 | CF4: 0 | CG4: 3 | CH4: 0.625 | CI4: 0.041666667 | CJ4: 8 | CK4: 1 | CL4: 0 | CM4: 3 | CN4: 0.625 | CO4: 0.041666667 | CP4: 8 | CQ4: 1 | CR4: 0 | CS4: 3 | CT4: =SUM(G4,O4,V4,AB4,AH4,AN4,AT4,AZ4,BF4,BL4,BR4,BX4,CD4,CJ4,CP4) -> 80 | CU4: =SUM(H4) -> 8 | CV4: =SUM(I4,P4,W4,AC4,AI4,AO4,AU4,BA4,BG4,BM4,BS4,BY4,CE4,CK4,CQ4) -> 9 | CW4: =SUM(Q4) -> 0 | CX4: =SUM(J4,R4,X4,AD4,AJ4,AP4,AV4,BB4,BH4,BN4,BT4,BZ4,CF4,CL4,CR4) -> 0 | CY4: =SUM(K4,S4,Y4,AE4,AK4,AQ4,AW4,BC4,BI4,BO4,BU4,CA4,CG4,CM4,CS4) -> 30 | CZ4: =SUM(L4) -> 2 | DA4: 0 | DB4: 0 | DC4: 0
A5: 8010 | B5: Unipart Logistics | C5: L1 | D5: C | E5: OFF | F5: OFF | G5: OFF | H5: OFF | I5: OFF | J5: OFF | K5: OFF | L5: OFF | M5: OFF | N5: OFF | O5: OFF | P5: OFF | Q5: OFF | R5: OFF | S5: OFF | T5: 0.25 | U5: 0.75 | V5: 8 | W5: 3 | X5: 0 | Y5: 0 | Z5: 0.25 | AA5: 0.75 | AB5: 8 | AC5: 3 | AD5: 0 | AE5: 0 | AF5: 0.41666667 | AG5: 0.79166667 | AH5: 8 | AI5: 0 | AJ5: 0 | AK5: 0 | AL5: 0.41666667 | AM5: 0.79166667 | AN5: 8 | AO5: 0 | AP5: 0 | AQ5: 0 | AR5: 0.41666667 | AS5: 0.79166667 | AT5: 8 | AU5: 0 | AV5: 0 | AW5: 0 | AX5: OFF | AY5: OFF | AZ5: OFF | BA5: OFF | BB5: OFF | BC5: OFF | BD5: OFF | BE5: OFF | BF5: OFF | BG5: OFF | BH5: OFF | BI5: OFF | BJ5: 0.25 | BK5: 0.75 | BL5: 8 | BM5: 3 | BN5: 0 | BO5: 0 | BP5: 0.25 | BQ5: 0.75 | BR5: 8 | BS5: 3 | BT5: 0 | BU5: 0 | BV5: 0.41666667 | BW5: 0.79166667 | BX5: 8 | BY5: 0 | BZ5: 0 | CA5: 0 | CB5: 0.41666667 | CC5: 0.79166667 | CD5: 8 | CE5: 0 | CF5: 0 | CG5: 0 | CH5: 0.41666667 | CI5: 0.79166667 | CJ5: 8 | CK5: 0 | CL5: 0 | CM5: 0 | CN5: OFF | CO5: OFF | CP5: OFF | CQ5: OFF | CR5: OFF | CS5: OFF | CT5: =SUM(G5,O5,V5,AB5,AH5,AN5,AT5,AZ5,BF5,BL5,BR5,BX5,CD5,CJ5,CP5) -> 80 | CU5: =SUM(H5) -> 0 | CV5: =SUM(I5,P5,W5,AC5,AI5,AO5,AU5,BA5,BG5,BM5,BS5,BY5,CE5,CK5,CQ5) -> 12 | CW5: =SUM(Q5) -> 0 | CX5: =SUM(J5,R5,X5,AD5,AJ5,AP5,AV5,BB5,BH5,BN5,BT5,BZ5,CF5,CL5,CR5) -> 0 | CY5: =SUM(K5,S5,Y5,AE5,AK5,AQ5,AW5,BC5,BI5,BO5,BU5,CA5,CG5,CM5,CS5) -> 0 | CZ5: =SUM(L5) -> 0 | DA5: 0 | DB5: 0 | DC5: 0
A6: 8011 | B6: Shared | C6: Shared | D6: D | E6: Holiday Off | F6: Holiday Off | G6: Holiday Off | H6: Holiday Off | I6: Holiday Off | J6: Holiday Off | K6: Holiday Off | L6: Holiday Off | M6: 0.375 | N6: 0.75 | O6: 8 | P6: 0 | Q6: 0 | R6: 0 | S6: 0 | T6: OFF | U6: OFF | V6: OFF | W6: OFF | X6: OFF | Y6: OFF | Z6: OFF | AA6: OFF | AB6: OFF | AC6: OFF | AD6: OFF | AE6: OFF | AF6: 0.375 | AG6: 0.75 | AH6: 8 | AI6: 0 | AJ6: 0 | AK6: 0 | AL6: 0.375 | AM6: 0.75 | AN6: 8 | AO6: 0 | AP6: 0 | AQ6: 0 | AR6: 0.375 | AS6: 0.75 | AT6: 8 | AU6: 0 | AV6: 0 | AW6: 0 | AX6: 0.375 | AY6: 0.75 | AZ6: 8 | BA6: 0 | BB6: 0 | BC6: 0 | BD6: 0.375 | BE6: 0.75 | BF6: 8 | BG6: 0 | BH6: 0 | BI6: 0 | BJ6: OFF | BK6: OFF | BL6: OFF | BM6: OFF | BN6: OFF | BO6: OFF | BP6: OFF | BQ6: OFF | BR6: OFF | BS6: OFF | BT6: OFF | BU6: OFF | BV6: 0.375 | BW6: 0.75 | BX6: 8 | BY6: 0 | BZ6: 0 | CA6: 0 | CB6: 0.375 | CC6: 0.75 | CD6: 8 | CE6: 0 | CF6: 0 | CG6: 0 | CH6: 0.375 | CI6: 0.75 | CJ6: 8 | CK6: 0 | CL6: 0 | CM6: 0 | CN6: 0.375 | CO6: 0.75 | CP6: 8 | CQ6: 0 | CR6: 0 | CS6: 0 | CT6: =SUM(G6,O6,V6,AB6,AH6,AN6,AT6,AZ6,BF6,BL6,BR6,BX6,CD6,CJ6,CP6) -> 80 | CU6: =SUM(H6) -> 0 | CV6: =SUM(I6,P6,W6,AC6,AI6,AO6,AU6,BA6,BG6,BM6,BS6,BY6,CE6,CK6,CQ6) -> 0 | CW6: =SUM(Q6) -> 0 | CX6: =SUM(J6,R6,X6,AD6,AJ6,AP6,AV6,BB6,BH6,BN6,BT6,BZ6,CF6,CL6,CR6) -> 0 | CY6: =SUM(K6,S6,Y6,AE6,AK6,AQ6,AW6,BC6,BI6,BO6,BU6,CA6,CG6,CM6,CS6) -> 0 | CZ6: =SUM(L6) -> 0 | DA6: 1 | DB6: 0 | DC6: 0
A7: 8012 | B7: CEVA Logistics | C7: CEVA Logistics | D7: E | E7: Holiday Off | F7: Holiday Off | G7: Holiday Off | H7: Holiday Off | I7: Holiday Off | J7: Holiday Off | K7: Holiday Off | L7: Holiday Off | M7: 0.54166667 | N7: 0.91666667 | O7: 8 | P7: 0 | Q7: 0 | R7: 0 | S7: 0 | T7: OFF | U7: OFF | V7: OFF | W7: OFF | X7: OFF | Y7: OFF | Z7: OFF | AA7: OFF | AB7: OFF | AC7: OFF | AD7: OFF | AE7: OFF | AF7: 0.54166667 | AG7: 0.91666667 | AH7: 8 | AI7: 0 | AJ7: 0 | AK7: 0 | AL7: 0.54166667 | AM7: 0.91666667 | AN7: 8 | AO7: 0 | AP7: 0 | AQ7: 0 | AR7: 0.54166667 | AS7: 0.91666667 | AT7: 8 | AU7: 0 | AV7: 0 | AW7: 0 | AX7: 0.54166667 | AY7: 0.91666667 | AZ7: 8 | BA7: 0 | BB7: 0 | BC7: 0 | BD7: 0.54166667 | BE7: 0.91666667 | BF7: 8 | BG7: 0 | BH7: 0 | BI7: 0 | BJ7: OFF | BK7: OFF | BL7: OFF | BM7: OFF | BN7: OFF | BO7: OFF | BP7: OFF | BQ7: OFF | BR7: OFF | BS7: OFF | BT7: OFF | BU7: OFF | BV7: 0.54166667 | BW7: 0.91666667 | BX7: 8 | BY7: 0 | BZ7: 0 | CA7: 0 | CB7: 0.54166667 | CC7: 0.91666667 | CD7: 8 | CE7: 0 | CF7: 0 | CG7: 0 | CH7: 0.54166667 | CI7: 0.91666667 | CJ7: 8 | CK7: 0 | CL7: 0 | CM7: 0 | CN7: Vacation Leave | CO7: Vacation Leave | CP7: Vacation Leave | CQ7: Vacation Leave | CR7: Vacation Leave | CS7: Vacation Leave | CT7: =SUM(G7,O7,V7,AB7,AH7,AN7,AT7,AZ7,BF7,BL7,BR7,BX7,CD7,CJ7,CP7) -> 72 | CU7: =SUM(H7) -> 0 | CV7: =SUM(I7,P7,W7,AC7,AI7,AO7,AU7,BA7,BG7,BM7,BS7,BY7,CE7,CK7,CQ7) -> 0 | CW7: =SUM(Q7) -> 0 | CX7: =SUM(J7,R7,X7,AD7,AJ7,AP7,AV7,BB7,BH7,BN7,BT7,BZ7,CF7,CL7,CR7) -> 0 | CY7: =SUM(K7,S7,Y7,AE7,AK7,AQ7,AW7,BC7,BI7,BO7,BU7,CA7,CG7,CM7,CS7) -> 0 | CZ7: =SUM(L7) -> 0 | DA7: 1 | DB7: 1 | DC7: 0
A8: 8015 | B8: Unipart Logistics | C8: L1 | D8: F | E8: 0.25 | F8: 0.625 | G8: 0 | H8: 8 | I8: 0 | J8: 0 | K8: 0 | L8: 0 | M8: 0.25 | N8: 0.625 | O8: 8 | P8: 0 | Q8: 0 | R8: 0 | S8: 0 | T8: OFF | U8: OFF | V8: OFF | W8: OFF | X8: OFF | Y8: OFF | Z8: OFF | AA8: OFF | AB8: OFF | AC8: OFF | AD8: OFF | AE8: OFF | AF8: 0.25 | AG8: 0.625 | AH8: 8 | AI8: 0 | AJ8: 0 | AK8: 0 | AL8: 0.25 | AM8: 0.625 | AN8: 8 | AO8: 0 | AP8: 0 | AQ8: 0 | AR8: 0.25 | AS8: 0.625 | AT8: 8 | AU8: 0 | AV8: 0 | AW8: 0 | AX8: 0.25 | AY8: 0.625 | AZ8: 8 | BA8: 0 | BB8: 0 | BC8: 0 | BD8: 0.25 | BE8: 0.625 | BF8: 8 | BG8: 0 | BH8: 0 | BI8: 0 | BJ8: OFF | BK8: OFF | BL8: OFF | BM8: OFF | BN8: OFF | BO8: OFF | BP8: OFF | BQ8: OFF | BR8: OFF | BS8: OFF | BT8: OFF | BU8: OFF | BV8: 0.25 | BW8: 0.625 | BX8: 8 | BY8: 0 | BZ8: 0 | CA8: 0 | CB8: 0.25 | CC8: 0.625 | CD8: 8 | CE8: 0 | CF8: 0 | CG8: 0 | CH8: 0.25 | CI8: 0.625 | CJ8: 8 | CK8: 0 | CL8: 0 | CM8: 0 | CN8: 0.25 | CO8: 0.625 | CP8: 8 | CQ8: 0 | CR8: 0 | CS8: 0 | CT8: =SUM(G8,O8,V8,AB8,AH8,AN8,AT8,AZ8,BF8,BL8,BR8,BX8,CD8,CJ8,CP8) -> 80 | CU8: =SUM(H8) -> 8 | CV8: =SUM(I8,P8,W8,AC8,AI8,AO8,AU8,BA8,BG8,BM8,BS8,BY8,CE8,CK8,CQ8) -> 0 | CW8: =SUM(Q8) -> 0 | CX8: =SUM(J8,R8,X8,AD8,AJ8,AP8,AV8,BB8,BH8,BN8,BT8,BZ8,CF8,CL8,CR8) -> 0 | CY8: =SUM(K8,S8,Y8,AE8,AK8,AQ8,AW8,BC8,BI8,BO8,BU8,CA8,CG8,CM8,CS8) -> 0 | CZ8: =SUM(L8) -> 0 | DA8: 0 | DB8: 0 | DC8: 0
A9: 8019 | B9: Unipart Logistics | C9: L1 | D9: G | E9: 0.58333333 | F9: 0.95833333 | G9: 0 | H9: 8 | I9: 0 | J9: 0 | K9: 0 | L9: 1 | M9: 0.58333333 | N9: 0.95833333 | O9: 8 | P9: 0 | Q9: 0 | R9: 0 | S9: 1 | T9: OFF | U9: OFF | V9: OFF | W9: OFF | X9: OFF | Y9: OFF | Z9: OFF | AA9: OFF | AB9: OFF | AC9: OFF | AD9: OFF | AE9: OFF | AF9: 0.58333333 | AG9: 0.95833333 | AH9: 8 | AI9: 0 | AJ9: 0 | AK9: 1 | AL9: 0.58333333 | AM9: 0.95833333 | AN9: 8 | AO9: 0 | AP9: 0 | AQ9: 1 | AR9: 0.58333333 | AS9: 0.95833333 | AT9: 8 | AU9: 0 | AV9: 0 | AW9: 1 | AX9: 0.58333333 | AY9: 0.95833333 | AZ9: 8 | BA9: 0 | BB9: 0 | BC9: 1 | BD9: 0.58333333 | BE9: 0.95833333 | BF9: 8 | BG9: 0 | BH9: 0 | BI9: 1 | BJ9: OFF | BK9: OFF | BL9: OFF | BM9: OFF | BN9: OFF | BO9: OFF | BP9: OFF | BQ9: OFF | BR9: OFF | BS9: OFF | BT9: OFF | BU9: OFF | BV9: 0.58333333 | BW9: 0.95833333 | BX9: 8 | BY9: 0 | BZ9: 0 | CA9: 1 | CB9: 0.58333333 | CC9: 0.75 | CD9: 4 | CE9: 0 | CF9: 0 | CG9: 0 | CH9: 0.58333333 | CI9: 0.95833333 | CJ9: 8 | CK9: 0 | CL9: 0 | CM9: 1 | CN9: 0.58333333 | CO9: 0.95833333 | CP9: 8 | CQ9: 0 | CR9: 0 | CS9: 1 | CT9: =SUM(G9,O9,V9,AB9,AH9,AN9,AT9,AZ9,BF9,BL9,BR9,BX9,CD9,CJ9,CP9) -> 76 | CU9: =SUM(H9) -> 8 | CV9: =SUM(I9,P9,W9,AC9,AI9,AO9,AU9,BA9,BG9,BM9,BS9,BY9,CE9,CK9,CQ9) -> 0 | CW9: =SUM(Q9) -> 0 | CX9: =SUM(J9,R9,X9,AD9,AJ9,AP9,AV9,BB9,BH9,BN9,BT9,BZ9,CF9,CL9,CR9) -> 0 | CY9: =SUM(K9,S9,Y9,AE9,AK9,AQ9,AW9,BC9,BI9,BO9,BU9,CA9,CG9,CM9,CS9) -> 9 | CZ9: =SUM(L9) -> 1 | DA9: 0 | DB9: 0.5 | DC9: 0
A10: 8036 | B10: SPORTSRADAR | C10: SPORTSRADAR | D10: H | E10: Holiday Off | F10: Holiday Off | G10: Holiday Off | H10: Holiday Off | I10: Holiday Off | J10: Holiday Off | K10: Holiday Off | L10: Holiday Off | M10: 0.33333333 | N10: 0.70833333 | O10: 8 | P10: 0 | Q10: 0 | R10: 0 | S10: 0 | T10: OFF | U10: OFF | V10: OFF | W10: OFF | X10: OFF | Y10: OFF | Z10: OFF | AA10: OFF | AB10: OFF | AC10: OFF | AD10: OFF | AE10: OFF | AF10: 0.27083333 | AG10: 0.64583333 | AH10: 8 | AI10: 0 | AJ10: 0 | AK10: 0 | AL10: 0.27083333 | AM10: 0.64583333 | AN10: 8 | AO10: 0 | AP10: 0 | AQ10: 0 | AR10: 0.27083333 | AS10: 0.64583333 | AT10: 8 | AU10: 0 | AV10: 0 | AW10: 0 | AX10: 0.27083333 | AY10: 0.64583333 | AZ10: 8 | BA10: 0 | BB10: 0 | BC10: 0 | BD10: 0.27083333 | BE10: 0.64583333 | BF10: 8 | BG10: 0 | BH10: 0 | BI10: 0 | BJ10: OFF | BK10: OFF | BL10: OFF | BM10: OFF | BN10: OFF | BO10: OFF | BP10: OFF | BQ10: OFF | BR10: OFF | BS10: OFF | BT10: OFF | BU10: OFF | BV10: 0.27083333 | BW10: 0.64583333 | BX10: 8 | BY10: 0 | BZ10: 0 | CA10: 0 | CB10: 0.27083333 | CC10: 0.64583333 | CD10: 8 | CE10: 0 | CF10: 0 | CG10: 0 | CH10: 0.27083333 | CI10: 0.64583333 | CJ10: 8 | CK10: 0 | CL10: 0 | CM10: 0 | CN10: 0.27083333 | CO10: 0.64583333 | CP10: 8 | CQ10: 0 | CR10: 0 | CS10: 0 | CT10: =SUM(G10,O10,V10,AB10,AH10,AN10,AT10,AZ10,BF10,BL10,BR10,BX10,CD10,CJ10,CP10) -> 80 | CU10: =SUM(H10) -> 0 | CV10: =SUM(I10,P10,W10,AC10,AI10,AO10,AU10,BA10,BG10,BM10,BS10,BY10,CE10,CK10,CQ10) -> 0 | CW10: =SUM(Q10) -> 0 | CX10: =SUM(J10,R10,X10,AD10,AJ10,AP10,AV10,BB10,BH10,BN10,BT10,BZ10,CF10,CL10,CR10) -> 0 | CY10: =SUM(K10,S10,Y10,AE10,AK10,AQ10,AW10,BC10,BI10,BO10,BU10,CA10,CG10,CM10,CS10) -> 0 | CZ10: =SUM(L10) -> 0 | DA10: 1 | DB10: 0 | DC10: 0
A11: 8037 | B11: SPORTSRADAR | C11: SPORTSRADAR | D11: I | E11: Holiday Off | F11: Holiday Off | G11: Holiday Off | H11: Holiday Off | I11: Holiday Off | J11: Holiday Off | K11: Holiday Off | L11: Holiday Off | M11: 0.70833333 | N11: 0.083333333 | O11: 8 | P11: 0 | Q11: 0 | R11: 0 | S11: 4 | T11: OFF | U11: OFF | V11: OFF | W11: OFF | X11: OFF | Y11: OFF | Z11: OFF | AA11: OFF | AB11: OFF | AC11: OFF | AD11: OFF | AE11: OFF | AF11: 0.70833333 | AG11: 0.083333333 | AH11: 8 | AI11: 0 | AJ11: 0 | AK11: 4 | AL11: 0.70833333 | AM11: 0.083333333 | AN11: 8 | AO11: 0 | AP11: 0 | AQ11: 4 | AR11: 0.70833333 | AS11: 0.083333333 | AT11: 8 | AU11: 0 | AV11: 0 | AW11: 4 | AX11: 0.70833333 | AY11: 0.083333333 | AZ11: 8 | BA11: 0 | BB11: 0 | BC11: 4 | BD11: 0.70833333 | BE11: 0.083333333 | BF11: 8 | BG11: 0 | BH11: 0 | BI11: 4 | BJ11: OFF | BK11: OFF | BL11: OFF | BM11: OFF | BN11: OFF | BO11: OFF | BP11: OFF | BQ11: OFF | BR11: OFF | BS11: OFF | BT11: OFF | BU11: OFF | BV11: 0.70833333 | BW11: 0.083333333 | BX11: 8 | BY11: 0 | BZ11: 0 | CA11: 4 | CB11: 0.70833333 | CC11: 0.083333333 | CD11: 8 | CE11: 0 | CF11: 0 | CG11: 4 | CH11: 0.70833333 | CI11: 0.083333333 | CJ11: 8 | CK11: 0 | CL11: 0 | CM11: 4 | CN11: 0.70833333 | CO11: 0.083333333 | CP11: 8 | CQ11: 0 | CR11: 0 | CS11: 4 | CT11: =SUM(G11,O11,V11,AB11,AH11,AN11,AT11,AZ11,BF11,BL11,BR11,BX11,CD11,CJ11,CP11) -> 80 | CU11: =SUM(H11) -> 0 | CV11: =SUM(I11,P11,W11,AC11,AI11,AO11,AU11,BA11,BG11,BM11,BS11,BY11,CE11,CK11,CQ11) -> 0 | CW11: =SUM(Q11) -> 0 | CX11: =SUM(J11,R11,X11,AD11,AJ11,AP11,AV11,BB11,BH11,BN11,BT11,BZ11,CF11,CL11,CR11) -> 0 | CY11: =SUM(K11,S11,Y11,AE11,AK11,AQ11,AW11,BC11,BI11,BO11,BU11,CA11,CG11,CM11,CS11) -> 40 | CZ11: =SUM(L11) -> 0 | DA11: 1 | DB11: 0 | DC11: 0
A12: 8038 | B12: Unipart Logistics | C12: L1 | D12: J | E12: OFF | F12: OFF | G12: OFF | H12: OFF | I12: OFF | J12: OFF | K12: OFF | L12: OFF | M12: 0 | N12: 0.25 | O12: 0 | P12: 0 | Q12: 6 | R12: 0 | S12: 6 | T12: 0.75 | U12: 0.25 | V12: 8 | W12: 3 | X12: 0 | Y12: 8 | Z12: 0.75 | AA12: 0.25 | AB12: 8 | AC12: 3 | AD12: 0 | AE12: 8 | AF12: 0.91666667 | AG12: 0.29166667 | AH12: 8 | AI12: 0 | AJ12: 0 | AK12: 8 | AL12: 0.91666667 | AM12: 0.29166667 | AN12: 8 | AO12: 0 | AP12: 0 | AQ12: 8 | AR12: 0.91666667 | AS12: 0.29166667 | AT12: 8 | AU12: 0 | AV12: 0 | AW12: 8 | AX12: OFF | AY12: OFF | AZ12: OFF | BA12: OFF | BB12: OFF | BC12: OFF | BD12: OFF | BE12: OFF | BF12: OFF | BG12: OFF | BH12: OFF | BI12: OFF | BJ12: 0.75 | BK12: 0.25 | BL12: 8 | BM12: 3 | BN12: 0 | BO12: 8 | BP12: 0.75 | BQ12: 0.25 | BR12: 8 | BS12: 3 | BT12: 0 | BU12: 8 | BV12: 0.91666667 | BW12: 0.29166667 | BX12: 8 | BY12: 0 | BZ12: 0 | CA12: 8 | CB12: 0.91666667 | CC12: 0.29166667 | CD12: 8 | CE12: 0 | CF12: 0 | CG12: 8 | CH12: 0.91666667 | CI12: 0.29166667 | CJ12: 8 | CK12: 0 | CL12: 0 | CM12: 8 | CN12: OFF | CO12: OFF | CP12: OFF | CQ12: OFF | CR12: OFF | CS12: OFF | CT12: =SUM(G12,O12,V12,AB12,AH12,AN12,AT12,AZ12,BF12,BL12,BR12,BX12,CD12,CJ12,CP12) -> 80 | CU12: =SUM(H12) -> 0 | CV12: =SUM(I12,P12,W12,AC12,AI12,AO12,AU12,BA12,BG12,BM12,BS12,BY12,CE12,CK12,CQ12) -> 12 | CW12: =SUM(Q12) -> 6 | CX12: =SUM(J12,R12,X12,AD12,AJ12,AP12,AV12,BB12,BH12,BN12,BT12,BZ12,CF12,CL12,CR12) -> 0 | CY12: =SUM(K12,S12,Y12,AE12,AK12,AQ12,AW12,BC12,BI12,BO12,BU12,CA12,CG12,CM12,CS12) -> 86 | CZ12: =SUM(L12) -> 0 | DA12: 0 | DB12: 0 | DC12: 0
A13: 8042 | B13: Unipart Logistics | C13: L1 | D13: K | E13: 0.91666667 | F13: 0.29166667 | G13: 6 | H13: 2 | I13: 0 | J13: 0 | K13: 6 | L13: 2 | M13: Vacation Leave | N13: Vacation Leave | O13: Vacation Leave | P13: Vacation Leave | Q13: Vacation Leave | R13: Vacation Leave | S13: Vacation Leave | T13: OFF | U13: OFF | V13: OFF | W13: OFF | X13: OFF | Y13: OFF | Z13: OFF | AA13: OFF | AB13: OFF | AC13: OFF | AD13: OFF | AE13: OFF | AF13: 0.91666667 | AG13: 0.29166667 | AH13: 8 | AI13: 0 | AJ13: 0 | AK13: 8 | AL13: 0.91666667 | AM13: 0.29166667 | AN13: 8 | AO13: 0 | AP13: 0 | AQ13: 8 | AR13: 0.91666667 | AS13: 0.29166667 | AT13: 8 | AU13: 0 | AV13: 0 | AW13: 8 | AX13: 0.91666667 | AY13: 0.29166667 | AZ13: 8 | BA13: 0 | BB13: 0 | BC13: 8 | BD13: 0.91666667 | BE13: 0.29166667 | BF13: 8 | BG13: 0 | BH13: 0 | BI13: 8 | BJ13: OFF | BK13: OFF | BL13: OFF | BM13: OFF | BN13: OFF | BO13: OFF | BP13: OFF | BQ13: OFF | BR13: OFF | BS13: OFF | BT13: OFF | BU13: OFF | BV13: 0.91666667 | BW13: 0.29166667 | BX13: 8 | BY13: 0 | BZ13: 0 | CA13: 8 | CB13: 0.91666667 | CC13: 0.29166667 | CD13: 8 | CE13: 0 | CF13: 0 | CG13: 8 | CH13: 0.91666667 | CI13: 0.29166667 | CJ13: 8 | CK13: 0 | CL13: 0 | CM13: 8 | CN13: 0.91666667 | CO13: 0.29166667 | CP13: 8 | CQ13: 0 | CR13: 0 | CS13: 8 | CT13: =SUM(G13,O13,V13,AB13,AH13,AN13,AT13,AZ13,BF13,BL13,BR13,BX13,CD13,CJ13,CP13) -> 78 | CU13: =SUM(H13) -> 2 | CV13: =SUM(I13,P13,W13,AC13,AI13,AO13,AU13,BA13,BG13,BM13,BS13,BY13,CE13,CK13,CQ13) -> 0 | CW13: =SUM(Q13) -> 0 | CX13: =SUM(J13,R13,X13,AD13,AJ13,AP13,AV13,BB13,BH13,BN13,BT13,BZ13,CF13,CL13,CR13) -> 0 | CY13: =SUM(K13,S13,Y13,AE13,AK13,AQ13,AW13,BC13,BI13,BO13,BU13,CA13,CG13,CM13,CS13) -> 78 | CZ13: =SUM(L13) -> 2 | DA13: 0 | DB13: 1 | DC13: 0
A14: 8043 | B14: SPORTSRADAR | C14: SPORTSRADAR | D14: L | E14: Holiday Off | F14: Holiday Off | G14: Holiday Off | H14: Holiday Off | I14: Holiday Off | J14: Holiday Off | K14: Holiday Off | L14: Holiday Off | M14: 0.625 | N14: 0 | O14: 8 | P14: 0 | Q14: 0 | R14: 0 | S14: 2 | T14: OFF | U14: OFF | V14: OFF | W14: OFF | X14: OFF | Y14: OFF | Z14: OFF | AA14: OFF | AB14: OFF | AC14: OFF | AD14: OFF | AE14: OFF | AF14: 0.625 | AG14: 0 | AH14: 8 | AI14: 0 | AJ14: 0 | AK14: 2 | AL14: 0.625 | AM14: 0 | AN14: 8 | AO14: 0 | AP14: 0 | AQ14: 2 | AR14: 0.625 | AS14: 0 | AT14: 8 | AU14: 0 | AV14: 0 | AW14: 2 | AX14: 0.625 | AY14: 0 | AZ14: 8 | BA14: 0 | BB14: 0 | BC14: 2 | BD14: 0.625 | BE14: 0 | BF14: 8 | BG14: 0 | BH14: 0 | BI14: 2 | BJ14: OFF | BK14: OFF | BL14: OFF | BM14: OFF | BN14: OFF | BO14: OFF | BP14: OFF | BQ14: OFF | BR14: OFF | BS14: OFF | BT14: OFF | BU14: OFF | BV14: 0.625 | BW14: 0 | BX14: 8 | BY14: 0 | BZ14: 0 | CA14: 2 | CB14: 0.625 | CC14: 0 | CD14: 8 | CE14: 0 | CF14: 0 | CG14: 2 | CH14: 0.625 | CI14: 0 | CJ14: 8 | CK14: 0 | CL14: 0 | CM14: 2 | CN14: 0.625 | CO14: 0 | CP14: 8 | CQ14: 0 | CR14: 0 | CS14: 2 | CT14: =SUM(G14,O14,V14,AB14,AH14,AN14,AT14,AZ14,BF14,BL14,BR14,BX14,CD14,CJ14,CP14) -> 80 | CU14: =SUM(H14) -> 0 | CV14: =SUM(I14,P14,W14,AC14,AI14,AO14,AU14,BA14,BG14,BM14,BS14,BY14,CE14,CK14,CQ14) -> 0 | CW14: =SUM(Q14) -> 0 | CX14: =SUM(J14,R14,X14,AD14,AJ14,AP14,AV14,BB14,BH14,BN14,BT14,BZ14,CF14,CL14,CR14) -> 0 | CY14: =SUM(K14,S14,Y14,AE14,AK14,AQ14,AW14,BC14,BI14,BO14,BU14,CA14,CG14,CM14,CS14) -> 20 | CZ14: =SUM(L14) -> 0 | DA14: 1 | DB14: 0 | DC14: 0
A15: 8044 | B15: SPORTSRADAR | C15: SPORTSRADAR | D15: M | E15: Holiday Off | F15: Holiday Off | G15: Holiday Off | H15: Holiday Off | I15: Holiday Off | J15: Holiday Off | K15: Holiday Off | L15: Holiday Off | M15: Vacation Leave | N15: Vacation Leave | O15: Vacation Leave | P15: Vacation Leave | Q15: Vacation Leave | R15: Vacation Leave | S15: Vacation Leave | T15: OFF | U15: OFF | V15: OFF | W15: OFF | X15: OFF | Y15: OFF | Z15: OFF | AA15: OFF | AB15: OFF | AC15: OFF | AD15: OFF | AE15: OFF | AF15: Vacation Leave | AG15: Vacation Leave | AH15: Vacation Leave | AI15: Vacation Leave | AJ15: Vacation Leave | AK15: Vacation Leave | AL15: Vacation Leave | AM15: Vacation Leave | AN15: Vacation Leave | AO15: Vacation Leave | AP15: Vacation Leave | AQ15: Vacation Leave | AR15: Vacation Leave | AS15: Vacation Leave | AT15: Vacation Leave | AU15: Vacation Leave | AV15: Vacation Leave | AW15: Vacation Leave | AX15: Vacation Leave | AY15: Vacation Leave | AZ15: Vacation Leave | BA15: Vacation Leave | BB15: Vacation Leave | BC15: Vacation Leave | BD15: Vacation Leave | BE15: Vacation Leave | BF15: Vacation Leave | BG15: Vacation Leave | BH15: Vacation Leave | BI15: Vacation Leave | BJ15: OFF | BK15: OFF | BL15: OFF | BM15: OFF | BN15: OFF | BO15: OFF | BP15: OFF | BQ15: OFF | BR15: OFF | BS15: OFF | BT15: OFF | BU15: OFF | BV15: Vacation Leave | BW15: Vacation Leave | BX15: Vacation Leave | BY15: Vacation Leave | BZ15: Vacation Leave | CA15: Vacation Leave | CB15: LWOP | CC15: LWOP | CD15: LWOP | CE15: LWOP | CF15: LWOP | CG15: LWOP | CH15: LWOP | CI15: LWOP | CJ15: LWOP | CK15: LWOP | CL15: LWOP | CM15: LWOP | CN15: LWOP | CO15: LWOP | CP15: LWOP | CQ15: LWOP | CR15: LWOP | CS15: LWOP | CT15: =SUM(G15,O15,V15,AB15,AH15,AN15,AT15,AZ15,BF15,BL15,BR15,BX15,CD15,CJ15,CP15) -> 0 | CU15: =SUM(H15) -> 0 | CV15: =SUM(I15,P15,W15,AC15,AI15,AO15,AU15,BA15,BG15,BM15,BS15,BY15,CE15,CK15,CQ15) -> 0 | CW15: =SUM(Q15) -> 0 | CX15: =SUM(J15,R15,X15,AD15,AJ15,AP15,AV15,BB15,BH15,BN15,BT15,BZ15,CF15,CL15,CR15) -> 0 | CY15: =SUM(K15,S15,Y15,AE15,AK15,AQ15,AW15,BC15,BI15,BO15,BU15,CA15,CG15,CM15,CS15) -> 0 | CZ15: =SUM(L15) -> 0 | DA15: 1 | DB15: 7 | DC15: 3
A16: 8045 | B16: Unipart Logistics | C16: L1 | D16: N | E16: 0.875 | F16: 0.25 | G16: 5 | H16: 3 | I16: 0 | J16: 0 | K16: 6 | L16: 2 | M16: 0.625 | N16: 0 | O16: 8 | P16: 0 | Q16: 0 | R16: 0 | S16: 2 | T16: OFF | U16: OFF | V16: OFF | W16: OFF | X16: OFF | Y16: OFF | Z16: OFF | AA16: OFF | AB16: OFF | AC16: OFF | AD16: OFF | AE16: OFF | AF16: 0.75 | AG16: 0.125 | AH16: 8 | AI16: 0 | AJ16: 0 | AK16: 5 | AL16: 0.75 | AM16: 0.125 | AN16: 8 | AO16: 0 | AP16: 0 | AQ16: 5 | AR16: 0.75 | AS16: 0.125 | AT16: 8 | AU16: 0 | AV16: 0 | AW16: 5 | AX16: 0.875 | AY16: 0.25 | AZ16: 8 | BA16: 0 | BB16: 0 | BC16: 8 | BD16: 0.875 | BE16: 0.25 | BF16: 8 | BG16: 0 | BH16: 0 | BI16: 8 | BJ16: OFF | BK16: OFF | BL16: OFF | BM16: OFF | BN16: OFF | BO16: OFF | BP16: OFF | BQ16: OFF | BR16: OFF | BS16: OFF | BT16: OFF | BU16: OFF | BV16: 0.75 | BW16: 0.125 | BX16: 8 | BY16: 0 | BZ16: 0 | CA16: 5 | CB16: 0.75 | CC16: 0.125 | CD16: 8 | CE16: 0 | CF16: 0 | CG16: 5 | CH16: 0.75 | CI16: 0.125 | CJ16: 8 | CK16: 0 | CL16: 0 | CM16: 5 | CN16: 0.875 | CO16: 0.25 | CP16: 8 | CQ16: 0 | CR16: 0 | CS16: 8 | CT16: =SUM(G16,O16,V16,AB16,AH16,AN16,AT16,AZ16,BF16,BL16,BR16,BX16,CD16,CJ16,CP16) -> 85 | CU16: =SUM(H16) -> 3 | CV16: =SUM(I16,P16,W16,AC16,AI16,AO16,AU16,BA16,BG16,BM16,BS16,BY16,CE16,CK16,CQ16) -> 0 | CW16: =SUM(Q16) -> 0 | CX16: =SUM(J16,R16,X16,AD16,AJ16,AP16,AV16,BB16,BH16,BN16,BT16,BZ16,CF16,CL16,CR16) -> 0 | CY16: =SUM(K16,S16,Y16,AE16,AK16,AQ16,AW16,BC16,BI16,BO16,BU16,CA16,CG16,CM16,CS16) -> 62 | CZ16: =SUM(L16) -> 2 | DA16: 0 | DB16: 0 | DC16: 0
A17: 8046 | B17: SPORTSRADAR | C17: SPORTSRADAR | D17: O | E17: Holiday Off | F17: Holiday Off | G17: Holiday Off | H17: Holiday Off | I17: Holiday Off | J17: Holiday Off | K17: Holiday Off | L17: Holiday Off | M17: OFF | N17: OFF | O17: OFF | P17: OFF | Q17: OFF | R17: OFF | S17: OFF | T17: 0.79166667 | U17: 0.29166667 | V17: 8 | W17: 3 | X17: 0 | Y17: 8 | Z17: 0.79166667 | AA17: 0.29166667 | AB17: 8 | AC17: 3 | AD17: 0 | AE17: 8 | AF17: OFF | AG17: OFF | AH17: OFF | AI17: OFF | AJ17: OFF | AK17: OFF | AL17: OFF | AM17: OFF | AN17: OFF | AO17: OFF | AP17: OFF | AQ17: OFF | AR17: 0.91666667 | AS17: 0.29166667 | AT17: 8 | AU17: 0 | AV17: 0 | AW17: 8 | AX17: 0.91666667 | AY17: 0.29166667 | AZ17: 8 | BA17: 0 | BB17: 0 | BC17: 8 | BD17: 0.91666667 | BE17: 0.29166667 | BF17: 8 | BG17: 0 | BH17: 0 | BI17: 8 | BJ17: 0.79166667 | BK17: 0.29166667 | BL17: 8 | BM17: 3 | BN17: 0 | BO17: 8 | BP17: 0.79166667 | BQ17: 0.29166667 | BR17: 8 | BS17: 3 | BT17: 0 | BU17: 8 | BV17: OFF | BW17: OFF | BX17: OFF | BY17: OFF | BZ17: OFF | CA17: OFF | CB17: OFF | CC17: OFF | CD17: OFF | CE17: OFF | CF17: OFF | CG17: OFF | CH17: 0.91666667 | CI17: 0.29166667 | CJ17: 8 | CK17: 0 | CL17: 0 | CM17: 8 | CN17: 0.91666667 | CO17: 0.29166667 | CP17: 8 | CQ17: 0 | CR17: 0 | CS17: 8 | CT17: =SUM(G17,O17,V17,AB17,AH17,AN17,AT17,AZ17,BF17,BL17,BR17,BX17,CD17,CJ17,CP17) -> 72 | CU17: =SUM(H17) -> 0 | CV17: =SUM(I17,P17,W17,AC17,AI17,AO17,AU17,BA17,BG17,BM17,BS17,BY17,CE17,CK17,CQ17) -> 12 | CW17: =SUM(Q17) -> 0 | CX17: =SUM(J17,R17,X17,AD17,AJ17,AP17,AV17,BB17,BH17,BN17,BT17,BZ17,CF17,CL17,CR17) -> 0 | CY17: =SUM(K17,S17,Y17,AE17,AK17,AQ17,AW17,BC17,BI17,BO17,BU17,CA17,CG17,CM17,CS17) -> 72 | CZ17: =SUM(L17) -> 0 | DA17: 1 | DB17: 0 | DC17: 0
A18: 8047 | B18: SPORTSRADAR | C18: SPORTSRADAR | D18: P | E18: Holiday Off | F18: Holiday Off | G18: Holiday Off | H18: Holiday Off | I18: Holiday Off | J18: Holiday Off | K18: Holiday Off | L18: Holiday Off | M18: OFF | N18: OFF | O18: OFF | P18: OFF | Q18: OFF | R18: OFF | S18: OFF | T18: 0.29166667 | U18: 0.79166667 | V18: 8 | W18: 3 | X18: 0 | Y18: 0 | Z18: 0.29166667 | AA18: 0.79166667 | AB18: 8 | AC18: 3 | AD18: 0 | AE18: 0 | AF18: 0.91666667 | AG18: 0.29166667 | AH18: 8 | AI18: 0 | AJ18: 0 | AK18: 8 | AL18: 0.91666667 | AM18: 0.29166667 | AN18: 8 | AO18: 0 | AP18: 0 | AQ18: 8 | AR18: 0.70833333 | AS18: 0.083333333 | AT18: 8 | AU18: 0 | AV18: 0 | AW18: 4 | AX18: 0.70833333 | AY18: 0.083333333 | AZ18: 8 | BA18: 0 | BB18: 0 | BC18: 4 | BD18: OFF | BE18: OFF | BF18: OFF | BG18: OFF | BH18: OFF | BI18: OFF | BJ18: OFF | BK18: OFF | BL18: OFF | BM18: OFF | BN18: OFF | BO18: OFF | BP18: OFF | BQ18: OFF | BR18: OFF | BS18: OFF | BT18: OFF | BU18: OFF | BV18: 0.91666667 | BW18: 0.29166667 | BX18: 8 | BY18: 0 | BZ18: 0 | CA18: 8 | CB18: 0.91666667 | CC18: 0.29166667 | CD18: 8 | CE18: 0 | CF18: 0 | CG18: 8 | CH18: 0.70833333 | CI18: 0.083333333 | CJ18: 8 | CK18: 0 | CL18: 0 | CM18: 4 | CN18: 0.70833333 | CO18: 0.083333333 | CP18: 8 | CQ18: 0 | CR18: 0 | CS18: 4 | CT18: =SUM(G18,O18,V18,AB18,AH18,AN18,AT18,AZ18,BF18,BL18,BR18,BX18,CD18,CJ18,CP18) -> 80 | CU18: =SUM(H18) -> 0 | CV18: =SUM(I18,P18,W18,AC18,AI18,AO18,AU18,BA18,BG18,BM18,BS18,BY18,CE18,CK18,CQ18) -> 6 | CW18: =SUM(Q18) -> 0 | CX18: =SUM(J18,R18,X18,AD18,AJ18,AP18,AV18,BB18,BH18,BN18,BT18,BZ18,CF18,CL18,CR18) -> 0 | CY18: =SUM(K18,S18,Y18,AE18,AK18,AQ18,AW18,BC18,BI18,BO18,BU18,CA18,CG18,CM18,CS18) -> 48 | CZ18: =SUM(L18) -> 0 | DA18: 1 | DB18: 0 | DC18: 0
A19: 8048 | B19: Unipart Logistics | C19: L1 | D19: Q | E19: 0.625 | F19: 0 | G19: 0 | H19: 8 | I19: 0 | J19: 0 | K19: 0 | L19: 2 | M19: 0.625 | N19: 0 | O19: 8 | P19: 0 | Q19: 0 | R19: 0 | S19: 2 | T19: OFF | U19: OFF | V19: OFF | W19: OFF | X19: OFF | Y19: OFF | Z19: OFF | AA19: OFF | AB19: OFF | AC19: OFF | AD19: OFF | AE19: OFF | AF19: 0.625 | AG19: 0 | AH19: 8 | AI19: 0 | AJ19: 0 | AK19: 2 | AL19: 0.625 | AM19: 0 | AN19: 8 | AO19: 0 | AP19: 0 | AQ19: 2 | AR19: 0.625 | AS19: 0 | AT19: 8 | AU19: 0 | AV19: 0 | AW19: 2 | AX19: 0.625 | AY19: 0 | AZ19: 8 | BA19: 0 | BB19: 0 | BC19: 2 | BD19: 0.625 | BE19: 0 | BF19: 8 | BG19: 0 | BH19: 0 | BI19: 2 | BJ19: OFF | BK19: OFF | BL19: OFF | BM19: OFF | BN19: OFF | BO19: OFF | BP19: OFF | BQ19: OFF | BR19: OFF | BS19: OFF | BT19: OFF | BU19: OFF | BV19: 0.625 | BW19: 0 | BX19: 8 | BY19: 0 | BZ19: 0 | CA19: 2 | CB19: Vacation Leave | CC19: Vacation Leave | CD19: Vacation Leave | CE19: Vacation Leave | CF19: Vacation Leave | CG19: Vacation Leave | CH19: Vacation Leave | CI19: Vacation Leave | CJ19: Vacation Leave | CK19: Vacation Leave | CL19: Vacation Leave | CM19: Vacation Leave | CN19: LWOP | CO19: LWOP | CP19: LWOP | CQ19: LWOP | CR19: LWOP | CS19: LWOP | CT19: =SUM(G19,O19,V19,AB19,AH19,AN19,AT19,AZ19,BF19,BL19,BR19,BX19,CD19,CJ19,CP19) -> 56 | CU19: =SUM(H19) -> 8 | CV19: =SUM(I19,P19,W19,AC19,AI19,AO19,AU19,BA19,BG19,BM19,BS19,BY19,CE19,CK19,CQ19) -> 0 | CW19: =SUM(Q19) -> 0 | CX19: =SUM(J19,R19,X19,AD19,AJ19,AP19,AV19,BB19,BH19,BN19,BT19,BZ19,CF19,CL19,CR19) -> 0 | CY19: =SUM(K19,S19,Y19,AE19,AK19,AQ19,AW19,BC19,BI19,BO19,BU19,CA19,CG19,CM19,CS19) -> 14 | CZ19: =SUM(L19) -> 2 | DA19: 0 | DB19: 2 | DC19: 1
A20: 8050 | B20: Unipart Logistics | C20: L1 | D20: R | E20: Holiday Off | F20: Holiday Off | G20: Holiday Off | H20: Holiday Off | I20: Holiday Off | J20: Holiday Off | K20: Holiday Off | L20: Holiday Off | M20: 0.625 | N20: 0 | O20: 8 | P20: 0 | Q20: 0 | R20: 0 | S20: 2 | T20: OFF | U20: OFF | V20: OFF | W20: OFF | X20: OFF | Y20: OFF | Z20: OFF | AA20: OFF | AB20: OFF | AC20: OFF | AD20: OFF | AE20: OFF | AF20: 0.625 | AG20: 0 | AH20: 8 | AI20: 0 | AJ20: 0 | AK20: 2 | AL20: 0.625 | AM20: 0 | AN20: 8 | AO20: 0 | AP20: 0 | AQ20: 2 | AR20: 0.625 | AS20: 0 | AT20: 8 | AU20: 0 | AV20: 0 | AW20: 2 | AX20: 0.625 | AY20: 0 | AZ20: 8 | BA20: 0 | BB20: 0 | BC20: 2 | BD20: 0.625 | BE20: 0 | BF20: 8 | BG20: 0 | BH20: 0 | BI20: 2 | BJ20: OFF | BK20: OFF | BL20: OFF | BM20: OFF | BN20: OFF | BO20: OFF | BP20: OFF | BQ20: OFF | BR20: OFF | BS20: OFF | BT20: OFF | BU20: OFF | BV20: 0.625 | BW20: 0 | BX20: 8 | BY20: 0 | BZ20: 0 | CA20: 2 | CB20: 0.625 | CC20: 0 | CD20: 8 | CE20: 0 | CF20: 0 | CG20: 2 | CH20: 0.625 | CI20: 0 | CJ20: 8 | CK20: 0 | CL20: 0 | CM20: 2 | CN20: 0.625 | CO20: 0 | CP20: 8 | CQ20: 0 | CR20: 0 | CS20: 2 | CT20: =SUM(G20,O20,V20,AB20,AH20,AN20,AT20,AZ20,BF20,BL20,BR20,BX20,CD20,CJ20,CP20) -> 80 | CU20: =SUM(H20) -> 0 | CV20: =SUM(I20,P20,W20,AC20,AI20,AO20,AU20,BA20,BG20,BM20,BS20,BY20,CE20,CK20,CQ20) -> 0 | CW20: =SUM(Q20) -> 0 | CX20: =SUM(J20,R20,X20,AD20,AJ20,AP20,AV20,BB20,BH20,BN20,BT20,BZ20,CF20,CL20,CR20) -> 0 | CY20: =SUM(K20,S20,Y20,AE20,AK20,AQ20,AW20,BC20,BI20,BO20,BU20,CA20,CG20,CM20,CS20) -> 20 | CZ20: =SUM(L20) -> 0 | DA20: 1 | DB20: 0 | DC20: 0
A21: 8051 | B21: SPORTSRADAR | C21: SPORTSRADAR | D21: S | E21: Holiday Off | F21: Holiday Off | G21: Holiday Off | H21: Holiday Off | I21: Holiday Off | J21: Holiday Off | K21: Holiday Off | L21: Holiday Off | M21: 0.91666667 | N21: 0.29166667 | O21: 8 | P21: 0 | Q21: 0 | R21: 0 | S21: 8 | T21: OFF | U21: OFF | V21: OFF | W21: OFF | X21: OFF | Y21: OFF | Z21: OFF | AA21: OFF | AB21: OFF | AC21: OFF | AD21: OFF | AE21: OFF | AF21: 0.70833333 | AG21: 0.083333333 | AH21: 8 | AI21: 0 | AJ21: 0 | AK21: 4 | AL21: 0.70833333 | AM21: 0.083333333 | AN21: 8 | AO21: 0 | AP21: 0 | AQ21: 4 | AR21: 0.70833333 | AS21: 0.083333333 | AT21: 8 | AU21: 0 | AV21: 0 | AW21: 4 | AX21: OFF | AY21: OFF | AZ21: OFF | BA21: OFF | BB21: OFF | BC21: OFF | BD21: OFF | BE21: OFF | BF21: OFF | BG21: OFF | BH21: OFF | BI21: OFF | BJ21: 0.29166667 | BK21: 0.79166667 | BL21: 8 | BM21: 3 | BN21: 0 | BO21: 0 | BP21: 0.29166667 | BQ21: 0.79166667 | BR21: 8 | BS21: 3 | BT21: 0 | BU21: 0 | BV21: 0.70833333 | BW21: 0.083333333 | BX21: 8 | BY21: 0 | BZ21: 0 | CA21: 4 | CB21: 0.70833333 | CC21: 0.083333333 | CD21: 8 | CE21: 0 | CF21: 0 | CG21: 4 | CH21: Vacation Leave | CI21: Vacation Leave | CJ21: Vacation Leave | CK21: Vacation Leave | CL21: Vacation Leave | CM21: Vacation Leave | CN21: 0.70833333 | CO21: 0.083333333 | CP21: 8 | CQ21: 0 | CR21: 0 | CS21: 4 | CT21: =SUM(G21,O21,V21,AB21,AH21,AN21,AT21,AZ21,BF21,BL21,BR21,BX21,CD21,CJ21,CP21) -> 72 | CU21: =SUM(H21) -> 0 | CV21: =SUM(I21,P21,W21,AC21,AI21,AO21,AU21,BA21,BG21,BM21,BS21,BY21,CE21,CK21,CQ21) -> 6 | CW21: =SUM(Q21) -> 0 | CX21: =SUM(J21,R21,X21,AD21,AJ21,AP21,AV21,BB21,BH21,BN21,BT21,BZ21,CF21,CL21,CR21) -> 0 | CY21: =SUM(K21,S21,Y21,AE21,AK21,AQ21,AW21,BC21,BI21,BO21,BU21,CA21,CG21,CM21,CS21) -> 32 | CZ21: =SUM(L21) -> 0 | DA21: 1 | DB21: 1 | DC21: 0
A22: 8052 | B22: Unipart Logistics | C22: L1 | D22: T | E22: 0.625 | F22: 0 | G22: 0 | H22: 8 | I22: 0 | J22: 0 | K22: 0 | L22: 2 | M22: 0.875 | N22: 0.25 | O22: 8 | P22: 0 | Q22: 0 | R22: 0 | S22: 8 | T22: OFF | U22: OFF | V22: OFF | W22: OFF | X22: OFF | Y22: OFF | Z22: OFF | AA22: OFF | AB22: OFF | AC22: OFF | AD22: OFF | AE22: OFF | AF22: 0.625 | AG22: 0 | AH22: 8 | AI22: 0 | AJ22: 0 | AK22: 2 | AL22: Vacation Leave | AM22: Vacation Leave | AN22: Vacation Leave | AO22: Vacation Leave | AP22: Vacation Leave | AQ22: Vacation Leave | AR22: 0.625 | AS22: 0 | AT22: 8 | AU22: 0 | AV22: 0 | AW22: 2 | AX22: 0.625 | AY22: 0 | AZ22: 8 | BA22: 0 | BB22: 120 | BC22: 2 | BD22: 0.625 | BE22: 0 | BF22: 8 | BG22: 0 | BH22: 0 | BI22: 2 | BJ22: OFF | BK22: OFF | BL22: OFF | BM22: OFF | BN22: OFF | BO22: OFF | BP22: OFF | BQ22: OFF | BR22: OFF | BS22: OFF | BT22: OFF | BU22: OFF | BV22: 0.625 | BW22: 0 | BX22: 8 | BY22: 0 | BZ22: 0 | CA22: 2 | CB22: 0.625 | CC22: 0 | CD22: 8 | CE22: 0 | CF22: 0 | CG22: 2 | CH22: 0.625 | CI22: 0.79166667 | CJ22: 4 | CK22: 0 | CL22: 0 | CM22: 0 | CN22: 0.625 | CO22: 0 | CP22: 8 | CQ22: 0 | CR22: 0 | CS22: 2 | CT22: =SUM(G22,O22,V22,AB22,AH22,AN22,AT22,AZ22,BF22,BL22,BR22,BX22,CD22,CJ22,CP22) -> 68 | CU22: =SUM(H22) -> 8 | CV22: =SUM(I22,P22,W22,AC22,AI22,AO22,AU22,BA22,BG22,BM22,BS22,BY22,CE22,CK22,CQ22) -> 0 | CW22: =SUM(Q22) -> 0 | CX22: =SUM(J22,R22,X22,AD22,AJ22,AP22,AV22,BB22,BH22,BN22,BT22,BZ22,CF22,CL22,CR22) -> 120 | CY22: =SUM(K22,S22,Y22,AE22,AK22,AQ22,AW22,BC22,BI22,BO22,BU22,CA22,CG22,CM22,CS22) -> 22 | CZ22: =SUM(L22) -> 2 | DA22: 0 | DB22: 1.5 | DC22: 0
A23: 8053 | B23: Unipart Logistics | C23: L1 | D23: U | E23: 0.625 | F23: 0 | G23: 0 | H23: 8 | I23: 0 | J23: 0 | K23: 0 | L23: 2 | M23: 0.625 | N23: 0 | O23: 8 | P23: 0 | Q23: 0 | R23: 0 | S23: 2 | T23: OFF | U23: OFF | V23: OFF | W23: OFF | X23: OFF | Y23: OFF | Z23: OFF | AA23: OFF | AB23: OFF | AC23: OFF | AD23: OFF | AE23: OFF | AF23: 0.625 | AG23: 0 | AH23: 8 | AI23: 0 | AJ23: 0 | AK23: 2 | AL23: 0.625 | AM23: 0 | AN23: 8 | AO23: 0 | AP23: 0 | AQ23: 2 | AR23: 0.625 | AS23: 0 | AT23: 8 | AU23: 0 | AV23: 0 | AW23: 2 | AX23: 0.625 | AY23: 0 | AZ23: 8 | BA23: 0 | BB23: 0 | BC23: 2 | BD23: 0.625 | BE23: 0 | BF23: 8 | BG23: 0 | BH23: 0 | BI23: 2 | BJ23: OFF | BK23: OFF | BL23: OFF | BM23: OFF | BN23: OFF | BO23: OFF | BP23: OFF | BQ23: OFF | BR23: OFF | BS23: OFF | BT23: OFF | BU23: OFF | BV23: 0.625 | BW23: 0 | BX23: 8 | BY23: 0 | BZ23: 0 | CA23: 2 | CB23: 0.625 | CC23: 0 | CD23: 8 | CE23: 0 | CF23: 0 | CG23: 2 | CH23: 0.625 | CI23: 0 | CJ23: 8 | CK23: 0 | CL23: 0 | CM23: 2 | CN23: 0.625 | CO23: 0 | CP23: 8 | CQ23: 0 | CR23: 0 | CS23: 2 | CT23: =SUM(G23,O23,V23,AB23,AH23,AN23,AT23,AZ23,BF23,BL23,BR23,BX23,CD23,CJ23,CP23) -> 80 | CU23: =SUM(H23) -> 8 | CV23: =SUM(I23,P23,W23,AC23,AI23,AO23,AU23,BA23,BG23,BM23,BS23,BY23,CE23,CK23,CQ23) -> 0 | CW23: =SUM(Q23) -> 0 | CX23: =SUM(J23,R23,X23,AD23,AJ23,AP23,AV23,BB23,BH23,BN23,BT23,BZ23,CF23,CL23,CR23) -> 0 | CY23: =SUM(K23,S23,Y23,AE23,AK23,AQ23,AW23,BC23,BI23,BO23,BU23,CA23,CG23,CM23,CS23) -> 20 | CZ23: =SUM(L23) -> 2 | DA23: 0 | DB23: 0 | DC23: 0
CT25: =SUM(CT3:CT23) -> 1531 | CU25: =SUM(CU3:CU23) -> 53 | CV25: =SUM(CV3:CV23) -> 57 | CW25: =SUM(CW3:CW23) -> 6 | CX25: =SUM(CX3:CX23) -> 120 | CY25: =SUM(CY3:CY23) -> 565 | CZ25: =SUM(CZ3:CZ23) -> 13 | DA25: =SUM(DA3:DA23) -> 11 | ... DC25: =SUM(DC3:DC23) -> 4

Sheet Raw Sheet
A1: ESPIRE INFOLABS INC.
A2: Payroll Period: | D2: 46023 | E2: 46037 | F2: =NETWORKDAYS(D2,E2) -> 11 | G2: No. of Hours | H2: =F2*8 -> 88 | J2: Password: | K2: Espire@1234
A4: 1 | B4: =A4+1 -> 2 | C4: =B4+1 -> 3 | D4: =C4+1 -> 4 | E4: =D4+1 -> 5 | F4: =E4+1 -> 6 | G4: =F4+1 -> 7 | H4: =G4+1 -> 8 | I4: =H4+1 -> 9 | ... BK4: =BJ4+1 -> 63
K5: DE MINIMIS BENEFIT | Q5: Other Non-Taxable Compensation (Vacation Leave) | R5: Salary Adjustment | S5: Salary Adjusment | T5: First Half Gross Compensation | U5: First Half Basic Salary, net of tardiness | AG5: WORKDAYS OVERTIME | AK5: SATURDAY OVERTIME | AQ5: SUNDAY OVERTIME | AW5: SPECIAL HOLIDAY OVERTIME | BC5: REGULAR HOLIDAY OVERTIME
A6: No. | C6: Name of Employees | D6: Civil Status | E6: Start of Employment | F6: Position | G6: Gross Salary | K6: YEAR END GIFTS | L6: Rice Subsidy | M6: Uniform/Clothing Allowance | N6: Laundry Allowance | O6: Meal Allowance | P6: Medical Allowance | V6: SSS Loan | X6: HDMF Loan | Y6: Advances to Employees | Z6: 2025 Tax Due | AA6: UNDERTIME | AC6: ABSENT | AE6: TRAVEL TIME | AG6: OVERTIME | AI6: Night differential 10pm-6am | AK6: OVERTIME | AO6: Night differential 10pm-6am | AQ6: OVERTIME | AU6: Night differential 10pm-6am | AW6: OVERTIME | BA6: Night differential 10pm-6am | BC6: OVERTIME | BG6: Night differential 10pm-6am | BI6: Total Overtime | BJ6: Total Tardiness/Absent | BK6: Reg. Hours
G7: Monthly | H7: Semi Monthly | I7: Daily | J7: Hourly | V7: Salary | W7: Calamity | Y7: Salary Loan | AA7: Hours | AB7: PHP Equiv. | AC7: Day(s) | AD7: PHP Equiv. | AE7: Hours | AF7: PHP Equiv. | AG7: Hours | AH7: PHP Equiv. | AI7: Hours | AJ7: PHP Equiv. | AK7: 1st 8 Hours | AL7: PHP Equiv. | AM7: Excess 8 Hours | AN7: PHP Equiv. | AO7: Hours | AP7: Peso Equivalent | AQ7: Hours | AR7: PHP Equiv. | AS7: Excess 8 Hours | AT7: PHP Equiv. | AU7: Hours | AV7: Peso Equivalent | AW7: 1st 8 Hours | AX7: PHP Equiv. | AY7: Excess 8 Hours | AZ7: PHP Equiv. | BA7: Hours | BB7: Peso Equivalent | BC7: 1st 8 Hours | BD7: Peso Equivalent | BE7: Excess 8 Hours | BF7: Peso Equivalent | BG7: Hours | BH7: Peso Equivalent | BI7: Peso Equivalent | BJ7: Peso Equivalent | BN7: Password | BO7: Email Address
A8: 1 | B8: 3 | C8: A | D8: Married | E8: 44886 | F8: Service Desk Analyst-L1 | G8: 37200 | H8: =G8/2 -> 18600 | I8: =G8*12/261 -> 1710.3448 | J8: =I8/8 -> 213.7931 | L8: 2000 | M8: 500 | N8: 300 | V8: 1845.8 | AA8: =VLOOKUP(C8,Timesheet!D:DD,99,0)/60 -> 0 | AB8: =AA8*J8 -> 0 | AC8: =VLOOKUP(C8,Timesheet!D:DD,104,0) -> 0 | AD8: =I8*AC8 -> 0 | AF8: =J8*AE8 -> 0 | AG8: =VLOOKUP(C8,Timesheet!D:DD,97,0) -> 0 | AH8: =(J8*AG8*125%) -> 0 | AI8: =VLOOKUP(C8,Timesheet!D:DD,100,0) -> 12 | AJ8: =J8*0.1*AI8 -> 256.55172 | AK8: =VLOOKUP(C8,Timesheet!D:DD,98,0) -> 0 | AL8: =J8*1.3*AK8 -> 0 | AN8: =(J8*1.3*1.3)*AM8 -> 0 | AP8: =(J8*130%*10%)*AO8 -> 0 | AR8: =J8*1.3*AQ8 -> 0 | AT8: =(J8*1.3*1.3)*AS8 -> 0 | AV8: =(J8*0.3*0.1)*AU8 -> 0 | AW8: 0 | AX8: =(J8*0.3)*AW8 -> 0 | AY8: 0 | AZ8: =((J8*1.3)*1.3)*AY8 -> 0 | BA8: 0 | BB8: =((J8*0.3)*0.1)*BA8 -> 0 | BC8: =VLOOKUP(C8,Timesheet!D:DD,96,0) -> 0 | BD8: =J8*1*BC8 -> 0 | BF8: =(J8*2*1.3)*BE8 -> 0 | BG8: =VLOOKUP(C8,Timesheet!D:DD,101,0) -> 0 | BH8: =(J8*10%*2)*BG8 -> 0 | BI8: =AH8+AJ8+AL8+AN8+AP8+AR8+AT8+AV8+AX8+AZ8+BB8+BD8+BF8+BH8 -> 256.55172 | BJ8: =-(AB8+AD8) -> 0 | BK8: =Timesheet!CT3 -> 72 | BL8: =BI8-SUM(AH8,AJ8,AL8,AN8,AP8,AR8,AV8,AX8,AZ8,BB8,BD8,BF8,BH8) -> 0 | BN8: 249411050 | BO8: yolanda.haguimit@espire.com
A9: 8 | B9: 17 | C9: B | D9: Single | E9: 44910 | F9: Service Desk Analyst-L1 | G9: 45000 | H9: =G9/2 -> 22500 | I9: =G9*12/261 -> 2068.9655 | J9: =I9/8 -> 258.62069 | V9: 922.9 | AA9: =VLOOKUP(C9,Timesheet!D:DD,99,0)/60 -> 0 | AB9: =AA9*J9 -> 0 | AC9: =VLOOKUP(C9,Timesheet!D:DD,104,0) -> 0 | AD9: =I9*AC9 -> 0 | AF9: =J9*AE9 -> 0 | AG9: =VLOOKUP(C9,Timesheet!D:DD,97,0) -> 9 | AH9: =(J9*AG9*125%) -> 2909.4828 | AI9: =VLOOKUP(C9,Timesheet!D:DD,100,0) -> 30 | AJ9: =J9*0.1*AI9 -> 775.86207 | AK9: =VLOOKUP(C9,Timesheet!D:DD,98,0) -> 0 | AL9: =J9*1.3*AK9 -> 0 | AN9: =(J9*1.3*1.3)*AM9 -> 0 | AP9: =(J9*130%*10%)*AO9 -> 0 | AR9: =J9*1.3*AQ9 -> 0 | AT9: =(J9*1.3*1.3)*AS9 -> 0 | AV9: =(J9*0.3*0.1)*AU9 -> 0 | AW9: 0 | AX9: =(J9*0.3)*AW9 -> 0 | AY9: 0 | AZ9: =((J9*1.3)*1.3)*AY9 -> 0 | BA9: 0 | BB9: =((J9*0.3)*0.1)*BA9 -> 0 | BC9: =VLOOKUP(C9,Timesheet!D:DD,96,0) -> 8 | BD9: =J9*1*BC9 -> 2068.9655 | BF9: =(J9*2*1.3)*BE9 -> 0 | BG9: =VLOOKUP(C9,Timesheet!D:DD,101,0) -> 2 | BH9: =(J9*10%*2)*BG9 -> 103.44828 | BI9: =AH9+AJ9+AL9+AN9+AP9+AR9+AT9+AV9+AX9+AZ9+BB9+BD9+BF9+BH9 -> 5857.7586 | BJ9: =-(AB9+AD9) -> 0 | BK9: =Timesheet!CT4 -> 80 | BL9: =BI9-SUM(AH9,AJ9,AL9,AN9,AP9,AR9,AV9,AX9,AZ9,BB9,BD9,BF9,BH9) -> 0 | BN9: 348877466 | BO9: kyle.viray@espire.com
A10: 10 | B10: 21 | C10: C | D10: Single | E10: 44910 | F10: Service Desk Analyst-L1 | G10: 42000 | H10: =G10/2 -> 21000 | I10: =G10*12/261 -> 1931.0345 | J10: =I10/8 -> 241.37931 | L10: 2000 | M10: 100 | V10: 922.9 | AA10: =VLOOKUP(C10,Timesheet!D:DD,99,0)/60 -> 0 | AB10: =AA10*J10 -> 0 | AC10: =VLOOKUP(C10,Timesheet!D:DD,104,0) -> 0 | AD10: =I10*AC10 -> 0 | AF10: =J10*AE10 -> 0 | AG10: =VLOOKUP(C10,Timesheet!D:DD,97,0) -> 12 | AH10: =(J10*AG10*125%) -> 3620.6897 | AI10: =VLOOKUP(C10,Timesheet!D:DD,100,0) -> 0 | AJ10: =J10*0.1*AI10 -> 0 | AK10: =VLOOKUP(C10,Timesheet!D:DD,98,0) -> 0 | AL10: =J10*1.3*AK10 -> 0 | AN10: =(J10*1.3*1.3)*AM10 -> 0 | AP10: =(J10*130%*10%)*AO10 -> 0 | AR10: =J10*1.3*AQ10 -> 0 | AT10: =(J10*1.3*1.3)*AS10 -> 0 | AV10: =(J10*0.3*0.1)*AU10 -> 0 | AW10: 0 | AX10: =(J10*0.3)*AW10 -> 0 | AY10: 0 | AZ10: =((J10*1.3)*1.3)*AY10 -> 0 | BA10: 0 | BB10: =((J10*0.3)*0.1)*BA10 -> 0 | BC10: =VLOOKUP(C10,Timesheet!D:DD,96,0) -> 0 | BD10: =J10*1*BC10 -> 0 | BF10: =(J10*2*1.3)*BE10 -> 0 | BG10: =VLOOKUP(C10,Timesheet!D:DD,101,0) -> 0 | BH10: =(J10*10%*2)*BG10 -> 0 | BI10: =AH10+AJ10+AL10+AN10+AP10+AR10+AT10+AV10+AX10+AZ10+BB10+BD10+BF10+BH10 -> 3620.6897 | BJ10: =-(AB10+AD10) -> 0 | BK10: =Timesheet!CT5 -> 80 | BL10: =BI10-SUM(AH10,AJ10,AL10,AN10,AP10,AR10,AV10,AX10,AZ10,BB10,BD10,BF10,BH10) -> 0 | BN10: 379535400 | BO10: christian.piolino@espire.com
A11: 11 | B11: 23 | C11: D | D11: Married | E11: 44922 | F11: Senior Operations Manager | G11: 169600 | H11: =G11/2 -> 84800 | I11: =G11*12/261 -> 7797.7011 | J11: =I11/8 -> 974.71264 | L11: 2000 | M11: 500 | N11: 300 | AA11: =VLOOKUP(C11,Timesheet!D:DD,99,0)/60 -> 0 | AB11: =AA11*J11 -> 0 | AC11: =VLOOKUP(C11,Timesheet!D:DD,104,0) -> 0 | AD11: =I11*AC11 -> 0 | AF11: =J11*AE11 -> 0 | AG11: =VLOOKUP(C11,Timesheet!D:DD,97,0) -> 0 | AH11: =(J11*AG11*125%) -> 0 | AI11: =VLOOKUP(C11,Timesheet!D:DD,100,0) -> 0 | AJ11: =J11*0.1*AI11 -> 0 | AK11: =VLOOKUP(C11,Timesheet!D:DD,98,0) -> 0 | AL11: =J11*1.3*AK11 -> 0 | AN11: =(J11*1.3*1.3)*AM11 -> 0 | AP11: =(J11*130%*10%)*AO11 -> 0 | AR11: =J11*1.3*AQ11 -> 0 | AT11: =(J11*1.3*1.3)*AS11 -> 0 | AV11: =(J11*0.3*0.1)*AU11 -> 0 | AW11: 0 | AX11: =(J11*0.3)*AW11 -> 0 | AY11: 0 | AZ11: =((J11*1.3)*1.3)*AY11 -> 0 | BA11: 0 | BB11: =((J11*0.3)*0.1)*BA11 -> 0 | BC11: =VLOOKUP(C11,Timesheet!D:DD,96,0) -> 0 | BD11: =J11*1.6*BC11 -> 0 | BF11: =(J11*2*1.3)*BE11 -> 0 | BG11: =VLOOKUP(C11,Timesheet!D:DD,101,0) -> 0 | BH11: =(J11*10%*2)*BG11 -> 0 | BI11: =AH11+AJ11+AL11+AN11+AP11+AR11+AT11+AV11+AX11+AZ11+BB11+BD11+BF11+BH11 -> 0 | BJ11: =-(AB11+AD11) -> 0 | BK11: =Timesheet!CT6 -> 80 | BL11: =BI11-SUM(AH11,AJ11,AL11,AN11,AP11,AR11,AV11,AX11,AZ11,BB11,BD11,BF11,BH11) -> 0 | BN11: 228243729 | BO11: mark.marquez@espire.com
A12: 12 | B12: 25 | C12: E | D12: Married | E12: 44929 | F12: Senior Project Manager | G12: 255600 | H12: =G12/2 -> 127800 | I12: =G12*12/261 -> 11751.724 | J12: =I12/8 -> 1468.9655 | L12: 2000 | M12: 500 | N12: 300 | Y12: 41395.83 | AA12: =VLOOKUP(C12,Timesheet!D:DD,99,0)/60 -> 0 | AB12: =AA12*J12 -> 0 | AC12: =VLOOKUP(C12,Timesheet!D:DD,104,0) -> 0 | AD12: =I12*AC12 -> 0 | AF12: =J12*AE12 -> 0 | AG12: =VLOOKUP(C12,Timesheet!D:DD,97,0) -> 0 | AH12: =(J12*AG12*125%) -> 0 | AI12: =VLOOKUP(C12,Timesheet!D:DD,100,0) -> 0 | AJ12: =J12*0.1*AI12 -> 0 | AK12: =VLOOKUP(C12,Timesheet!D:DD,98,0) -> 0 | AL12: =J12*1.3*AK12 -> 0 | AN12: =(J12*1.3*1.3)*AM12 -> 0 | AP12: =(J12*130%*10%)*AO12 -> 0 | AR12: =J12*1.3*AQ12 -> 0 | AT12: =(J12*1.3*1.3)*AS12 -> 0 | AV12: =(J12*0.3*0.1)*AU12 -> 0 | AW12: 0 | AX12: =(J12*0.3)*AW12 -> 0 | AY12: 0 | AZ12: =((J12*1.3)*1.3)*AY12 -> 0 | BA12: 0 | BB12: =((J12*0.3)*0.1)*BA12 -> 0 | BC12: =VLOOKUP(C12,Timesheet!D:DD,96,0) -> 0 | BD12: =J12*1.6*BC12 -> 0 | BF12: =(J12*2*1.3)*BE12 -> 0 | BG12: =VLOOKUP(C12,Timesheet!D:DD,101,0) -> 0 | BH12: =(J12*10%*2)*BG12 -> 0 | BI12: =AH12+AJ12+AL12+AN12+AP12+AR12+AT12+AV12+AX12+AZ12+BB12+BD12+BF12+BH12 -> 0 | BJ12: =-(AB12+AD12) -> 0 | BK12: =Timesheet!CT7 -> 72 | BL12: =BI12-SUM(AH12,AJ12,AL12,AN12,AP12,AR12,AV12,AX12,AZ12,BB12,BD12,BF12,BH12) -> 0 | BN12: 913668774 | BO12: ryan.carreon@espire.com
A13: 15 | B13: 31 | C13: F | D13: Single | E13: 44991 | F13: Service Desk Analyst-L1 | G13: 26000 | H13: =G13/2 -> 13000 | I13: =G13*12/261 -> 1195.4023 | J13: =I13/8 -> 149.42529 | L13: 1560 | AA13: =VLOOKUP(C13,Timesheet!D:DD,99,0)/60 -> 0 | AB13: =AA13*J13 -> 0 | AC13: =VLOOKUP(C13,Timesheet!D:DD,104,0) -> 0 | AD13: =I13*AC13 -> 0 | AF13: =J13*AE13 -> 0 | AG13: =VLOOKUP(C13,Timesheet!D:DD,97,0) -> 0 | AH13: =(J13*AG13*125%) -> 0 | AI13: =VLOOKUP(C13,Timesheet!D:DD,100,0) -> 0 | AJ13: =J13*0.1*AI13 -> 0 | AK13: =VLOOKUP(C13,Timesheet!D:DD,98,0) -> 0 | AL13: =J13*1.3*AK13 -> 0 | AN13: =(J13*1.3*1.3)*AM13 -> 0 | AP13: =(J13*130%*10%)*AO13 -> 0 | AR13: =J13*1.3*AQ13 -> 0 | AT13: =(J13*1.3*1.3)*AS13 -> 0 | AV13: =(J13*0.3*0.1)*AU13 -> 0 | AW13: 0 | AX13: =(J13*0.3)*AW13 -> 0 | AY13: 0 | AZ13: =((J13*1.3)*1.3)*AY13 -> 0 | BA13: 0 | BB13: =((J13*0.3)*0.1)*BA13 -> 0 | BC13: =VLOOKUP(C13,Timesheet!D:DD,96,0) -> 8 | BD13: =J13*1.6*BC13 -> 1912.6437 | BF13: =(J13*2*1.3)*BE13 -> 0 | BG13: =VLOOKUP(C13,Timesheet!D:DD,101,0) -> 0 | BH13: =(J13*10%*2)*BG13 -> 0 | BI13: =AH13+AJ13+AL13+AN13+AP13+AR13+AT13+AV13+AX13+AZ13+BB13+BD13+BF13+BH13 -> 1912.6437 | BJ13: =-(AB13+AD13) -> 0 | BK13: =Timesheet!CT8 -> 80 | BL13: =BI13-SUM(AH13,AJ13,AL13,AN13,AP13,AR13,AV13,AX13,AZ13,BB13,BD13,BF13,BH13) -> 0 | BN13: 622972173 | BO13: james.colongan@espire.com
A14: 19 | B14: 39 | C14: G | D14: Single | E14: 45051 | F14: Service Desk Analyst-L1 | G14: 29680 | H14: =G14/2 -> 14840 | I14: =G14*12/261 -> 1364.5977 | J14: =I14/8 -> 170.57471 | L14: 2000 | M14: 500 | N14: 300 | AA14: =VLOOKUP(C14,Timesheet!D:DD,99,0)/60 -> 0 | AB14: =AA14*J14 -> 0 | AC14: =VLOOKUP(C14,Timesheet!D:DD,104,0) -> 0 | AD14: =I14*AC14 -> 0 | AF14: =J14*AE14 -> 0 | AG14: =VLOOKUP(C14,Timesheet!D:DD,97,0) -> 0 | AH14: =(J14*AG14*125%) -> 0 | AI14: =VLOOKUP(C14,Timesheet!D:DD,100,0) -> 9 | AJ14: =J14*0.1*AI14 -> 153.51724 | AK14: =VLOOKUP(C14,Timesheet!D:DD,98,0) -> 0 | AL14: =J14*1.3*AK14 -> 0 | AN14: =(J14*1.3*1.3)*AM14 -> 0 | AP14: =(J14*130%*10%)*AO14 -> 0 | AR14: =J14*1.3*AQ14 -> 0 | AT14: =(J14*1.3*1.3)*AS14 -> 0 | AV14: =(J14*0.3*0.1)*AU14 -> 0 | AW14: 0 | AX14: =(J14*0.3)*AW14 -> 0 | AY14: 0 | AZ14: =((J14*1.3)*1.3)*AY14 -> 0 | BA14: 0 | BB14: =((J14*0.3)*0.1)*BA14 -> 0 | BC14: =VLOOKUP(C14,Timesheet!D:DD,96,0) -> 8 | BD14: =J14*1.6*BC14 -> 2183.3563 | BF14: =(J14*2*1.3)*BE14 -> 0 | BG14: =VLOOKUP(C14,Timesheet!D:DD,101,0) -> 1 | BH14: =(J14*10%*2)*BG14 -> 34.114943 | BI14: =AH14+AJ14+AL14+AN14+AP14+AR14+AT14+AV14+AX14+AZ14+BB14+BD14+BF14+BH14 -> 2370.9885 | BJ14: =-(AB14+AD14) -> 0 | BK14: =Timesheet!CT9 -> 76 | BL14: =BI14-SUM(AH14,AJ14,AL14,AN14,AP14,AR14,AV14,AX14,AZ14,BB14,BD14,BF14,BH14) -> 0 | BN14: 353612804 | BO14: kricia.labradores@espire.com
A15: 36 | B15: 73 | C15: H | D15: Married | E15: 45293 | F15: Senior Security Analyst | G15: 90100 | H15: =G15/2 -> 45050 | I15: =G15*12/261 -> 4142.5287 | J15: =I15/8 -> 517.81609 | L15: 2000 | M15: 500 | N15: 300 | AA15: =VLOOKUP(C15,Timesheet!D:DD,99,0)/60 -> 0 | AB15: =AA15*J15 -> 0 | AC15: =VLOOKUP(C15,Timesheet!D:DD,104,0) -> 0 | AD15: =I15*AC15 -> 0 | AF15: =J15*AE15 -> 0 | AG15: =VLOOKUP(C15,Timesheet!D:DD,97,0) -> 0 | AH15: =(J15*AG15*125%) -> 0 | AI15: =VLOOKUP(C15,Timesheet!D:DD,100,0) -> 0 | AJ15: =J15*0.1*AI15 -> 0 | AK15: =VLOOKUP(C15,Timesheet!D:DD,98,0) -> 0 | AL15: =J15*1.3*AK15 -> 0 | AN15: =(J15*1.3*1.3)*AM15 -> 0 | AP15: =(J15*130%*10%)*AO15 -> 0 | AR15: =J15*1.3*AQ15 -> 0 | AT15: =(J15*1.3*1.3)*AS15 -> 0 | AV15: =(J15*0.3*0.1)*AU15 -> 0 | AW15: 0 | AX15: =(J15*0.3)*AW15 -> 0 | AY15: 0 | AZ15: =((J15*1.3)*1.3)*AY15 -> 0 | BA15: 0 | BB15: =((J15*0.3)*0.1)*BA15 -> 0 | BC15: =VLOOKUP(C15,Timesheet!D:DD,96,0) -> 0 | BD15: =J15*1.6*BC15 -> 0 | BF15: =(J15*2*1.3)*BE15 -> 0 | BG15: =VLOOKUP(C15,Timesheet!D:DD,101,0) -> 0 | BH15: =(J15*10%*2)*BG15 -> 0 | BI15: =AH15+AJ15+AL15+AN15+AP15+AR15+AT15+AV15+AX15+AZ15+BB15+BD15+BF15+BH15 -> 0 | BJ15: =-(AB15+AD15) -> 0 | BK15: =Timesheet!CT10 -> 80 | BL15: =BI15-SUM(AH15,AJ15,AL15,AN15,AP15,AR15,AV15,AX15,AZ15,BB15,BD15,BF15,BH15) -> 0 | BN15: 310744008 | BO15: shiervonn.penaranda@espire.com
A16: 37 | B16: 75 | C16: I | D16: Married | E16: 45306 | F16: Lead Security Analyst | G16: 133125 | H16: =G16/2 -> 66562.5 | I16: =G16*12/261 -> 6120.6897 | J16: =I16/8 -> 765.08621 | L16: 2000 | M16: 500 | N16: 300 | AA16: =VLOOKUP(C16,Timesheet!D:DD,99,0)/60 -> 0 | AB16: =AA16*J16 -> 0 | AC16: =VLOOKUP(C16,Timesheet!D:DD,104,0) -> 0 | AD16: =I16*AC16 -> 0 | AF16: =J16*AE16 -> 0 | AG16: =VLOOKUP(C16,Timesheet!D:DD,97,0) -> 0 | AH16: =(J16*AG16*125%) -> 0 | AI16: =VLOOKUP(C16,Timesheet!D:DD,100,0) -> 40 | AJ16: =J16*0.1*AI16 -> 3060.3448 | AK16: =VLOOKUP(C16,Timesheet!D:DD,98,0) -> 0 | AL16: =J16*1.3*AK16 -> 0 | AN16: =(J16*1.3*1.3)*AM16 -> 0 | AP16: =(J16*130%*10%)*AO16 -> 0 | AR16: =J16*1.3*AQ16 -> 0 | AV16: =(J16*0.3*0.1)*AU16 -> 0 | AW16: 0 | AX16: =(J16*0.3)*AW16 -> 0 | AY16: 0 | AZ16: =((J16*1.3)*1.3)*AY16 -> 0 | BA16: 0 | BB16: =((J16*0.3)*0.1)*BA16 -> 0 | BC16: =VLOOKUP(C16,Timesheet!D:DD,96,0) -> 0 | BD16: =J16*1.6*BC16 -> 0 | BF16: =(J16*2*1.3)*BE16 -> 0 | BG16: =VLOOKUP(C16,Timesheet!D:DD,101,0) -> 0 | BH16: =(J16*10%*2)*BG16 -> 0 | BI16: =AH16+AJ16+AL16+AN16+AP16+AR16+AT16+AV16+AX16+AZ16+BB16+BD16+BF16+BH16 -> 3060.3448 | BJ16: =-(AB16+AD16) -> 0 | BK16: =Timesheet!CT11 -> 80 | BL16: =BI16-SUM(AH16,AJ16,AL16,AN16,AP16,AR16,AV16,AX16,AZ16,BB16,BD16,BF16,BH16) -> 0 | BN16: 255082259 | BO16: jonathan.cabante@espire.com
A17: 39 | B17: 79 | C17: J | D17: Single | E17: 45323 | F17: Service Desk Analyst L-1 | G17: 26250 | H17: =G17/2 -> 13125 | I17: =G17*12/261 -> 1206.8966 | J17: =I17/8 -> 150.86207 | L17: 2000 | M17: 500 | N17: 300 | AA17: =VLOOKUP(C17,Timesheet!D:DD,99,0)/60 -> 0 | AB17: =AA17*J17 -> 0 | AC17: =VLOOKUP(C17,Timesheet!D:DD,104,0) -> 0 | AD17: =I17*AC17 -> 0 | AF17: =J17*AE17 -> 0 | AG17: =VLOOKUP(C17,Timesheet!D:DD,97,0) -> 12 | AH17: =(J17*AG17*125%) -> 2262.931 | AI17: =VLOOKUP(C17,Timesheet!D:DD,100,0) -> 86 | AJ17: =J17*0.1*AI17 -> 1297.4138 | AK17: =VLOOKUP(C17,Timesheet!D:DD,98,0) -> 6 | AL17: =J17*1.3*AK17 -> 1176.7241 | AN17: =(J17*1.3*1.3)*AM17 -> 0 | AP17: =(J17*130%*10%)*AO17 -> 0 | AR17: =J17*1.3*AQ17 -> 0 | AV17: =(J17*0.3*0.1)*AU17 -> 0 | AW17: 0 | AX17: =(J17*0.3)*AW17 -> 0 | AY17: 0 | AZ17: =((J17*1.3)*1.3)*AY17 -> 0 | BA17: 0 | BB17: =((J17*0.3)*0.1)*BA17 -> 0 | BC17: =VLOOKUP(C17,Timesheet!D:DD,96,0) -> 0 | BD17: =J17*1*BC17 -> 0 | BF17: =(J17*2*1.3)*BE17 -> 0 | BG17: =VLOOKUP(C17,Timesheet!D:DD,101,0) -> 0 | BH17: =(J17*10%*2)*BG17 -> 0 | BI17: =AH17+AJ17+AL17+AN17+AP17+AR17+AT17+AV17+AX17+AZ17+BB17+BD17+BF17+BH17 -> 4737.069 | BJ17: =-(AB17+AD17) -> 0 | BK17: =Timesheet!CT12 -> 80 | BL17: =BI17-SUM(AH17,AJ17,AL17,AN17,AP17,AR17,AV17,AX17,AZ17,BB17,BD17,BF17,BH17) -> 0 | BN17: 435469247 | BO17: jodie.zamora@espire.com
A18: 41 | B18: 83 | C18: K | D18: Single | E18: 45453 | F18: Service Desk Analyst L-1 | G18: 28646 | H18: =G18/2 -> 14323 | I18: =G18*12/261 -> 1317.0575 | J18: =I18/8 -> 164.63218 | L18: 2000 | M18: 500 | N18: 300 | AA18: =VLOOKUP(C18,Timesheet!D:DD,99,0)/60 -> 0 | AB18: =AA18*J18 -> 0 | AC18: =VLOOKUP(C18,Timesheet!D:DD,104,0) -> 0 | AD18: =I18*AC18 -> 0 | AF18: =J18*AE18 -> 0 | AG18: =VLOOKUP(C18,Timesheet!D:DD,97,0) -> 0 | AH18: =(J18*AG18*125%)+((J18*AG18*10%)*25%) -> 0 | AI18: =VLOOKUP(C18,Timesheet!D:DD,100,0) -> 78 | AJ18: =J18*0.1*AI18 -> 1284.131 | AK18: =VLOOKUP(C18,Timesheet!D:DD,98,0) -> 0 | AL18: =J18*1.3*AK18 -> 0 | AN18: =(J18*1.3*1.3)*AM18 -> 0 | AP18: =(J18*130%*10%)*AO18 -> 0 | AR18: =J18*1.3*AQ18 -> 0 | AV18: =(J18*0.3*0.1)*AU18 -> 0 | AW18: 0 | AX18: =(J18*0.3)*AW18 -> 0 | AY18: 0 | AZ18: =((J18*1.3)*1.3)*AY18 -> 0 | BA18: 0 | BB18: =((J18*0.3)*0.1)*BA18 -> 0 | BC18: =VLOOKUP(C18,Timesheet!D:DD,96,0) -> 2 | BD18: =J18*1*BC18 -> 329.26437 | BF18: =(J18*2*1.3)*BE18 -> 0 | BG18: =VLOOKUP(C18,Timesheet!D:DD,101,0) -> 2 | BH18: =(J18*1*0.1)*BG18 -> 32.926437 | BI18: =AH18+AJ18+AL18+AN18+AP18+AR18+AT18+AV18+AX18+AZ18+BB18+BD18+BF18+BH18 -> 1646.3218 | BJ18: =-(AB18+AD18) -> 0 | BK18: =Timesheet!CT13 -> 78 | BL18: =BI18-SUM(AH18,AJ18,AL18,AN18,AP18,AR18,AV18,AX18,AZ18,BB18,BD18,BF18,BH18) -> 0 | BN18: 325896554 | BO18: mairalyn.belarma@espire.com
A19: 42 | B19: 85 | C19: L | D19: Single | E19: 45461 | F19: Lead Security Analyst | G19: 187500 | H19: =G19/2 -> 93750 | I19: =G19*12/261 -> 8620.6897 | J19: =I19/8 -> 1077.5862 | L19: 2000 | M19: 500 | N19: 300 | AA19: =VLOOKUP(C19,Timesheet!D:DD,99,0)/60 -> 0 | AB19: =AA19*J19 -> 0 | AC19: =VLOOKUP(C19,Timesheet!D:DD,104,0) -> 0 | AD19: =I19*AC19 -> 0 | AF19: =J19*AE19 -> 0 | AG19: =VLOOKUP(C19,Timesheet!D:DD,97,0) -> 0 | AH19: =(J19*AG19*125%)+((J19*AG19*10%)*25%) -> 0 | AI19: =VLOOKUP(C19,Timesheet!D:DD,100,0) -> 20 | AJ19: =J19*0.1*AI19 -> 2155.1724 | AK19: =VLOOKUP(C19,Timesheet!D:DD,98,0) -> 0 | AL19: =J19*1.3*AK19 -> 0 | AN19: =(J19*1.3*1.3)*AM19 -> 0 | AP19: =(J19*130%*10%)*AO19 -> 0 | AR19: =J19*1.3*AQ19 -> 0 | AV19: =(J19*0.3*0.1)*AU19 -> 0 | AW19: 0 | AX19: =(J19*0.3)*AW19 -> 0 | AY19: 0 | AZ19: =((J19*1.3)*1.3)*AY19 -> 0 | BA19: 0 | BB19: =((J19*0.3)*0.1)*BA19 -> 0 | BC19: =VLOOKUP(C19,Timesheet!D:DD,96,0) -> 0 | BD19: =J19*1*BC19 -> 0 | BF19: =(J19*2*1.3)*BE19 -> 0 | BG19: =VLOOKUP(C19,Timesheet!D:DD,101,0) -> 0 | BH19: =(J19*1*0.1)*BG19 -> 0 | BI19: =AH19+AJ19+AL19+AN19+AP19+AR19+AT19+AV19+AX19+AZ19+BB19+BD19+BF19+BH19 -> 2155.1724 | BJ19: =-(AB19+AD19) -> 0 | BK19: =Timesheet!CT14 -> 80 | BL19: =BI19-SUM(AH19,AJ19,AL19,AN19,AP19,AR19,AV19,AX19,AZ19,BB19,BD19,BF19,BH19) -> 0 | BN19: 419094830 | BO19: pauljohan.virtudes@espire.com
A20: 43 | B20: 87 | C20: M | D20: Single | E20: 45488 | F20: Senior Security Analyst | G20: 102816 | H20: =G20/2 -> 51408 | I20: =G20*12/261 -> 4727.1724 | J20: =I20/8 -> 590.89655 | L20: 2000 | M20: 500 | N20: 300 | AA20: =VLOOKUP(C20,Timesheet!D:DD,99,0)/60 -> 0 | AB20: =AA20*J20 -> 0 | AC20: =VLOOKUP(C20,Timesheet!D:DD,104,0) -> 3 | AD20: =I20*AC20 -> 14181.517 | AF20: =J20*AE20 -> 0 | AG20: =VLOOKUP(C20,Timesheet!D:DD,97,0) -> 0 | AH20: =(J20*AG20*125%)+((J20*AG20*10%)*25%) -> 0 | AI20: =VLOOKUP(C20,Timesheet!D:DD,100,0) -> 0 | AJ20: =J20*0.1*AI20 -> 0 | AK20: =VLOOKUP(C20,Timesheet!D:DD,98,0) -> 0 | AL20: =J20*1.3*AK20 -> 0 | AN20: =(J20*1.3*1.3)*AM20 -> 0 | AP20: =(J20*130%*10%)*AO20 -> 0 | AR20: =J20*1.3*AQ20 -> 0 | AV20: =(J20*0.3*0.1)*AU20 -> 0 | AW20: 0 | AX20: =(J20*0.3)*AW20 -> 0 | AY20: 0 | AZ20: =((J20*1.3)*1.3)*AY20 -> 0 | BA20: 0 | BB20: =((J20*0.3)*0.1)*BA20 -> 0 | BC20: =VLOOKUP(C20,Timesheet!D:DD,96,0) -> 0 | BD20: =J20*1*BC20 -> 0 | BF20: =(J20*2*1.3)*BE20 -> 0 | BG20: =VLOOKUP(C20,Timesheet!D:DD,101,0) -> 0 | BH20: =(J20*1*0.1)*BG20 -> 0 | BI20: =AH20+AJ20+AL20+AN20+AP20+AR20+AT20+AV20+AX20+AZ20+BB20+BD20+BF20+BH20 -> 0 | BJ20: =-(AB20+AD20) -> -14181.517 | BK20: =Timesheet!CT15 -> 0 | BL20: =BI20-SUM(AH20,AJ20,AL20,AN20,AP20,AR20,AV20,AX20,AZ20,BB20,BD20,BF20,BH20) -> 0 | BN20: 428347497 | BO20: adelfos.bautista@espire.com
A21: 44 | B21: 89 | C21: N | D21: Single | E21: 45539 | F21: Service Desk Analyst-L1 | G21: 24700 | H21: =G21/2 -> 12350 | I21: =G21*12/261 -> 1135.6322 | J21: =I21/8 -> 141.95402 | L21: 2000 | M21: 500 | N21: 300 | V21: 697.88 | X21: 697.88 | AA21: =VLOOKUP(C21,Timesheet!D:DD,99,0)/60 -> 0 | AB21: =AA21*J21 -> 0 | AC21: =VLOOKUP(C21,Timesheet!D:DD,104,0) -> 0 | AD21: =I21*AC21 -> 0 | AG21: =VLOOKUP(C21,Timesheet!D:DD,97,0) -> 0 | AH21: =(J21*AG21*125%)+((J21*AG21*10%)*25%) -> 0 | AI21: =VLOOKUP(C21,Timesheet!D:DD,100,0) -> 62 | AJ21: =J21*0.1*AI21 -> 880.11494 | AK21: =VLOOKUP(C21,Timesheet!D:DD,98,0) -> 0 | AL21: =J21*1.3*AK21 -> 0 | AN21: =(J21*1.3*1.3)*AM21 -> 0 | AP21: =(J21*130%*10%)*AO21 -> 0 | AR21: =J21*1.3*AQ21 -> 0 | AV21: =(J21*0.3*0.1)*AU21 -> 0 | AW21: 0 | AX21: =(J21*0.3)*AW21 -> 0 | AY21: 0 | AZ21: =((J21*1.3)*1.3)*AY21 -> 0 | BA21: 0 | BB21: =((J21*0.3)*0.1)*BA21 -> 0 | BC21: =VLOOKUP(C21,Timesheet!D:DD,96,0) -> 3 | BD21: =J21*1*BC21 -> 425.86207 | BG21: =VLOOKUP(C21,Timesheet!D:DD,101,0) -> 2 | BH21: =(J21*1*0.1)*BG21 -> 28.390805 | BI21: =AH21+AJ21+AL21+AN21+AP21+AR21+AT21+AV21+AX21+AZ21+BB21+BD21+BF21+BH21 -> 1334.3678 | BJ21: =-(AB21+AD21) -> 0 | BK21: =Timesheet!CT16 -> 85 | BL21: =BI21-SUM(AH21,AJ21,AL21,AN21,AP21,AR21,AV21,AX21,AZ21,BB21,BD21,BF21,BH21) -> 0 | BN21: 720012795 | BO21: Alvin.Angeles@espire.com
A22: 45 | B22: 91 | C22: O | D22: Single | E22: 45600 | F22: Senior Security Analyst | G22: 85000 | H22: =G22/2 -> 42500 | I22: =G22*12/261 -> 3908.046 | J22: =I22/8 -> 488.50575 | L22: 2000 | M22: 500 | N22: 300 | AA22: =VLOOKUP(C22,Timesheet!D:DD,99,0)/60 -> 0 | AB22: =AA22*J22 -> 0 | AC22: =VLOOKUP(C22,Timesheet!D:DD,104,0) -> 0 | AD22: =I22*AC22 -> 0 | AG22: =VLOOKUP(C22,Timesheet!D:DD,97,0) -> 12 | AH22: =(J22*AG22*125%)+((J22*AG22*10%)*25%) -> 7474.1379 | AI22: =VLOOKUP(C22,Timesheet!D:DD,100,0) -> 72 | AJ22: =J22*0.1*AI22 -> 3517.2414 | AK22: =VLOOKUP(C22,Timesheet!D:DD,98,0) -> 0 | AL22: =J22*1.3*AK22 -> 0 | AN22: =(J22*1.3*1.3)*AM22 -> 0 | AP22: =(J22*130%*10%)*AO22 -> 0 | AR22: =J22*1.3*AQ22 -> 0 | AV22: =(J22*0.3*0.1)*AU22 -> 0 | AW22: 0 | AX22: =(J22*0.3)*AW22 -> 0 | AY22: 0 | AZ22: =((J22*1.3)*1.3)*AY22 -> 0 | BA22: 0 | BB22: =((J22*0.3)*0.1)*BA22 -> 0 | BC22: =VLOOKUP(C22,Timesheet!D:DD,96,0) -> 0 | BD22: =J22*1*BC22 -> 0 | BG22: =VLOOKUP(C22,Timesheet!D:DD,101,0) -> 0 | BH22: =(J22*1*0.1)*BG22 -> 0 | BI22: =AH22+AJ22+AL22+AN22+AP22+AR22+AT22+AV22+AX22+AZ22+BB22+BD22+BF22+BH22 -> 10991.379 | BJ22: =-(AB22+AD22) -> 0 | BK22: =Timesheet!CT17 -> 72 | BL22: =BI22-SUM(AH22,AJ22,AL22,AN22,AP22,AR22,AV22,AX22,AZ22,BB22,BD22,BF22,BH22) -> 0 | BN22: 288391366 | BO22: james.morante@espire.com
A23: 46 | B23: 93 | C23: P | D23: Single | E23: 45600 | F23: Senior Security Analyst | G23: 130000 | H23: =G23/2 -> 65000 | I23: =G23*12/261 -> 5977.0115 | J23: =I23/8 -> 747.12644 | L23: 2000 | M23: 500 | N23: 300 | V23: 1845.8 | AA23: =VLOOKUP(C23,Timesheet!D:DD,99,0)/60 -> 0 | AB23: =AA23*J23 -> 0 | AC23: =VLOOKUP(C23,Timesheet!D:DD,104,0) -> 0 | AD23: =I23*AC23 -> 0 | AG23: =VLOOKUP(C23,Timesheet!D:DD,97,0) -> 6 | AH23: =(J23*AG23*125%)+((J23*AG23*10%)*25%) -> 5715.5172 | AI23: =VLOOKUP(C23,Timesheet!D:DD,100,0) -> 48 | AJ23: =J23*0.1*AI23 -> 3586.2069 | AK23: =VLOOKUP(C23,Timesheet!D:DD,98,0) -> 0 | AL23: =J23*1.3*AK23 -> 0 | AN23: =(J23*1.3*1.3)*AM23 -> 0 | AP23: =(J23*130%*10%)*AO23 -> 0 | AR23: =J23*1.3*AQ23 -> 0 | AV23: =(J23*0.3*0.1)*AU23 -> 0 | AW23: 0 | AX23: =(J23*0.3)*AW23 -> 0 | AY23: 0 | AZ23: =((J23*1.3)*1.3)*AY23 -> 0 | BA23: 0 | BB23: =((J23*0.3)*0.1)*BA23 -> 0 | BC23: =VLOOKUP(C23,Timesheet!D:DD,96,0) -> 0 | BD23: =J23*1*BC23 -> 0 | BG23: =VLOOKUP(C23,Timesheet!D:DD,101,0) -> 0 | BH23: =(J23*1*0.1)*BG23 -> 0 | BI23: =AH23+AJ23+AL23+AN23+AP23+AR23+AT23+AV23+AX23+AZ23+BB23+BD23+BF23+BH23 -> 9301.7241 | BJ23: =-(AB23+AD23) -> 0 | BK23: =Timesheet!CT18 -> 80 | BL23: =BI23-SUM(AH23,AJ23,AL23,AN23,AP23,AR23,AV23,AX23,AZ23,BB23,BD23,BF23,BH23) -> 0 | BN23: 307812652 | BO23: nathaniel.lindo@espire.com
A24: 47 | B24: 95 | C24: Q | D24: Single | E24: 45600 | F24: Service Desk Analyst L-1 | G24: 30000 | H24: =G24/2 -> 15000 | I24: =G24*12/261 -> 1379.3103 | J24: =I24/8 -> 172.41379 | L24: 2000 | M24: 500 | N24: 300 | AA24: =VLOOKUP(C24,Timesheet!D:DD,99,0)/60 -> 0 | AB24: =AA24*J24 -> 0 | AC24: =VLOOKUP(C24,Timesheet!D:DD,104,0) -> 1 | AD24: =I24*AC24 -> 1379.3103 | AG24: =VLOOKUP(C24,Timesheet!D:DD,97,0) -> 0 | AH24: =(J24*AG24*125%)+((J24*AG24*10%)*25%) -> 0 | AI24: =VLOOKUP(C24,Timesheet!D:DD,100,0) -> 14 | AJ24: =J24*0.1*AI24 -> 241.37931 | AK24: =VLOOKUP(C24,Timesheet!D:DD,98,0) -> 0 | AL24: =J24*1.3*AK24 -> 0 | AN24: =(J24*1.3*1.3)*AM24 -> 0 | AP24: =(J24*130%*10%)*AO24 -> 0 | AR24: =J24*1.3*AQ24 -> 0 | AV24: =(J24*0.3*0.1)*AU24 -> 0 | AW24: 0 | AX24: =(J24*0.3)*AW24 -> 0 | AY24: 0 | AZ24: =((J24*1.3)*1.3)*AY24 -> 0 | BA24: 0 | BB24: =((J24*0.3)*0.1)*BA24 -> 0 | BC24: =VLOOKUP(C24,Timesheet!D:DD,96,0) -> 8 | BD24: =J24*1*BC24 -> 1379.3103 | BG24: =VLOOKUP(C24,Timesheet!D:DD,101,0) -> 2 | BH24: =(J24*1*0.1)*BG24 -> 34.482759 | BI24: =AH24+AJ24+AL24+AN24+AP24+AR24+AT24+AV24+AX24+AZ24+BB24+BD24+BF24+BH24 -> 1655.1724 | BJ24: =-(AB24+AD24) -> -1379.3103 | BK24: =Timesheet!CT19 -> 56 | BL24: =BI24-SUM(AH24,AJ24,AL24,AN24,AP24,AR24,AV24,AX24,AZ24,BB24,BD24,BF24,BH24) -> 0 | BN24: 306005428 | BO24: maria.silva@espire.com
A25: 49 | B25: 99 | C25: R | D25: Single | E25: 45726 | F25: Service Desk Analyst L-1 | G25: 28000 | H25: =G25/2 -> 14000 | I25: =G25*12/261 -> 1287.3563 | J25: =I25/8 -> 160.91954 | L25: 2000 | M25: 500 | N25: 300 | AA25: =VLOOKUP(C25,Timesheet!D:DD,99,0)/60 -> 0 | AB25: =AA25*J25 -> 0 | AC25: =VLOOKUP(C25,Timesheet!D:DD,104,0) -> 0 | AD25: =I25*AC25 -> 0 | AG25: =VLOOKUP(C25,Timesheet!D:DD,97,0) -> 0 | AH25: =(J25*AG25*125%)+((J25*AG25*10%)*25%) -> 0 | AI25: =VLOOKUP(C25,Timesheet!D:DD,100,0) -> 20 | AJ25: =J25*0.1*AI25 -> 321.83908 | AK25: =VLOOKUP(C25,Timesheet!D:DD,98,0) -> 0 | AL25: =J25*1.3*AK25 -> 0 | AN25: =(J25*1.3*1.3)*AM25 -> 0 | AP25: =(J25*130%*10%)*AO25 -> 0 | AR25: =J25*1.3*AQ25 -> 0 | AV25: =(J25*0.3*0.1)*AU25 -> 0 | AW25: 0 | AX25: =(J25*0.3)*AW25 -> 0 | AY25: 0 | AZ25: =((J25*1.3)*1.3)*AY25 -> 0 | BA25: 0 | BB25: =((J25*0.3)*0.1)*BA25 -> 0 | BC25: =VLOOKUP(C25,Timesheet!D:DD,96,0) -> 0 | BD25: =J25*1*BC25 -> 0 | BG25: =VLOOKUP(C25,Timesheet!D:DD,101,0) -> 0 | BH25: =(J25*1*0.1)*BG25 -> 0 | BI25: =AH25+AJ25+AL25+AN25+AP25+AR25+AT25+AV25+AX25+AZ25+BB25+BD25+BF25+BH25 -> 321.83908 | BJ25: =-(AB25+AD25) -> 0 | BK25: =Timesheet!CT20 -> 80 | BL25: =BI25-SUM(AH25,AJ25,AL25,AN25,AP25,AR25,AV25,AX25,AZ25,BB25,BD25,BF25,BH25) -> 0 | BN25: 398029807 | BO25: john.espino@espire.com
A26: 50 | B26: 101 | C26: S | D26: Single | E26: 45775 | F26: Senior Security Analyst | G26: 85000 | H26: =G26/2 -> 42500 | I26: =G26*12/261 -> 3908.046 | J26: =I26/8 -> 488.50575 | L26: 2000 | M26: 500 | N26: 300 | V26: 1809.09 | AA26: =VLOOKUP(C26,Timesheet!D:DD,99,0)/60 -> 0 | AB26: =AA26*J26 -> 0 | AC26: =VLOOKUP(C26,Timesheet!D:DD,104,0) -> 0 | AD26: =I26*AC26 -> 0 | AG26: =VLOOKUP(C26,Timesheet!D:DD,97,0) -> 6 | AH26: =(J26*AG26*125%)+((J26*AG26*10%)*25%) -> 3737.069 | AI26: =VLOOKUP(C26,Timesheet!D:DD,100,0) -> 32 | AJ26: =J26*0.1*AI26 -> 1563.2184 | AK26: =VLOOKUP(C26,Timesheet!D:DD,98,0) -> 0 | AL26: =J26*1.3*AK26 -> 0 | AN26: =(J26*1.3*1.3)*AM26 -> 0 | AP26: =(J26*130%*10%)*AO26 -> 0 | AR26: =J26*1.3*AQ26 -> 0 | AV26: =(J26*0.3*0.1)*AU26 -> 0 | AW26: 0 | AX26: =(J26*0.3)*AW26 -> 0 | AY26: 0 | AZ26: =((J26*1.3)*1.3)*AY26 -> 0 | BA26: 0 | BB26: =((J26*0.3)*0.1)*BA26 -> 0 | BC26: =VLOOKUP(C26,Timesheet!D:DD,96,0) -> 0 | BD26: =J26*1*BC26 -> 0 | BG26: =VLOOKUP(C26,Timesheet!D:DD,101,0) -> 0 | BH26: =(J26*1*0.1)*BG26 -> 0 | BI26: =AH26+AJ26+AL26+AN26+AP26+AR26+AT26+AV26+AX26+AZ26+BB26+BD26+BF26+BH26 -> 5300.2874 | BJ26: =-(AB26+AD26) -> 0 | BK26: =Timesheet!CT21 -> 72 | BL26: =BI26-SUM(AH26,AJ26,AL26,AN26,AP26,AR26,AV26,AX26,AZ26,BB26,BD26,BF26,BH26) -> 0 | BN26: 338342591 | BO26: paul.austria@espire.com
A27: 51 | B27: 103 | C27: T | D27: Single | E27: 45777 | F27: Service Desk Analyst L-1 | G27: 22000 | H27: =G27/2 -> 11000 | I27: =G27*12/261 -> 1011.4943 | J27: =I27/8 -> 126.43678 | L27: 2000 | M27: 500 | N27: 300 | AA27: =VLOOKUP(C27,Timesheet!D:DD,99,0)/60 -> 2 | AB27: =AA27*J27 -> 252.87356 | AC27: =VLOOKUP(C27,Timesheet!D:DD,104,0) -> 0 | AD27: =I27*AC27 -> 0 | AG27: =VLOOKUP(C27,Timesheet!D:DD,97,0) -> 0 | AH27: =(J27*AG27*125%)+((J27*AG27*10%)*25%) -> 0 | AI27: =VLOOKUP(C27,Timesheet!D:DD,100,0) -> 22 | AJ27: =J27*0.1*AI27 -> 278.16092 | AK27: =VLOOKUP(C27,Timesheet!D:DD,98,0) -> 0 | AL27: =J27*1.3*AK27 -> 0 | AN27: =(J27*1.3*1.3)*AM27 -> 0 | AP27: =(J27*130%*10%)*AO27 -> 0 | AR27: =J27*1.3*AQ27 -> 0 | AV27: =(J27*0.3*0.1)*AU27 -> 0 | AW27: 0 | AX27: =(J27*0.3)*AW27 -> 0 | AY27: 0 | AZ27: =((J27*1.3)*1.3)*AY27 -> 0 | BA27: 0 | BB27: =((J27*0.3)*0.1)*BA27 -> 0 | BC27: =VLOOKUP(C27,Timesheet!D:DD,96,0) -> 8 | BD27: =J27*1*BC27 -> 1011.4943 | BG27: =VLOOKUP(C27,Timesheet!D:DD,101,0) -> 2 | BH27: =(J27*1*0.1)*BG27 -> 25.287356 | BI27: =AH27+AJ27+AL27+AN27+AP27+AR27+AT27+AV27+AX27+AZ27+BB27+BD27+BF27+BH27 -> 1314.9425 | BJ27: =-(AB27+AD27) -> -252.87356 | BK27: =Timesheet!CT22 -> 68 | BL27: =BI27-SUM(AH27,AJ27,AL27,AN27,AP27,AR27,AV27,AX27,AZ27,BB27,BD27,BF27,BH27) -> 0 | BN27: 457949341 | BO27: gustav.cruz@espire.com
A28: 52 | B28: 105 | C28: U | D28: Single | E28: 45817 | F28: Service Desk Analyst L-1 | G28: 18000 | H28: =G28/2 -> 9000 | I28: =G28*12/261 -> 827.58621 | J28: =I28/8 -> 103.44828 | L28: 2000 | M28: 500 | N28: 300 | AA28: =VLOOKUP(C28,Timesheet!D:DD,99,0)/60 -> 0 | AB28: =AA28*J28 -> 0 | AC28: =VLOOKUP(C28,Timesheet!D:DD,104,0) -> 0 | AD28: =I28*AC28 -> 0 | AG28: =VLOOKUP(C28,Timesheet!D:DD,97,0) -> 0 | AH28: =(J28*AG28*125%)+((J28*AG28*10%)*25%) -> 0 | AI28: =VLOOKUP(C28,Timesheet!D:DD,100,0) -> 20 | AJ28: =J28*0.1*AI28 -> 206.89655 | AK28: =VLOOKUP(C28,Timesheet!D:DD,98,0) -> 0 | AL28: =J28*1.3*AK28 -> 0 | AN28: =(J28*1.3*1.3)*AM28 -> 0 | AP28: =(J28*130%*10%)*AO28 -> 0 | AR28: =J28*1.3*AQ28 -> 0 | AV28: =(J28*0.3*0.1)*AU28 -> 0 | AW28: 0 | AX28: =(J28*0.3)*AW28 -> 0 | AY28: 0 | AZ28: =((J28*1.3)*1.3)*AY28 -> 0 | BA28: 0 | BB28: =((J28*0.3)*0.1)*BA28 -> 0 | BC28: =VLOOKUP(C28,Timesheet!D:DD,96,0) -> 8 | BD28: =J28*1*BC28 -> 827.58621 | BG28: =VLOOKUP(C28,Timesheet!D:DD,101,0) -> 2 | BH28: =(J28*1*0.1)*BG28 -> 20.689655 | BI28: =AH28+AJ28+AL28+AN28+AP28+AR28+AT28+AV28+AX28+AZ28+BB28+BD28+BF28+BH28 -> 1055.1724 | BJ28: =-(AB28+AD28) -> 0 | BK28: =Timesheet!CT23 -> 80 | BL28: =BI28-SUM(AH28,AJ28,AL28,AN28,AP28,AR28,AV28,AX28,AZ28,BB28,BD28,BF28,BH28) -> 0 | BN28: 121366114074 | BO28: nealle.magnaye@espire.com
AB29: =AA29*J29 -> 0 | AD29: =I29*AC29 -> 0 | AH29: =(J29*AG29*125%)+((J29*AG29*10%)*25%) -> 0 | AJ29: =J29*0.1*AI29 -> 0 | AL29: =J29*1.3*AK29 -> 0 | AP29: =(J29*130%*10%)*AO29 -> 0 | AR29: =J29*1.3*AQ29 -> 0 | AV29: =(J29*0.3*0.1)*AU29 -> 0 | AX29: =(J29*0.3)*AW29 -> 0 | AZ29: =((J29*1.3)*1.3)*AY29 -> 0 | BB29: =((J29*0.3)*0.1)*BA29 -> 0 | BD29: =J29*1*BC29 -> 0 | BH29: =(J29*1*0.1)*BG29 -> 0 | BI29: =AH29+AJ29+AL29+AN29+AP29+AR29+AT29+AV29+AX29+AZ29+BB29+BD29+BF29+BH29 -> 0 | BJ29: =-(AB29+AD29) -> 0 | BK29: =Timesheet!CT24 -> 0 | BL29: =BI29-SUM(AH29,AJ29,AL29,AN29,AP29,AR29,AV29,AX29,AZ29,BB29,BD29,BF29,BH29) -> 0
C30: TOTAL | G30: =SUM(G8:G29) -> 1596217 | H30: =SUM(H8:H29) -> 798108.5 | I30: =SUM(I8:I29) -> 73389.287 | J30: =SUM(J8:J29) -> 9173.6609 | K30: =SUM(K8:K29) -> 0 | L30: =SUM(L8:L29) -> 39560 | M30: =SUM(M8:M29) -> 9100 | N30: =SUM(N8:N29) -> 5400 | ... AD30: =SUM(AD8:AD29) -> 15560.828 | AE30: 14856.897 | AF30: =SUM(AF8:AF29) -> 0 | AG30: =SUM(AG8:AG29) -> 57 | AH30: =SUM(AH8:AH29) -> 25719.828 | AI30: =SUM(AI8:AI29) -> 565 | AJ30: =SUM(AJ8:AJ29) -> 19578.051 | AK30: =SUM(AK8:AK29) -> 6 | AL30: =SUM(AL8:AL29) -> 1176.7241 | AM30: =SUM(AM8:AM29) -> 0 | ... BK30: =SUM(BK8:BK29) -> 1531
AA32: =AA30*60-Timesheet!CX25 -> 0 | AC32: =AC30-Timesheet!DC25 -> 0 | AG32: =AG30-Timesheet!CV25 -> 0 | AI32: =AI30-Timesheet!CY25 -> 0 | AK32: =AK30-Timesheet!CW25 -> 0 | BC32: =BC30-Timesheet!CU25 -> 0 | BG32: =BG30-Timesheet!CZ25 -> 0 | BK32: =BK30-Timesheet!CT25 -> 0

Sheet 2025 SSS Table
A2: RANGE OF COMPENSATION | C2: MONTHLY SALARY CREDIT | F2: AMOUNT OF CONTRIBUTIONS
C3: REGULAR SOCIAL SECURITY | D3: MANDATORY PROVIDENT FUND | E3: TOTAL | F3: REGULAR SOCIAL SECURITY | I3: EMPLOYEE CONTRIBUTION | L3: MANDATORY PROVIDENT FUND | O3: TOTAL
C4: EMPLOYEES' COMPENSATION | F4: ER | G4: EE | H4: TOTAL | I4: ER | J4: EE | K4: TOTAL | L4: ER | M4: EE | N4: TOTAL | O4: ER | P4: EE | Q4: TOTAL
A5: 0 | B5: =A6-0.01 -> 5249.99 | C5: 5000 | D5: 0 | E5: 5000 | F5: =E5*0.1 -> 500 | G5: =E5*0.05 -> 250 | H5: =F5+G5 -> 750 | I5: 10 | J5: 0 | K5: =I5+J5 -> 10 | L5: 0 | M5: 0 | N5: =SUM(L5:M5) -> 0 | O5: =F5+I5+L5 -> 510 | P5: =G5+J5+M5 -> 250 | Q5: =SUM(O5:P5) -> 760
A6: 5250 | B6: =A7-0.01 -> 5749.99 | C6: =C5+500 -> 5500 | D6: 0 | E6: =E5+500 -> 5500 | F6: =E6*0.1 -> 550 | G6: =E6*0.05 -> 275 | H6: =F6+G6 -> 825 | I6: 10 | J6: 0 | K6: =I6+J6 -> 10 | L6: 0 | M6: 0 | N6: =SUM(L6:M6) -> 0 | O6: =F6+I6+L6 -> 560 | P6: =G6+J6+M6 -> 275 | Q6: =SUM(O6:P6) -> 835
A7: =A6+500 -> 5750 | B7: =A8-0.01 -> 6249.99 | C7: =C6+500 -> 6000 | D7: 0 | E7: =E6+500 -> 6000 | F7: =E7*0.1 -> 600 | G7: =E7*0.05 -> 300 | H7: =F7+G7 -> 900 | I7: 10 | J7: 0 | K7: =I7+J7 -> 10 | L7: 0 | M7: 0 | N7: =SUM(L7:M7) -> 0 | O7: =F7+I7+L7 -> 610 | P7: =G7+J7+M7 -> 300 | Q7: =SUM(O7:P7) -> 910
A8: =A7+500 -> 6250 | B8: =A9-0.01 -> 6749.99 | C8: =C7+500 -> 6500 | D8: 0 | E8: =E7+500 -> 6500 | F8: =E8*0.1 -> 650 | G8: =E8*0.05 -> 325 | H8: =F8+G8 -> 975 | I8: 10 | J8: 0 | K8: =I8+J8 -> 10 | L8: 0 | M8: 0 | N8: =SUM(L8:M8) -> 0 | O8: =F8+I8+L8 -> 660 | P8: =G8+J8+M8 -> 325 | Q8: =SUM(O8:P8) -> 985
A9: =A8+500 -> 6750 | B9: =A10-0.01 -> 7249.99 | C9: =C8+500 -> 7000 | D9: 0 | E9: =E8+500 -> 7000 | F9: =E9*0.1 -> 700 | G9: =E9*0.05 -> 350 | H9: =F9+G9 -> 1050 | I9: 10 | J9: 0 | K9: =I9+J9 -> 10 | L9: 0 | M9: 0 | N9: =SUM(L9:M9) -> 0 | O9: =F9+I9+L9 -> 710 | P9: =G9+J9+M9 -> 350 | Q9: =SUM(O9:P9) -> 1060
A10: =A9+500 -> 7250 | B10: =A11-0.01 -> 7749.99 | C10: =C9+500 -> 7500 | D10: 0 | E10: =E9+500 -> 7500 | F10: =E10*0.1 -> 750 | G10: =E10*0.05 -> 375 | H10: =F10+G10 -> 1125 | I10: 10 | J10: 0 | K10: =I10+J10 -> 10 | L10: 0 | M10: 0 | N10: =SUM(L10:M10) -> 0 | O10: =F10+I10+L10 -> 760 | P10: =G10+J10+M10 -> 375 | Q10: =SUM(O10:P10) -> 1135
A11: =A10+500 -> 7750 | B11: =A12-0.01 -> 8249.99 | C11: =C10+500 -> 8000 | D11: 0 | E11: =E10+500 -> 8000 | F11: =E11*0.1 -> 800 | G11: =E11*0.05 -> 400 | H11: =F11+G11 -> 1200 | I11: 10 | J11: 0 | K11: =I11+J11 -> 10 | L11: 0 | M11: 0 | N11: =SUM(L11:M11) -> 0 | O11: =F11+I11+L11 -> 810 | P11: =G11+J11+M11 -> 400 | Q11: =SUM(O11:P11) -> 1210
A12: =A11+500 -> 8250 | B12: =A13-0.01 -> 8749.99 | C12: =C11+500 -> 8500 | D12: 0 | E12: =E11+500 -> 8500 | F12: =E12*0.1 -> 850 | G12: =E12*0.05 -> 425 | H12: =F12+G12 -> 1275 | I12: 10 | J12: 0 | K12: =I12+J12 -> 10 | L12: 0 | M12: 0 | N12: =SUM(L12:M12) -> 0 | O12: =F12+I12+L12 -> 860 | P12: =G12+J12+M12 -> 425 | Q12: =SUM(O12:P12) -> 1285
A13: =A12+500 -> 8750 | B13: =A14-0.01 -> 9249.99 | C13: =C12+500 -> 9000 | D13: 0 | E13: =E12+500 -> 9000 | F13: =E13*0.1 -> 900 | G13: =E13*0.05 -> 450 | H13: =F13+G13 -> 1350 | I13: 10 | J13: 0 | K13: =I13+J13 -> 10 | L13: 0 | M13: 0 | N13: =SUM(L13:M13) -> 0 | O13: =F13+I13+L13 -> 910 | P13: =G13+J13+M13 -> 450 | Q13: =SUM(O13:P13) -> 1360
A14: =A13+500 -> 9250 | B14: =A15-0.01 -> 9749.99 | C14: =C13+500 -> 9500 | D14: 0 | E14: =E13+500 -> 9500 | F14: =E14*0.1 -> 950 | G14: =E14*0.05 -> 475 | H14: =F14+G14 -> 1425 | I14: 10 | J14: 0 | K14: =I14+J14 -> 10 | L14: 0 | M14: 0 | N14: =SUM(L14:M14) -> 0 | O14: =F14+I14+L14 -> 960 | P14: =G14+J14+M14 -> 475 | Q14: =SUM(O14:P14) -> 1435
A15: =A14+500 -> 9750 | B15: =A16-0.01 -> 10249.99 | C15: =C14+500 -> 10000 | D15: 0 | E15: =E14+500 -> 10000 | F15: =E15*0.1 -> 1000 | G15: =E15*0.05 -> 500 | H15: =F15+G15 -> 1500 | I15: 10 | J15: 0 | K15: =I15+J15 -> 10 | L15: 0 | M15: 0 | N15: =SUM(L15:M15) -> 0 | O15: =F15+I15+L15 -> 1010 | P15: =G15+J15+M15 -> 500 | Q15: =SUM(O15:P15) -> 1510
A16: =A15+500 -> 10250 | B16: =A17-0.01 -> 10749.99 | C16: =C15+500 -> 10500 | D16: 0 | E16: =E15+500 -> 10500 | F16: =E16*0.1 -> 1050 | G16: =E16*0.05 -> 525 | H16: =F16+G16 -> 1575 | I16: 10 | J16: 0 | K16: =I16+J16 -> 10 | L16: 0 | M16: 0 | N16: =SUM(L16:M16) -> 0 | O16: =F16+I16+L16 -> 1060 | P16: =G16+J16+M16 -> 525 | Q16: =SUM(O16:P16) -> 1585
A17: =A16+500 -> 10750 | B17: =A18-0.01 -> 11249.99 | C17: =C16+500 -> 11000 | D17: 0 | E17: =E16+500 -> 11000 | F17: =E17*0.1 -> 1100 | G17: =E17*0.05 -> 550 | H17: =F17+G17 -> 1650 | I17: 10 | J17: 0 | K17: =I17+J17 -> 10 | L17: 0 | M17: 0 | N17: =SUM(L17:M17) -> 0 | O17: =F17+I17+L17 -> 1110 | P17: =G17+J17+M17 -> 550 | Q17: =SUM(O17:P17) -> 1660
A18: =A17+500 -> 11250 | B18: =A19-0.01 -> 11749.99 | C18: =C17+500 -> 11500 | D18: 0 | E18: =E17+500 -> 11500 | F18: =E18*0.1 -> 1150 | G18: =E18*0.05 -> 575 | H18: =F18+G18 -> 1725 | I18: 10 | J18: 0 | K18: =I18+J18 -> 10 | L18: 0 | M18: 0 | N18: =SUM(L18:M18) -> 0 | O18: =F18+I18+L18 -> 1160 | P18: =G18+J18+M18 -> 575 | Q18: =SUM(O18:P18) -> 1735
... A35: =A34+500 -> 19750 | B35: =A36-0.01 -> 20249.99 | C35: =C34+500 -> 20000 | D35: 0 | E35: =E34+500 -> 20000 | F35: =E35*0.1 -> 2000 | G35: =E35*0.05 -> 1000 | H35: =F35+G35 -> 3000 | I35: 30 | J35: 0 | K35: =I35+J35 -> 30 | L35: 0 | M35: 0 | N35: =SUM(L35:M35) -> 0 | O35: =F35+I35+L35 -> 2030 | P35: =G35+J35+M35 -> 1000 | Q35: =SUM(O35:P35) -> 3030
A36: =A35+500 -> 20250 | B36: =A37-0.01 -> 20749.99 | C36: =C35 -> 20000 | D36: 500 | E36: =E35+500 -> 20500 | F36: =F35 -> 2000 | G36: =E36*0.05 -> 1025 | H36: =F36+G36 -> 3025 | I36: 30 | J36: 0 | K36: =I36+J36 -> 30 | L36: 50 | M36: 25 | N36: =SUM(L36:M36) -> 75 | O36: =F36+I36+L36 -> 2080 | P36: =G36+J36+M36 -> 1050 | Q36: =SUM(O36:P36) -> 3130
A37: =A36+500 -> 20750 | B37: =A38-0.01 -> 21249.99 | C37: =C36 -> 20000 | D37: =D36+500 -> 1000 | E37: =E36+500 -> 21000 | F37: =F36 -> 2000 | G37: 1000 | H37: =F37+G37 -> 3000 | I37: 30 | J37: 0 | K37: =I37+J37 -> 30 | L37: =L36+50 -> 100 | M37: =M36+25 -> 50 | N37: =SUM(L37:M37) -> 150 | O37: =F37+I37+L37 -> 2130 | P37: =G37+J37+M37 -> 1050 | Q37: =SUM(O37:P37) -> 3180
A38: =A37+500 -> 21250 | B38: =A39-0.01 -> 21749.99 | C38: =C37 -> 20000 | D38: =D37+500 -> 1500 | E38: =E37+500 -> 21500 | F38: =F37 -> 2000 | G38: =G37 -> 1000 | H38: =F38+G38 -> 3000 | I38: 30 | J38: 0 | K38: =I38+J38 -> 30 | L38: =L37+50 -> 150 | M38: =M37+25 -> 75 | N38: 70 | O38: =F38+I38+L38 -> 2180 | P38: =G38+J38+M38 -> 1075 | Q38: =SUM(O38:P38) -> 3255
A39: =A38+500 -> 21750 | B39: =A40-0.01 -> 22249.99 | C39: =C38 -> 20000 | D39: =D38+500 -> 2000 | E39: =E38+500 -> 22000 | F39: =F38 -> 2000 | G39: =G38 -> 1000 | H39: =F39+G39 -> 3000 | I39: 30 | J39: 0 | K39: =I39+J39 -> 30 | L39: =L38+50 -> 200 | M39: =M38+25 -> 100 | N39: =N38+70 -> 140 | O39: =F39+I39+L39 -> 2230 | P39: =G39+J39+M39 -> 1100 | Q39: =SUM(O39:P39) -> 3330
A40: =A39+500 -> 22250 | B40: =A41-0.01 -> 22749.99 | C40: =C39 -> 20000 | D40: =D39+500 -> 2500 | E40: =E39+500 -> 22500 | F40: =F39 -> 2000 | G40: =G39 -> 1000 | H40: =F40+G40 -> 3000 | I40: 30 | J40: 0 | K40: =I40+J40 -> 30 | L40: =L39+50 -> 250 | M40: =M39+25 -> 125 | N40: =N39+70 -> 210 | O40: =F40+I40+L40 -> 2280 | P40: =G40+J40+M40 -> 1125 | Q40: =SUM(O40:P40) -> 3405
A41: =A40+500 -> 22750 | B41: =A42-0.01 -> 23249.99 | C41: =C40 -> 20000 | D41: =D40+500 -> 3000 | E41: =E40+500 -> 23000 | F41: =F40 -> 2000 | G41: =G40 -> 1000 | H41: =F41+G41 -> 3000 | I41: 30 | J41: 0 | K41: =I41+J41 -> 30 | L41: =L40+50 -> 300 | M41: =M40+25 -> 150 | N41: =N40+70 -> 280 | O41: =F41+I41+L41 -> 2330 | P41: =G41+J41+M41 -> 1150 | Q41: =SUM(O41:P41) -> 3480
A42: =A41+500 -> 23250 | B42: =A43-0.01 -> 23749.99 | C42: =C41 -> 20000 | D42: =D41+500 -> 3500 | E42: =E41+500 -> 23500 | F42: =F41 -> 2000 | G42: =G41 -> 1000 | H42: =F42+G42 -> 3000 | I42: 30 | J42: 0 | K42: =I42+J42 -> 30 | L42: =L41+50 -> 350 | M42: =M41+25 -> 175 | N42: =N41+70 -> 350 | O42: =F42+I42+L42 -> 2380 | P42: =G42+J42+M42 -> 1175 | Q42: =SUM(O42:P42) -> 3555
A43: =A42+500 -> 23750 | B43: =A44-0.01 -> 24249.99 | C43: =C42 -> 20000 | D43: =D42+500 -> 4000 | E43: =E42+500 -> 24000 | F43: =F42 -> 2000 | G43: =G42 -> 1000 | H43: =F43+G43 -> 3000 | I43: 30 | J43: 0 | K43: =I43+J43 -> 30 | L43: =L42+50 -> 400 | M43: =M42+25 -> 200 | N43: =N42+70 -> 420 | O43: =F43+I43+L43 -> 2430 | P43: =G43+J43+M43 -> 1200 | Q43: =SUM(O43:P43) -> 3630
A44: =A43+500 -> 24250 | B44: =A45-0.01 -> 24749.99 | C44: =C43 -> 20000 | D44: =D43+500 -> 4500 | E44: =E43+500 -> 24500 | F44: =F43 -> 2000 | G44: =G43 -> 1000 | H44: =F44+G44 -> 3000 | I44: 30 | J44: 0 | K44: =I44+J44 -> 30 | L44: =L43+50 -> 450 | M44: =M43+25 -> 225 | N44: =N43+70 -> 490 | O44: =F44+I44+L44 -> 2480 | P44: =G44+J44+M44 -> 1225 | Q44: =SUM(O44:P44) -> 3705
A45: =A44+500 -> 24750 | B45: =A46-0.01 -> 25249.99 | C45: =C44 -> 20000 | D45: =D44+500 -> 5000 | E45: =E44+500 -> 25000 | F45: =F44 -> 2000 | G45: =G44 -> 1000 | H45: =F45+G45 -> 3000 | I45: 30 | J45: 0 | K45: =I45+J45 -> 30 | L45: =L44+50 -> 500 | M45: =M44+25 -> 250 | N45: =N44+70 -> 560 | O45: =F45+I45+L45 -> 2530 | P45: =G45+J45+M45 -> 1250 | Q45: =SUM(O45:P45) -> 3780
A46: =A45+500 -> 25250 | B46: =A47-0.01 -> 25749.99 | C46: =C45 -> 20000 | D46: =D45+500 -> 5500 | E46: =E45+500 -> 25500 | F46: =F45 -> 2000 | G46: =G45 -> 1000 | H46: =F46+G46 -> 3000 | I46: 30 | J46: 0 | K46: =I46+J46 -> 30 | L46: =L45+50 -> 550 | M46: =M45+25 -> 275 | N46: =N45+70 -> 630 | O46: =F46+I46+L46 -> 2580 | P46: =G46+J46+M46 -> 1275 | Q46: =SUM(O46:P46) -> 3855
A47: =A46+500 -> 25750 | B47: =A48-0.01 -> 26249.99 | C47: =C46 -> 20000 | D47: =D46+500 -> 6000 | E47: =E46+500 -> 26000 | F47: =F46 -> 2000 | G47: =G46 -> 1000 | H47: =F47+G47 -> 3000 | I47: 30 | J47: 0 | K47: =I47+J47 -> 30 | L47: =L46+50 -> 600 | M47: =M46+25 -> 300 | N47: =N46+70 -> 700 | O47: =F47+I47+L47 -> 2630 | P47: =G47+J47+M47 -> 1300 | Q47: =SUM(O47:P47) -> 3930
A48: =A47+500 -> 26250 | B48: =A49-0.01 -> 26749.99 | C48: =C47 -> 20000 | D48: =D47+500 -> 6500 | E48: =E47+500 -> 26500 | F48: =F47 -> 2000 | G48: =G47 -> 1000 | H48: =F48+G48 -> 3000 | I48: 30 | J48: 0 | K48: =I48+J48 -> 30 | L48: =L47+50 -> 650 | M48: =M47+25 -> 325 | N48: =N47+70 -> 770 | O48: =F48+I48+L48 -> 2680 | P48: =G48+J48+M48 -> 1325 | Q48: =SUM(O48:P48) -> 4005
A49: =A48+500 -> 26750 | B49: =A50-0.01 -> 27249.99 | C49: =C48 -> 20000 | D49: =D48+500 -> 7000 | E49: =E48+500 -> 27000 | F49: =F48 -> 2000 | G49: =G48 -> 1000 | H49: =F49+G49 -> 3000 | I49: 30 | J49: 0 | K49: =I49+J49 -> 30 | L49: =L48+50 -> 700 | M49: =M48+25 -> 350 | N49: =N48+70 -> 840 | O49: =F49+I49+L49 -> 2730 | P49: =G49+J49+M49 -> 1350 | Q49: =SUM(O49:P49) -> 4080
A50: =A49+500 -> 27250 | B50: =A51-0.01 -> 27749.99 | C50: =C49 -> 20000 | D50: =D49+500 -> 7500 | E50: =E49+500 -> 27500 | F50: =F49 -> 2000 | G50: =G49 -> 1000 | H50: =F50+G50 -> 3000 | I50: 30 | J50: 0 | K50: =I50+J50 -> 30 | L50: =L49+50 -> 750 | M50: =M49+25 -> 375 | N50: =N49+70 -> 910 | O50: =F50+I50+L50 -> 2780 | P50: =G50+J50+M50 -> 1375 | Q50: =SUM(O50:P50) -> 4155
... A64: =A63+500 -> 34250 | B64: =A65-0.01 -> 34749.99 | C64: =C63 -> 20000 | D64: =D63+500 -> 14500 | E64: =E63+500 -> 34500 | F64: =F63 -> 2000 | G64: =G63 -> 1000 | H64: =F64+G64 -> 3000 | I64: 30 | J64: 0 | K64: =I64+J64 -> 30 | L64: =L63+50 -> 1450 | M64: =M63+25 -> 725 | N64: =N63+70 -> 1890 | O64: =F64+I64+L64 -> 3480 | P64: =G64+J64+M64 -> 1725 | Q64: =SUM(O64:P64) -> 5205
A65: =A64+500 -> 34750 | B65: OVER | C65: =C64 -> 20000 | D65: =D64+500 -> 15000 | E65: =E64+500 -> 35000 | F65: =F64 -> 2000 | G65: =G64 -> 1000 | H65: =F65+G65 -> 3000 | I65: 30 | J65: 0 | K65: =I65+J65 -> 30 | L65: =L64+50 -> 1500 | M65: =M64+25 -> 750 | N65: =N64+70 -> 1960 | O65: =F65+I65+L65 -> 3530 | P65: =G65+J65+M65 -> 1750 | Q65: =SUM(O65:P65) -> 5280

Sheet WTAX
D1: SEMI-MONTHLY
D2: 1 | E2: 0 | F2: 0 | G2: 0
D3: 2 | E3: 10417 | F3: 0.15 | G3: 0 | N3: 1 | O3: 3
D4: 3 | E4: 16667 | F4: 0.2 | G4: 937.5 | N4: 2 | O4: 5
D5: 4 | E5: 33333 | F5: 0.25 | G5: 4270.7 | N5: 3 | O5: 7
D6: 5 | E6: 83333 | F6: 0.3 | G6: 16770.7 | N6: 4 | O6: 9
D7: 6 | E7: 333333 | F7: 0.35 | G7: 91770 | N7: 5 | O7: 11
N8: 6 | O8: 13
N9: 7 | O9: 15
N10: 8 | O10: 17
N11: 9 | O11: 19
N12: 10 | O12: 21
N13: 11 | O13: 23
N14: 12 | O14: 25
N15: 13 | O15: 27
N16: 14 | O16: 29
N17: 15 | O17: 31
N18: 16 | O18: 33
N19: 17 | O19: 35
... N102: 100 | O102: 201

Sheet PHIC
C5: Bracket Salary | D5: Salary Range | G5: Salary Base | H5: Employee Share | I5: Employer Share | J5: Total Monthly Premium
C6: 1
C7: 2 | D7: 8999.99 | E7: - | F7: 8999.99 | G7: 8000 | H7: 100 | I7: 100 | J7: 200
C8: 3 | D8: 9000 | E8: - | F8: 9999.99 | G8: 9000 | H8: 112.5 | I8: 112.5 | J8: 225
C9: 4 | D9: 10000 | E9: - | F9: 10999.99 | G9: 10000 | H9: 125 | I9: 125 | J9: 250
C10: 5 | D10: 11000 | E10: - | F10: 11999.99 | G10: 11000 | H10: 137.5 | I10: 137.5 | J10: 275
C11: 6 | D11: 12000 | E11: - | F11: 12999.99 | G11: 12000 | H11: 150 | I11: 150 | J11: 300
C12: 7 | D12: 13000 | E12: - | F12: 13999.99 | G12: 13000 | H12: 162.5 | I12: 162.5 | J12: 325
C13: 8 | D13: 14000 | E13: - | F13: 14999.99 | G13: 14000 | H13: 175 | I13: 175 | J13: 350
C14: 9 | D14: 15000 | E14: - | F14: 15999.99 | G14: 15000 | H14: 187.5 | I14: 187.5 | J14: 375
C15: 10 | D15: 16000 | E15: - | F15: 16999.99 | G15: 16000 | H15: 200 | I15: 200 | J15: 400
C16: 11 | D16: 17000 | E16: - | F16: 17999.99 | G16: 17000 | H16: 212.5 | I16: 212.5 | J16: 425
C17: 12 | D17: 18000 | E17: - | F17: 18999.99 | G17: 18000 | H17: 225 | I17: 225 | J17: 450
C18: 13 | D18: 19000 | E18: - | F18: 19999.99 | G18: 19000 | H18: 237.5 | I18: 237.5 | J18: 475
... C33: 28 | D33: 34000 | E33: - | F33: 34999.99 | G33: 34000 | H33: 425 | I33: 425 | J33: 850
C34: 29 | D34: 35000 | E34: - | G34: 35000 | H34: 437.5 | I34: 437.5 | J34: 875

Sheet Albert Ato
C3: Should be:
D4: 1st Half | E4: 2nd Half | F4: TOTAL
C5: Basic Pay | D5: 12674.34 | E5: 12674.34 | F5: =SUM(D5:E5) -> 25348.68
C6: Transportation | D6: 4587.963 | E6: 5872.1472 | F6: =SUM(D6:E6) -> 10460.11
C7: De Minimis | D7: 5689.165 | E7: 5689.165 | F7: =SUM(D7:E7) -> 11378.33
C8: SSS | E8: -1125 | F8: =SUM(D8:E8) -> -1125
C9: PHIC | E9: -380.2302 | F9: =SUM(D9:E9) -> -380.2302 | H9: 875 | I9: =E9+H9 -> 494.7698
C10: HDMF | E10: -100 | F10: =SUM(D10:E10) -> -100
C11: W/tax | D11: -451.468 | E11: -130.42196 | F11: =SUM(D11:E11) -> -581.88996 | H11: 638.7 | I11: =E11+H11 -> 508.27804
C12: Total | D12: =SUM(D5:D11) -> 22500 | E12: =SUM(E5:E11) -> 22500 | F12: =SUM(F5:F11) -> 45000
E13: =D12-E12 -> 0
E14: 8463.7 | I14: =SUM(I9:I11) -> 1003.0478
